{"p": {"msgId": "396321", "id": "26329", "rnds": [{"n": "1", "holes": [{"n": "1", "cNum": "10", "sc": "4", "pDay": "-1", "pTot": "-1", "shots": [{"n": "1", "pid": "0", "time": "", "putt": "", "t": "S", "prv": "n", "tee": "y", "cup": "n", "from": "OTB", "to": "OIR", "asc": "1", "dist": "0", "left": "0", "x": "0", "y": "0", "z": "0", "club": "CDR", "con": "", "shotText": "Shot 1 from the tee box"}, {"n": "2", "pid": "0", "time": "", "putt": "", "t": "S", "prv": "n", "tee": "n", "cup": "n", "from": "OIR", "to": "OGR", "asc": "1", "dist": "0", "left": "0", "x": "0", "y": "0", "z": "0", "club": "CUK", "con": "", "shotText": "Shot 2 from the intermediate rough"}, {"n": "3", "pid": "0", "time": "", "putt": "1", "t": "S", "prv": "n", "tee": "n", "cup": "n", "from": "OGR", "to": "OGR", "asc": "1", "dist": "0", "left": "0", "x": "0", "y": "0", "z": "0", "club": "CUK", "con": "", "shotText": "Shot 3 from the green"}, {"n": "4", "pid": "0", "time": "", "putt": "2", "t": "S", "prv": "n", "tee": "n", "cup": "y", "from": "OGR", "to": "hole", "asc": "1", "dist": "0", "left": "0", "x": "0", "y": "0", "z": "0", "club": "CUK", "con": "", "shotText": "Shot 4 from the green (in the hole)"}]}, {"n": "2", "cNum": "11", "sc": "4", "pDay": "-1", "pTot": "-1", "shots": [{"n": "1", "pid": "0", "time": "", "putt": "", "t": "S", "prv": "n", "tee": "y", "cup": "n", "from": "OTB", "to": "ORO", "asc": "1", "dist": "0", "left": "0", "x": "0", "y": "0", "z": "0", "club": "CDR", "con": "", "shotText": "Shot 1 from the tee box"}, {"n": "2", "pid": "0", "time": "", "putt": "", "t": "S", "prv": "n", "tee": "n", "cup": "n", "from": "ORO", "to": "OGR", "asc": "1", "dist": "0", "left": "0", "x": "0", "y": "0", "z": "0", "club": "CUK", "con": "", "shotText": "Shot 2 from the primary rough"}, {"n": "3", "pid": "0", "time": "", "putt": "1", "t": "S", "prv": "n", "tee": "n", "cup": "n", "from": "OGR", "to": "OGR", "asc": "1", "dist": "0", "left": "0", "x": "0", "y": "0", "z": "0", "club": "CUK", "con": "", "shotText": "Shot 3 from the green"}, {"n": "4", "pid": "0", "time": "", "putt": "2", "t": "S", "prv": "n", "tee": "n", "cup": "y", "from": "OGR", "to": "hole", "asc": "1", "dist": "0", "left": "0", "x": "0", "y": "0", "z": "0", "club": "CUK", "con": "", "shotText": "Shot 4 from the green (in the hole)"}]}, {"n": "3", "cNum": "12", "sc": "3", "pDay": "-1", "pTot": "-1", "shots": [{"n": "1", "pid": "0", "time": "", "putt": "", "t": "S", "prv": "n", "tee": "y", "cup": "n", "from": "OTB", "to": "OFW", "asc": "1", "dist": "0", "left": "0", "x": "0", "y": "0", "z": "0", "club": "CUK", "con": "", "shotText": "Shot 1 from the tee box"}, {"n": "2", "pid": "0", "time": "", "putt": "", "t": "S", "prv": "n", "tee": "n", "cup": "n", "from": "OFW", "to": "OGR", "asc": "1", "dist": "0", "left": "0", "x": "0", "y": "0", "z": "0", "club": "CUK", "con": "", "shotText": "Shot 2 from the fairway"}, {"n": "3", "pid": "0", "time": "", "putt": "1", "t": "S", "prv": "n", "tee": "n", "cup": "y", "from": "OGR", "to": "hole", "asc": "1", "dist": "0", "left": "0", "x": "0", "y": "0", "z": "0", "club": "CUK", "con": "", "shotText": "Shot 3 from the green (in the hole)"}]}, {"n": "4", "cNum": "13", "sc": "4", "pDay": "-1", "pTot": "-1", "shots": [{"n": "1", "pid": "0", "time": "", "putt": "", "t": "S", "prv": "n", "tee": "y", "cup": "n", "from": "OTB", "to": "ORO", "asc": "1", "dist": "0", "left": "0", "x": "0", "y": "0", "z": "0", "club": "CDR", "con": "", "shotText": "Shot 1 from the tee box"}, {"n": "2", "pid": "0", "time": "", "putt": "", "t": "S", "prv": "n", "tee": "n", "cup": "n", "from": "ORO", "to": "ORO", "asc": "1", "dist": "0", "left": "0", "x": "0", "y": "0", "z": "0", "club": "CUK", "con": "", "shotText": "Shot 2 from the primary rough"}, {"n": "3", "pid": "0", "time": "", "putt": "", "t": "S", "prv": "n", "tee": "n", "cup": "n", "from": "ORO", "to": "OGR", "asc": "1", "dist": "0", "left": "0", "x": "0", "y": "0", "z": "0", "club": "CUK", "con": "", "shotText": "Shot 3 from the primary rough"}, {"n": "4", "pid": "0", "time": "", "putt": "1", "t": "S", "prv": "n", "tee": "n", "cup": "y", "from": "OGR", "to": "hole", "asc": "1", "dist": "0", "left": "0", "x": "0", "y": "0", "z": "0", "club": "CUK", "con": "", "shotText": "Shot 4 from the green (in the hole)"}]}, {"n": "5", "cNum": "14", "sc": "4", "pDay": "-1", "pTot": "-1", "shots": [{"n": "1", "pid": "0", "time": "", "putt": "", "t": "S", "prv": "n", "tee": "y", "cup": "n", "from": "OTB", "to": "OIR", "asc": "1", "dist": "0", "left": "0", "x": "0", "y": "0", "z": "0", "club": "CDR", "con": "", "shotText": "Shot 1 from the tee box"}, {"n": "2", "pid": "0", "time": "", "putt": "", "t": "S", "prv": "n", "tee": "n", "cup": "n", "from": "OIR", "to": "OFW", "asc": "1", "dist": "0", "left": "0", "x": "0", "y": "0", "z": "0", "club": "CUK", "con": "", "shotText": "Shot 2 from the intermediate rough"}, {"n": "3", "pid": "0", "time": "", "putt": "", "t": "S", "prv": "n", "tee": "n", "cup": "n", "from": "OFW", "to": "OGR", "asc": "1", "dist": "0", "left": "0", "x": "0", "y": "0", "z": "0", "club": "CUK", "con": "", "shotText": "Shot 3 from the fairway"}, {"n": "4", "pid": "0", "time": "", "putt": "1", "t": "S", "prv": "n", "tee": "n", "cup": "y", "from": "OGR", "to": "hole", "asc": "1", "dist": "0", "left": "0", "x": "0", "y": "0", "z": "0", "club": "CUK", "con": "", "shotText": "Shot 4 from the green (in the hole)"}]}, {"n": "6", "cNum": "15", "sc": "3", "pDay": "-1", "pTot": "-1", "shots": [{"n": "1", "pid": "0", "time": "", "putt": "", "t": "S", "prv": "n", "tee": "y", "cup": "n", "from": "OTB", "to": "OGR", "asc": "1", "dist": "0", "left": "0", "x": "0", "y": "0", "z": "0", "club": "CUK", "con": "", "shotText": "Shot 1 from the tee box"}, {"n": "2", "pid": "0", "time": "", "putt": "1", "t": "S", "prv": "n", "tee": "n", "cup": "n", "from": "OGR", "to": "OGR", "asc": "1", "dist": "0", "left": "0", "x": "0", "y": "0", "z": "0", "club": "CUK", "con": "", "shotText": "Shot 2 from the green"}, {"n": "3", "pid": "0", "time": "", "putt": "2", "t": "S", "prv": "n", "tee": "n", "cup": "y", "from": "OGR", "to": "hole", "asc": "1", "dist": "0", "left": "0", "x": "0", "y": "0", "z": "0", "club": "CUK", "con": "", "shotText": "Shot 3 from the green (in the hole)"}]}, {"n": "7", "cNum": "16", "sc": "4", "pDay": "-1", "pTot": "-1", "shots": [{"n": "1", "pid": "0", "time": "", "putt": "", "t": "S", "prv": "n", "tee": "y", "cup": "n", "from": "OTB", "to": "ORO", "asc": "1", "dist": "0", "left": "0", "x": "0", "y": "0", "z": "0", "club": "CDR", "con": "", "shotText": "Shot 1 from the tee box"}, {"n": "2", "pid": "0", "time": "", "putt": "", "t": "S", "prv": "n", "tee": "n", "cup": "n", "from": "ORO", "to": "ORO", "asc": "1", "dist": "0", "left": "0", "x": "0", "y": "0", "z": "0", "club": "CUK", "con": "", "shotText": "Shot 2 from the primary rough"}, {"n": "3", "pid": "0", "time": "", "putt": "", "t": "S", "prv": "n", "tee": "n", "cup": "n", "from": "ORO", "to": "OGR", "asc": "1", "dist": "0", "left": "0", "x": "0", "y": "0", "z": "0", "club": "CUK", "con": "", "shotText": "Shot 3 from the primary rough"}, {"n": "4", "pid": "0", "time": "", "putt": "1", "t": "S", "prv": "n", "tee": "n", "cup": "y", "from": "OGR", "to": "hole", "asc": "1", "dist": "0", "left": "0", "x": "0", "y": "0", "z": "0", "club": "CUK", "con": "", "shotText": "Shot 4 from the green (in the hole)"}]}, {"n": "8", "cNum": "17", "sc": "5", "pDay": "-1", "pTot": "-1", "shots": [{"n": "1", "pid": "0", "time": "", "putt": "", "t": "S", "prv": "n", "tee": "y", "cup": "n", "from": "OTB", "to": "OFW", "asc": "1", "dist": "0", "left": "0", "x": "0", "y": "0", "z": "0", "club": "CDR", "con": "", "shotText": "Shot 1 from the tee box"}, {"n": "2", "pid": "0", "time": "", "putt": "", "t": "S", "prv": "n", "tee": "n", "cup": "n", "from": "OFW", "to": "OFW", "asc": "1", "dist": "0", "left": "0", "x": "0", "y": "0", "z": "0", "club": "CUK", "con": "", "shotText": "Shot 2 from the fairway"}, {"n": "3", "pid": "0", "time": "", "putt": "", "t": "S", "prv": "n", "tee": "n", "cup": "n", "from": "OFW", "to": "OFW", "asc": "1", "dist": "0", "left": "0", "x": "0", "y": "0", "z": "0", "club": "CUK", "con": "", "shotText": "Shot 3 from the fairway"}, {"n": "4", "pid": "0", "time": "", "putt": "", "t": "S", "prv": "n", "tee": "n", "cup": "n", "from": "OFW", "to": "OGR", "asc": "1", "dist": "0", "left": "0", "x": "0", "y": "0", "z": "0", "club": "CUK", "con": "", "shotText": "Shot 4 from the fairway"}, {"n": "5", "pid": "0", "time": "", "putt": "1", "t": "S", "prv": "n", "tee": "n", "cup": "y", "from": "OGR", "to": "hole", "asc": "1", "dist": "0", "left": "0", "x": "0", "y": "0", "z": "0", "club": "CUK", "con": "", "shotText": "Shot 5 from the green (in the hole)"}]}, {"n": "9", "cNum": "18", "sc": "4", "pDay": "-1", "pTot": "-1", "shots": [{"n": "1", "pid": "0", "time": "", "putt": "", "t": "S", "prv": "n", "tee": "y", "cup": "n", "from": "OTB", "to": "OFW", "asc": "1", "dist": "0", "left": "0", "x": "0", "y": "0", "z": "0", "club": "CDR", "con": "", "shotText": "Shot 1 from the tee box"}, {"n": "2", "pid": "0", "time": "", "putt": "", "t": "S", "prv": "n", "tee": "n", "cup": "n", "from": "OFW", "to": "OFW", "asc": "1", "dist": "0", "left": "0", "x": "0", "y": "0", "z": "0", "club": "CUK", "con": "", "shotText": "Shot 2 from the fairway"}, {"n": "3", "pid": "0", "time": "", "putt": "", "t": "S", "prv": "n", "tee": "n", "cup": "n", "from": "OFW", "to": "OGR", "asc": "1", "dist": "0", "left": "0", "x": "0", "y": "0", "z": "0", "club": "CUK", "con": "", "shotText": "Shot 3 from the fairway"}, {"n": "4", "pid": "0", "time": "", "putt": "1", "t": "S", "prv": "n", "tee": "n", "cup": "y", "from": "OGR", "to": "hole", "asc": "1", "dist": "0", "left": "0", "x": "0", "y": "0", "z": "0", "club": "CUK", "con": "", "shotText": "Shot 4 from the green (in the hole)"}]}, {"n": "10", "cNum": "1", "sc": "4", "pDay": "-1", "pTot": "-1", "shots": [{"n": "1", "pid": "0", "time": "", "putt": "", "t": "S", "prv": "n", "tee": "y", "cup": "n", "from": "OTB", "to": "ORO", "asc": "1", "dist": "0", "left": "0", "x": "0", "y": "0", "z": "0", "club": "CDR", "con": "", "shotText": "Shot 1 from the tee box"}, {"n": "2", "pid": "0", "time": "", "putt": "", "t": "S", "prv": "n", "tee": "n", "cup": "n", "from": "ORO", "to": "OFW", "asc": "1", "dist": "0", "left": "0", "x": "0", "y": "0", "z": "0", "club": "CUK", "con": "", "shotText": "Shot 2 from the primary rough"}, {"n": "3", "pid": "0", "time": "", "putt": "", "t": "S", "prv": "n", "tee": "n", "cup": "n", "from": "OFW", "to": "OGR", "asc": "1", "dist": "0", "left": "0", "x": "0", "y": "0", "z": "0", "club": "CUK", "con": "", "shotText": "Shot 3 from the fairway"}, {"n": "4", "pid": "0", "time": "", "putt": "1", "t": "S", "prv": "n", "tee": "n", "cup": "y", "from": "OGR", "to": "hole", "asc": "1", "dist": "0", "left": "0", "x": "0", "y": "0", "z": "0", "club": "CUK", "con": "", "shotText": "Shot 4 from the green (in the hole)"}]}, {"n": "11", "cNum": "2", "sc": "4", "pDay": "-1", "pTot": "-1", "shots": [{"n": "1", "pid": "0", "time": "", "putt": "", "t": "S", "prv": "n", "tee": "y", "cup": "n", "from": "OTB", "to": "OFW", "asc": "1", "dist": "0", "left": "0", "x": "0", "y": "0", "z": "0", "club": "CDR", "con": "", "shotText": "Shot 1 from the tee box"}, {"n": "2", "pid": "0", "time": "", "putt": "", "t": "S", "prv": "n", "tee": "n", "cup": "n", "from": "OFW", "to": "OFW", "asc": "1", "dist": "0", "left": "0", "x": "0", "y": "0", "z": "0", "club": "CUK", "con": "", "shotText": "Shot 2 from the fairway"}, {"n": "3", "pid": "0", "time": "", "putt": "", "t": "S", "prv": "n", "tee": "n", "cup": "n", "from": "OFW", "to": "OGR", "asc": "1", "dist": "0", "left": "0", "x": "0", "y": "0", "z": "0", "club": "CUK", "con": "", "shotText": "Shot 3 from the fairway"}, {"n": "4", "pid": "0", "time": "", "putt": "1", "t": "S", "prv": "n", "tee": "n", "cup": "y", "from": "OGR", "to": "hole", "asc": "1", "dist": "0", "left": "0", "x": "0", "y": "0", "z": "0", "club": "CUK", "con": "", "shotText": "Shot 4 from the green (in the hole)"}]}, {"n": "12", "cNum": "3", "sc": "3", "pDay": "-1", "pTot": "-1", "shots": [{"n": "1", "pid": "0", "time": "", "putt": "", "t": "S", "prv": "n", "tee": "y", "cup": "n", "from": "OTB", "to": "OGR", "asc": "1", "dist": "0", "left": "0", "x": "0", "y": "0", "z": "0", "club": "CUK", "con": "", "shotText": "Shot 1 from the tee box"}, {"n": "2", "pid": "0", "time": "", "putt": "1", "t": "S", "prv": "n", "tee": "n", "cup": "n", "from": "OGR", "to": "OGR", "asc": "1", "dist": "0", "left": "0", "x": "0", "y": "0", "z": "0", "club": "CUK", "con": "", "shotText": "Shot 2 from the green"}, {"n": "3", "pid": "0", "time": "", "putt": "2", "t": "S", "prv": "n", "tee": "n", "cup": "y", "from": "OGR", "to": "hole", "asc": "1", "dist": "0", "left": "0", "x": "0", "y": "0", "z": "0", "club": "CUK", "con": "", "shotText": "Shot 3 from the green (in the hole)"}]}, {"n": "13", "cNum": "4", "sc": "4", "pDay": "-1", "pTot": "-1", "shots": [{"n": "1", "pid": "0", "time": "", "putt": "", "t": "S", "prv": "n", "tee": "y", "cup": "n", "from": "OTB", "to": "ORO", "asc": "1", "dist": "0", "left": "0", "x": "0", "y": "0", "z": "0", "club": "CDR", "con": "", "shotText": "Shot 1 from the tee box"}, {"n": "2", "pid": "0", "time": "", "putt": "", "t": "S", "prv": "n", "tee": "n", "cup": "n", "from": "ORO", "to": "OGR", "asc": "1", "dist": "0", "left": "0", "x": "0", "y": "0", "z": "0", "club": "CUK", "con": "", "shotText": "Shot 2 from the primary rough"}, {"n": "3", "pid": "0", "time": "", "putt": "1", "t": "S", "prv": "n", "tee": "n", "cup": "n", "from": "OGR", "to": "OGR", "asc": "1", "dist": "0", "left": "0", "x": "0", "y": "0", "z": "0", "club": "CUK", "con": "", "shotText": "Shot 3 from the green"}, {"n": "4", "pid": "0", "time": "", "putt": "2", "t": "S", "prv": "n", "tee": "n", "cup": "y", "from": "OGR", "to": "hole", "asc": "1", "dist": "0", "left": "0", "x": "0", "y": "0", "z": "0", "club": "CUK", "con": "", "shotText": "Shot 4 from the green (in the hole)"}]}, {"n": "14", "cNum": "5", "sc": "5", "pDay": "-1", "pTot": "-1", "shots": [{"n": "1", "pid": "0", "time": "", "putt": "", "t": "S", "prv": "n", "tee": "y", "cup": "n", "from": "OTB", "to": "OFW", "asc": "1", "dist": "0", "left": "0", "x": "0", "y": "0", "z": "0", "club": "CDR", "con": "", "shotText": "Shot 1 from the tee box"}, {"n": "2", "pid": "0", "time": "", "putt": "", "t": "S", "prv": "n", "tee": "n", "cup": "n", "from": "OFW", "to": "OFW", "asc": "1", "dist": "0", "left": "0", "x": "0", "y": "0", "z": "0", "club": "CUK", "con": "", "shotText": "Shot 2 from the fairway"}, {"n": "3", "pid": "0", "time": "", "putt": "", "t": "S", "prv": "n", "tee": "n", "cup": "n", "from": "OFW", "to": "OGR", "asc": "1", "dist": "0", "left": "0", "x": "0", "y": "0", "z": "0", "club": "CUK", "con": "", "shotText": "Shot 3 from the fairway"}, {"n": "4", "pid": "0", "time": "", "putt": "1", "t": "S", "prv": "n", "tee": "n", "cup": "n", "from": "OGR", "to": "OGR", "asc": "1", "dist": "0", "left": "0", "x": "0", "y": "0", "z": "0", "club": "CUK", "con": "", "shotText": "Shot 4 from the green"}, {"n": "5", "pid": "0", "time": "", "putt": "2", "t": "S", "prv": "n", "tee": "n", "cup": "y", "from": "OGR", "to": "hole", "asc": "1", "dist": "0", "left": "0", "x": "0", "y": "0", "z": "0", "club": "CUK", "con": "", "shotText": "Shot 5 from the green (in the hole)"}]}, {"n": "15", "cNum": "6", "sc": "4", "pDay": "-1", "pTot": "-1", "shots": [{"n": "1", "pid": "0", "time": "", "putt": "", "t": "S", "prv": "n", "tee": "y", "cup": "n", "from": "OTB", "to": "OFW", "asc": "1", "dist": "0", "left": "0", "x": "0", "y": "0", "z": "0", "club": "CDR", "con": "", "shotText": "Shot 1 from the tee box"}, {"n": "2", "pid": "0", "time": "", "putt": "", "t": "S", "prv": "n", "tee": "n", "cup": "n", "from": "OFW", "to": "ORO", "asc": "1", "dist": "0", "left": "0", "x": "0", "y": "0", "z": "0", "club": "CUK", "con": "", "shotText": "Shot 2 from the fairway"}, {"n": "3", "pid": "0", "time": "", "putt": "", "t": "S", "prv": "n", "tee": "n", "cup": "n", "from": "ORO", "to": "OGR", "asc": "1", "dist": "0", "left": "0", "x": "0", "y": "0", "z": "0", "club": "CUK", "con": "", "shotText": "Shot 3 from the primary rough"}, {"n": "4", "pid": "0", "time": "", "putt": "1", "t": "S", "prv": "n", "tee": "n", "cup": "y", "from": "OGR", "to": "hole", "asc": "1", "dist": "0", "left": "0", "x": "0", "y": "0", "z": "0", "club": "CUK", "con": "", "shotText": "Shot 4 from the green (in the hole)"}]}, {"n": "16", "cNum": "7", "sc": "3", "pDay": "-2", "pTot": "-2", "shots": [{"n": "1", "pid": "0", "time": "", "putt": "", "t": "S", "prv": "n", "tee": "y", "cup": "n", "from": "OTB", "to": "OFW", "asc": "1", "dist": "0", "left": "0", "x": "0", "y": "0", "z": "0", "club": "CFW", "con": "", "shotText": "Shot 1 from the tee box"}, {"n": "2", "pid": "0", "time": "", "putt": "", "t": "S", "prv": "n", "tee": "n", "cup": "n", "from": "OFW", "to": "OGR", "asc": "1", "dist": "0", "left": "0", "x": "0", "y": "0", "z": "0", "club": "CUK", "con": "", "shotText": "Shot 2 from the fairway"}, {"n": "3", "pid": "0", "time": "", "putt": "1", "t": "S", "prv": "n", "tee": "n", "cup": "y", "from": "OGR", "to": "hole", "asc": "1", "dist": "0", "left": "0", "x": "0", "y": "0", "z": "0", "club": "CUK", "con": "", "shotText": "Shot 3 from the green (in the hole)"}]}, {"n": "17", "cNum": "8", "sc": "4", "pDay": "-1", "pTot": "-1", "shots": [{"n": "1", "pid": "0", "time": "", "putt": "", "t": "S", "prv": "n", "tee": "y", "cup": "n", "from": "OTB", "to": "OIR", "asc": "1", "dist": "0", "left": "0", "x": "0", "y": "0", "z": "0", "club": "CUK", "con": "", "shotText": "Shot 1 from the tee box"}, {"n": "2", "pid": "0", "time": "", "putt": "", "t": "S", "prv": "n", "tee": "n", "cup": "n", "from": "OIR", "to": "OGR", "asc": "1", "dist": "0", "left": "0", "x": "0", "y": "0", "z": "0", "club": "CUK", "con": "", "shotText": "Shot 2 from the intermediate rough"}, {"n": "3", "pid": "0", "time": "", "putt": "1", "t": "S", "prv": "n", "tee": "n", "cup": "n", "from": "OGR", "to": "OGR", "asc": "1", "dist": "0", "left": "0", "x": "0", "y": "0", "z": "0", "club": "CUK", "con": "", "shotText": "Shot 3 from the green"}, {"n": "4", "pid": "0", "time": "", "putt": "2", "t": "S", "prv": "n", "tee": "n", "cup": "y", "from": "OGR", "to": "hole", "asc": "1", "dist": "0", "left": "0", "x": "0", "y": "0", "z": "0", "club": "CUK", "con": "", "shotText": "Shot 4 from the green (in the hole)"}]}, {"n": "18", "cNum": "9", "sc": "5", "pDay": "-1", "pTot": "-1", "shots": [{"n": "1", "pid": "0", "time": "", "putt": "", "t": "S", "prv": "n", "tee": "y", "cup": "n", "from": "OTB", "to": "OFW", "asc": "1", "dist": "0", "left": "0", "x": "0", "y": "0", "z": "0", "club": "CDR", "con": "", "shotText": "Shot 1 from the tee box"}, {"n": "2", "pid": "0", "time": "", "putt": "", "t": "S", "prv": "n", "tee": "n", "cup": "n", "from": "OFW", "to": "OGS", "asc": "1", "dist": "0", "left": "0", "x": "0", "y": "0", "z": "0", "club": "CUK", "con": "", "shotText": "Shot 2 from the fairway"}, {"n": "3", "pid": "0", "time": "", "putt": "", "t": "S", "prv": "n", "tee": "n", "cup": "n", "from": "OGS", "to": "OFW", "asc": "1", "dist": "0", "left": "0", "x": "0", "y": "0", "z": "0", "club": "CUK", "con": "", "shotText": "Shot 3 from the green side bunker"}, {"n": "4", "pid": "0", "time": "", "putt": "", "t": "S", "prv": "n", "tee": "n", "cup": "n", "from": "OFW", "to": "OGR", "asc": "1", "dist": "0", "left": "0", "x": "0", "y": "0", "z": "0", "club": "CUK", "con": "", "shotText": "Shot 4 from the fairway"}, {"n": "5", "pid": "0", "time": "", "putt": "1", "t": "S", "prv": "n", "tee": "n", "cup": "y", "from": "OGR", "to": "hole", "asc": "1", "dist": "0", "left": "0", "x": "0", "y": "0", "z": "0", "club": "CUK", "con": "", "shotText": "Shot 5 from the green (in the hole)"}]}]}, {"n": "2", "holes": [{"n": "1", "cNum": "1", "sc": "4", "pDay": "0", "pTot": "-1", "shots": [{"n": "1", "pid": "0", "time": "", "putt": "", "t": "S", "prv": "n", "tee": "y", "cup": "n", "from": "OTB", "to": "ELF", "asc": "1", "dist": "10168", "left": "5667", "x": "8920.068", "y": "10846.613", "z": "53.293", "club": "CDR", "con": "", "shotText": "Shot 1 282 yds to left fairway, 157 yds to hole"}, {"n": "2", "pid": "0", "time": "", "putt": "", "t": "S", "prv": "n", "tee": "n", "cup": "n", "from": "OFW", "to": "ELR", "asc": "1", "dist": "5741", "left": "245", "x": "8464.130", "y": "10701.600", "z": "53.401", "club": "CUK", "con": "", "shotText": "Shot 2 159 yds to left rough, 20 ft 5 in. to hole"}, {"n": "3", "pid": "0", "time": "", "putt": "", "t": "S", "prv": "n", "tee": "n", "cup": "n", "from": "ORO", "to": "OGR", "asc": "1", "dist": "258", "left": "12", "x": "8465.146", "y": "10723.051", "z": "53.018", "club": "CUK", "con": "", "shotText": "Shot 3 21 ft 6 in. to green, 12 in. to hole"}, {"n": "4", "pid": "0", "time": "", "putt": "1", "t": "S", "prv": "n", "tee": "n", "cup": "y", "from": "OGR", "to": "hole", "asc": "1", "dist": "12", "left": "0", "x": "0", "y": "0", "z": "0", "club": "CUK", "con": "", "shotText": "Shot 4 in the hole"}]}, {"n": "2", "cNum": "2", "sc": "5", "pDay": "1", "pTot": "0", "shots": [{"n": "1", "pid": "0", "time": "", "putt": "", "t": "S", "prv": "n", "tee": "y", "cup": "n", "from": "OTB", "to": "ERR", "asc": "1", "dist": "8439", "left": "5065", "x": "8283.771", "y": "10185.799", "z": "45.991", "club": "CFW", "con": "", "shotText": "Shot 1 234 yds to right rough, 141 yds to hole"}, {"n": "2", "pid": "0", "time": "", "putt": "", "t": "S", "prv": "n", "tee": "n", "cup": "n", "from": "ORO", "to": "ELF", "asc": "1", "dist": "4569", "left": "554", "x": "8290.782", "y": "9805.092", "z": "42.374", "club": "CUK", "con": "", "shotText": "Shot 2 127 yds to left fairway, 46 ft 2 in. to hole"}, {"n": "3", "pid": "0", "time": "", "putt": "", "t": "S", "prv": "n", "tee": "n", "cup": "n", "from": "OFW", "to": "OGR", "asc": "1", "dist": "453", "left": "110", "x": "8270.891", "y": "9773.047", "z": "43.025", "club": "CUK", "con": "", "shotText": "Shot 3 37 ft 9 in. to green, 9 ft 2 in. to hole"}, {"n": "4", "pid": "0", "time": "", "putt": "1", "t": "S", "prv": "n", "tee": "n", "cup": "n", "from": "OGR", "to": "OGR", "asc": "1", "dist": "115", "left": "13", "x": "8268.500", "y": "9763.800", "z": "43.175", "club": "CUK", "con": "", "shotText": "Shot 4 putt 9 ft 7 in., 13 in. to hole"}, {"n": "5", "pid": "0", "time": "", "putt": "2", "t": "S", "prv": "n", "tee": "n", "cup": "y", "from": "OGR", "to": "hole", "asc": "1", "dist": "13", "left": "0", "x": "0", "y": "0", "z": "0", "club": "CUK", "con": "", "shotText": "Shot 5 in the hole"}]}, {"n": "3", "cNum": "3", "sc": "3", "pDay": "1", "pTot": "0", "shots": [{"n": "1", "pid": "0", "time": "", "putt": "", "t": "S", "prv": "n", "tee": "y", "cup": "n", "from": "OTB", "to": "OGR", "asc": "1", "dist": "6796", "left": "703", "x": "8046.173", "y": "9098.458", "z": "1.533", "club": "CUK", "con": "", "shotText": "Shot 1 189 yds to green, 58 ft 7 in. to hole"}, {"n": "2", "pid": "0", "time": "", "putt": "1", "t": "S", "prv": "n", "tee": "n", "cup": "n", "from": "OGR", "to": "OGR", "asc": "1", "dist": "686", "left": "17", "x": "8069.290", "y": "9046.223", "z": "3.408", "club": "CUK", "con": "", "shotText": "Shot 2 putt 57 ft 2 in., 17 in. to hole"}, {"n": "3", "pid": "0", "time": "", "putt": "2", "t": "S", "prv": "n", "tee": "n", "cup": "y", "from": "OGR", "to": "hole", "asc": "1", "dist": "17", "left": "0", "x": "0", "y": "0", "z": "0", "club": "CUK", "con": "", "shotText": "Shot 3 in the hole"}]}, {"n": "4", "cNum": "4", "sc": "4", "pDay": "1", "pTot": "0", "shots": [{"n": "1", "pid": "0", "time": "", "putt": "", "t": "S", "prv": "n", "tee": "y", "cup": "n", "from": "OTB", "to": "ERF", "asc": "1", "dist": "9423", "left": "7742", "x": "7767.590", "y": "10115.331", "z": "12.941", "club": "CDR", "con": "", "shotText": "Shot 1 262 yds to right fairway, 215 yds to hole"}, {"n": "2", "pid": "0", "time": "", "putt": "", "t": "S", "prv": "n", "tee": "n", "cup": "n", "from": "OFW", "to": "ELF", "asc": "1", "dist": "6573", "left": "1273", "x": "7731.906", "y": "10661.924", "z": "14.762", "club": "CUK", "con": "", "shotText": "Shot 2 183 yds to left fairway, 35 yds to hole"}, {"n": "3", "pid": "0", "time": "", "putt": "", "t": "S", "prv": "n", "tee": "n", "cup": "n", "from": "OFW", "to": "OGR", "asc": "1", "dist": "1220", "left": "56", "x": "7681.017", "y": "10749.967", "z": "15.917", "club": "CUK", "con": "", "shotText": "Shot 3 34 yds to green, 4 ft 8 in. to hole"}, {"n": "4", "pid": "0", "time": "", "putt": "1", "t": "S", "prv": "n", "tee": "n", "cup": "y", "from": "OGR", "to": "hole", "asc": "1", "dist": "56", "left": "0", "x": "0", "y": "0", "z": "0", "club": "CUK", "con": "", "shotText": "Shot 4 in the hole"}]}, {"n": "5", "cNum": "5", "sc": "4", "pDay": "1", "pTot": "0", "shots": [{"n": "1", "pid": "0", "time": "", "putt": "", "t": "S", "prv": "n", "tee": "y", "cup": "n", "from": "OTB", "to": "ELR", "asc": "1", "dist": "9302", "left": "7200", "x": "8077.833", "y": "10106.753", "z": "26.124", "club": "CDR", "con": "", "shotText": "Shot 1 258 yds to left rough, 200 yds to hole"}, {"n": "2", "pid": "0", "time": "", "putt": "", "t": "S", "prv": "n", "tee": "n", "cup": "n", "from": "ORO", "to": "ERF", "asc": "1", "dist": "6075", "left": "1141", "x": "8041.758", "y": "9601.924", "z": "13.400", "club": "CUK", "con": "", "shotText": "Shot 2 169 yds to right fairway, 95 ft 1 in. to hole"}, {"n": "3", "pid": "0", "time": "", "putt": "", "t": "S", "prv": "n", "tee": "n", "cup": "n", "from": "OFW", "to": "OGR", "asc": "1", "dist": "1127", "left": "20", "x": "8017.949", "y": "9511.099", "z": "16.694", "club": "CUK", "con": "", "shotText": "Shot 3 93 ft 11 in. to green, 20 in. to hole"}, {"n": "4", "pid": "0", "time": "", "putt": "1", "t": "S", "prv": "n", "tee": "n", "cup": "y", "from": "OGR", "to": "hole", "asc": "1", "dist": "20", "left": "0", "x": "0", "y": "0", "z": "0", "club": "CUK", "con": "", "shotText": "Shot 4 in the hole"}]}, {"n": "6", "cNum": "6", "sc": "4", "pDay": "0", "pTot": "-1", "shots": [{"n": "1", "pid": "0", "time": "", "putt": "", "t": "S", "prv": "n", "tee": "y", "cup": "n", "from": "OTB", "to": "ERF", "asc": "1", "dist": "9073", "left": "10868", "x": "8638.815", "y": "10214.879", "z": "53.016", "club": "CDR", "con": "", "shotText": "Shot 1 252 yds to right fairway, 302 yds to hole"}, {"n": "2", "pid": "0", "time": "", "putt": "", "t": "S", "prv": "n", "tee": "n", "cup": "n", "from": "OFW", "to": "ERR", "asc": "1", "dist": "8572", "left": "2357", "x": "9219.390", "y": "10631.123", "z": "51.046", "club": "CUK", "con": "", "shotText": "Shot 2 238 yds to right rough, 65 yds to hole"}, {"n": "3", "pid": "0", "time": "", "putt": "", "t": "S", "prv": "n", "tee": "n", "cup": "n", "from": "ORO", "to": "OGR", "asc": "1", "dist": "2396", "left": "95", "x": "9341.150", "y": "10789.168", "z": "59.163", "club": "CUK", "con": "", "shotText": "Shot 3 67 yds to green, 7 ft 11 in. to hole"}, {"n": "4", "pid": "0", "time": "", "putt": "1", "t": "S", "prv": "n", "tee": "n", "cup": "y", "from": "OGR", "to": "hole", "asc": "1", "dist": "95", "left": "0", "x": "0", "y": "0", "z": "0", "club": "CUK", "con": "", "shotText": "Shot 4 in the hole"}]}, {"n": "7", "cNum": "7", "sc": "4", "pDay": "0", "pTot": "-1", "shots": [{"n": "1", "pid": "0", "time": "", "putt": "", "t": "S", "prv": "n", "tee": "y", "cup": "n", "from": "OTB", "to": "ELI", "asc": "1", "dist": "10502", "left": "6322", "x": "9411.976", "y": "10046.426", "z": "55.557", "club": "CDR", "con": "", "shotText": "Shot 1 292 yds to left intermediate, 176 yds to hole"}, {"n": "2", "pid": "0", "time": "", "putt": "", "t": "S", "prv": "n", "tee": "n", "cup": "n", "from": "OIR", "to": "ERR", "asc": "1", "dist": "5643", "left": "864", "x": "9095.231", "y": "9699.230", "z": "38.789", "club": "CUK", "con": "", "shotText": "Shot 2 157 yds to right rough, 72 ft 0 in. to hole"}, {"n": "3", "pid": "0", "time": "", "putt": "", "t": "S", "prv": "n", "tee": "n", "cup": "n", "from": "ORO", "to": "OGR", "asc": "1", "dist": "801", "left": "85", "x": "9097.621", "y": "9632.682", "z": "43.231", "club": "CUK", "con": "", "shotText": "Shot 3 66 ft 9 in. to green, 7 ft 1 in. to hole"}, {"n": "4", "pid": "0", "time": "", "putt": "1", "t": "S", "prv": "n", "tee": "n", "cup": "y", "from": "OGR", "to": "hole", "asc": "1", "dist": "85", "left": "0", "x": "0", "y": "0", "z": "0", "club": "CUK", "con": "", "shotText": "Shot 4 in the hole"}]}, {"n": "8", "cNum": "8", "sc": "2", "pDay": "-1", "pTot": "-2", "shots": [{"n": "1", "pid": "0", "time": "", "putt": "", "t": "S", "prv": "n", "tee": "y", "cup": "n", "from": "OTB", "to": "OGR", "asc": "1", "dist": "6442", "left": "31", "x": "9696.603", "y": "9706.285", "z": "66.641", "club": "CUK", "con": "", "shotText": "Shot 1 179 yds to green, 2 ft 7 in. to hole"}, {"n": "2", "pid": "0", "time": "", "putt": "1", "t": "S", "prv": "n", "tee": "n", "cup": "y", "from": "OGR", "to": "hole", "asc": "1", "dist": "31", "left": "0", "x": "0", "y": "0", "z": "0", "club": "CUK", "con": "", "shotText": "Shot 2 in the hole"}]}, {"n": "9", "cNum": "9", "sc": "4", "pDay": "-2", "pTot": "-3", "shots": [{"n": "1", "pid": "0", "time": "", "putt": "", "t": "S", "prv": "n", "tee": "y", "cup": "n", "from": "OTB", "to": "ERF", "asc": "1", "dist": "11041", "left": "10655", "x": "10061.501", "y": "8956.208", "z": "73.024", "club": "CDR", "con": "", "shotText": "Shot 1 307 yds to right fairway, 296 yds to hole"}, {"n": "2", "pid": "0", "time": "", "putt": "", "t": "S", "prv": "n", "tee": "n", "cup": "n", "from": "OFW", "to": "ERF", "asc": "1", "dist": "10061", "left": "664", "x": "10122.134", "y": "8119.967", "z": "67.646", "club": "CUK", "con": "", "shotText": "Shot 2 279 yds to right fairway, 55 ft 4 in. to hole"}, {"n": "3", "pid": "0", "time": "", "putt": "", "t": "S", "prv": "n", "tee": "n", "cup": "n", "from": "OFW", "to": "OGR", "asc": "1", "dist": "644", "left": "24", "x": "10151.135", "y": "8074.862", "z": "68.835", "club": "CUK", "con": "", "shotText": "Shot 3 53 ft 8 in. to green, 2 ft 0 in. to hole"}, {"n": "4", "pid": "0", "time": "", "putt": "1", "t": "S", "prv": "n", "tee": "n", "cup": "y", "from": "OGR", "to": "hole", "asc": "1", "dist": "24", "left": "0", "x": "0", "y": "0", "z": "0", "club": "CUK", "con": "", "shotText": "Shot 4 in the hole"}]}, {"n": "10", "cNum": "10", "sc": "3", "pDay": "-3", "pTot": "-4", "shots": [{"n": "1", "pid": "0", "time": "", "putt": "", "t": "S", "prv": "n", "tee": "y", "cup": "n", "from": "OTB", "to": "OST", "asc": "1", "dist": "10707", "left": "4517", "x": "10308.749", "y": "7272.840", "z": "80.930", "club": "CDR", "con": "", "shotText": "Shot 1 297 yds to fairway bunker, 125 yds to hole"}, {"n": "2", "pid": "0", "time": "", "putt": "", "t": "S", "prv": "n", "tee": "n", "cup": "n", "from": "OST", "to": "OGR", "asc": "1", "dist": "4527", "left": "46", "x": "10306.942", "y": "6895.588", "z": "82.621", "club": "CUK", "con": "", "shotText": "Shot 2 126 yds to green, 3 ft 10 in. to hole"}, {"n": "3", "pid": "0", "time": "", "putt": "1", "t": "S", "prv": "n", "tee": "n", "cup": "y", "from": "OGR", "to": "hole", "asc": "1", "dist": "46", "left": "0", "x": "0", "y": "0", "z": "0", "club": "CUK", "con": "", "shotText": "Shot 3 in the hole"}]}, {"n": "11", "cNum": "11", "sc": "4", "pDay": "-2", "pTot": "-3", "shots": [{"n": "1", "pid": "0", "time": "", "putt": "", "t": "S", "prv": "n", "tee": "y", "cup": "n", "from": "OTB", "to": "ERR", "asc": "1", "dist": "7714", "left": "646", "x": "9761.429", "y": "6570.541", "z": "52.749", "club": "CUK", "con": "", "shotText": "Shot 1 214 yds to right rough, 53 ft 10 in. to hole"}, {"n": "2", "pid": "0", "time": "", "putt": "", "t": "S", "prv": "n", "tee": "n", "cup": "n", "from": "ORO", "to": "OGR", "asc": "1", "dist": "932", "left": "418", "x": "9749.933", "y": "6493.737", "z": "55.499", "club": "CUK", "con": "", "shotText": "Shot 2 77 ft 8 in. to green, 34 ft 10 in. to hole"}, {"n": "3", "pid": "0", "time": "", "putt": "1", "t": "S", "prv": "n", "tee": "n", "cup": "n", "from": "OGR", "to": "OGR", "asc": "1", "dist": "439", "left": "20", "x": "9776.766", "y": "6518.495", "z": "53.741", "club": "CUK", "con": "", "shotText": "Shot 3 putt 36 ft 7 in., 20 in. to hole"}, {"n": "4", "pid": "0", "time": "", "putt": "2", "t": "S", "prv": "n", "tee": "n", "cup": "y", "from": "OGR", "to": "hole", "asc": "1", "dist": "20", "left": "0", "x": "0", "y": "0", "z": "0", "club": "CUK", "con": "", "shotText": "Shot 4 in the hole"}]}, {"n": "12", "cNum": "12", "sc": "5", "pDay": "-1", "pTot": "-2", "shots": [{"n": "1", "pid": "0", "time": "", "putt": "", "t": "S", "prv": "n", "tee": "y", "cup": "n", "from": "OTB", "to": "ELR", "asc": "1", "dist": "9499", "left": "8279", "x": "8910.916", "y": "6582.352", "z": "40.823", "club": "CDR", "con": "", "shotText": "Shot 1 264 yds to left rough, 230 yds to hole"}, {"n": "2", "pid": "0", "time": "", "putt": "", "t": "S", "prv": "n", "tee": "n", "cup": "n", "from": "ORO", "to": "ERF", "asc": "1", "dist": "4652", "left": "3712", "x": "8630.501", "y": "6849.837", "z": "29.990", "club": "CUK", "con": "", "shotText": "Shot 2 129 yds to right fairway, 103 yds to hole"}, {"n": "3", "pid": "0", "time": "", "putt": "", "t": "S", "prv": "n", "tee": "n", "cup": "n", "from": "OFW", "to": "OGR", "asc": "1", "dist": "3294", "left": "421", "x": "8388.249", "y": "6978.996", "z": "30.514", "club": "CUK", "con": "", "shotText": "Shot 3 92 yds to green, 35 ft 1 in. to hole"}, {"n": "4", "pid": "0", "time": "", "putt": "1", "t": "S", "prv": "n", "tee": "n", "cup": "n", "from": "OGR", "to": "OGR", "asc": "1", "dist": "429", "left": "29", "x": "8354.048", "y": "6989.323", "z": "31.187", "club": "CUK", "con": "", "shotText": "Shot 4 putt 35 ft 9 in., 2 ft 5 in. to hole"}, {"n": "5", "pid": "0", "time": "", "putt": "2", "t": "S", "prv": "n", "tee": "n", "cup": "y", "from": "OGR", "to": "hole", "asc": "1", "dist": "29", "left": "0", "x": "0", "y": "0", "z": "0", "club": "CUK", "con": "", "shotText": "Shot 5 in the hole"}]}, {"n": "13", "cNum": "13", "sc": "4", "pDay": "-2", "pTot": "-3", "shots": [{"n": "1", "pid": "0", "time": "", "putt": "", "t": "S", "prv": "n", "tee": "y", "cup": "n", "from": "OTB", "to": "ERF", "asc": "1", "dist": "10673", "left": "8692", "x": "9151.443", "y": "6988.374", "z": "32.190", "club": "CDR", "con": "", "shotText": "Shot 1 296 yds to right fairway, 241 yds to hole"}, {"n": "2", "pid": "0", "time": "", "putt": "", "t": "S", "prv": "n", "tee": "n", "cup": "n", "from": "OFW", "to": "OGR", "asc": "1", "dist": "8600", "left": "586", "x": "9843.307", "y": "6802.577", "z": "52.165", "club": "CUK", "con": "", "shotText": "Shot 2 239 yds to green, 48 ft 10 in. to hole"}, {"n": "3", "pid": "0", "time": "", "putt": "1", "t": "S", "prv": "n", "tee": "n", "cup": "n", "from": "OGR", "to": "OGR", "asc": "1", "dist": "501", "left": "98", "x": "9855.662", "y": "6842.402", "z": "53.330", "club": "CUK", "con": "", "shotText": "Shot 3 putt 41 ft 9 in., 8 ft 2 in. to hole"}, {"n": "4", "pid": "0", "time": "", "putt": "2", "t": "S", "prv": "n", "tee": "n", "cup": "y", "from": "OGR", "to": "hole", "asc": "1", "dist": "98", "left": "0", "x": "0", "y": "0", "z": "0", "club": "CUK", "con": "", "shotText": "Shot 4 in the hole"}]}, {"n": "14", "cNum": "14", "sc": "4", "pDay": "-2", "pTot": "-3", "shots": [{"n": "1", "pid": "0", "time": "", "putt": "", "t": "S", "prv": "n", "tee": "y", "cup": "n", "from": "OTB", "to": "OST", "asc": "1", "dist": "9822", "left": "5939", "x": "9790.626", "y": "7536.278", "z": "48.853", "club": "CDR", "con": "", "shotText": "Shot 1 273 yds to fairway bunker, 165 yds to hole"}, {"n": "2", "pid": "0", "time": "", "putt": "", "t": "S", "prv": "n", "tee": "n", "cup": "n", "from": "OST", "to": "EG2", "asc": "1", "dist": "5417", "left": "614", "x": "9621.779", "y": "7954.945", "z": "46.956", "club": "CUK", "con": "", "shotText": "Shot 2 150 yds to right green side bunker, 51 ft 2 in. to hole"}, {"n": "3", "pid": "0", "time": "", "putt": "", "t": "S", "prv": "n", "tee": "n", "cup": "n", "from": "OGS", "to": "OGR", "asc": "1", "dist": "652", "left": "56", "x": "9575.112", "y": "7982.604", "z": "50.612", "club": "CUK", "con": "", "shotText": "Shot 3 54 ft 4 in. to green, 4 ft 8 in. to hole"}, {"n": "4", "pid": "0", "time": "", "putt": "1", "t": "S", "prv": "n", "tee": "n", "cup": "y", "from": "OGR", "to": "hole", "asc": "1", "dist": "56", "left": "0", "x": "0", "y": "0", "z": "0", "club": "CUK", "con": "", "shotText": "Shot 4 in the hole"}]}, {"n": "15", "cNum": "15", "sc": "6", "pDay": "0", "pTot": "-1", "shots": [{"n": "1", "pid": "0", "time": "", "putt": "", "t": "S", "prv": "n", "tee": "y", "cup": "n", "from": "OTB", "to": "ELR", "asc": "1", "dist": "9787", "left": "7315", "x": "9842.503", "y": "8292.222", "z": "53.877", "club": "CDR", "con": "", "shotText": "Shot 1 272 yds to left rough, 203 yds to hole"}, {"n": "2", "pid": "0", "time": "", "putt": "", "t": "S", "prv": "n", "tee": "n", "cup": "n", "from": "ORO", "to": "ELR", "asc": "1", "dist": "1049", "left": "6270", "x": "9835.773", "y": "8379.352", "z": "54.407", "club": "CUK", "con": "", "shotText": "Shot 2 87 ft 5 in. to left rough, 174 yds to hole"}, {"n": "3", "pid": "0", "time": "", "putt": "", "t": "S", "prv": "n", "tee": "n", "cup": "n", "from": "ORO", "to": "ERF", "asc": "1", "dist": "5281", "left": "1036", "x": "9785.200", "y": "8816.505", "z": "58.932", "club": "CUK", "con": "", "shotText": "Shot 3 147 yds to right fairway, 86 ft 4 in. to hole"}, {"n": "4", "pid": "0", "time": "", "putt": "", "t": "S", "prv": "n", "tee": "n", "cup": "n", "from": "OFW", "to": "OGR", "asc": "1", "dist": "891", "left": "145", "x": "9754.491", "y": "8884.038", "z": "62.396", "club": "CUK", "con": "", "shotText": "Shot 4 74 ft 3 in. to green, 12 ft 1 in. to hole"}, {"n": "5", "pid": "0", "time": "", "putt": "1", "t": "S", "prv": "n", "tee": "n", "cup": "n", "from": "OGR", "to": "OGR", "asc": "1", "dist": "151", "left": "6", "x": "9747.552", "y": "8894.579", "z": "62.660", "club": "CUK", "con": "", "shotText": "Shot 5 putt 12 ft 7 in., 6 in. to hole"}, {"n": "6", "pid": "0", "time": "", "putt": "2", "t": "S", "prv": "n", "tee": "n", "cup": "y", "from": "OGR", "to": "hole", "asc": "1", "dist": "6", "left": "0", "x": "0", "y": "0", "z": "0", "club": "CUK", "con": "", "shotText": "Shot 6 in the hole"}]}, {"n": "16", "cNum": "16", "sc": "3", "pDay": "0", "pTot": "-1", "shots": [{"n": "1", "pid": "0", "time": "", "putt": "", "t": "S", "prv": "n", "tee": "y", "cup": "n", "from": "OTB", "to": "OGR", "asc": "1", "dist": "7616", "left": "489", "x": "9097.546", "y": "8392.745", "z": "42.771", "club": "CUK", "con": "", "shotText": "Shot 1 212 yds to green, 40 ft 9 in. to hole"}, {"n": "2", "pid": "0", "time": "", "putt": "1", "t": "S", "prv": "n", "tee": "n", "cup": "n", "from": "OGR", "to": "OGR", "asc": "1", "dist": "543", "left": "54", "x": "9062.961", "y": "8363.572", "z": "43.683", "club": "CUK", "con": "", "shotText": "Shot 2 putt 45 ft 3 in., 4 ft 6 in. to hole"}, {"n": "3", "pid": "0", "time": "", "putt": "2", "t": "S", "prv": "n", "tee": "n", "cup": "y", "from": "OGR", "to": "hole", "asc": "1", "dist": "54", "left": "0", "x": "0", "y": "0", "z": "0", "club": "CUK", "con": "", "shotText": "Shot 3 in the hole"}]}, {"n": "17", "cNum": "17", "sc": "4", "pDay": "0", "pTot": "-1", "shots": [{"n": "1", "pid": "0", "time": "", "putt": "", "t": "S", "prv": "n", "tee": "y", "cup": "n", "from": "OTB", "to": "ERF", "asc": "1", "dist": "10439", "left": "5050", "x": "9536.622", "y": "9163.083", "z": "52.594", "club": "CDR", "con": "", "shotText": "Shot 1 290 yds to right fairway, 140 yds to hole"}, {"n": "2", "pid": "0", "time": "", "putt": "", "t": "S", "prv": "n", "tee": "n", "cup": "n", "from": "OFW", "to": "OGR", "asc": "1", "dist": "5270", "left": "221", "x": "9766.418", "y": "9536.947", "z": "69.071", "club": "CUK", "con": "", "shotText": "Shot 2 146 yds to green, 18 ft 5 in. to hole"}, {"n": "3", "pid": "0", "time": "", "putt": "1", "t": "S", "prv": "n", "tee": "n", "cup": "n", "from": "OGR", "to": "OGR", "asc": "1", "dist": "230", "left": "8", "x": "9760.623", "y": "9518.641", "z": "68.716", "club": "CUK", "con": "", "shotText": "Shot 3 putt 19 ft 2 in., 8 in. to hole"}, {"n": "4", "pid": "0", "time": "", "putt": "2", "t": "S", "prv": "n", "tee": "n", "cup": "y", "from": "OGR", "to": "hole", "asc": "1", "dist": "8", "left": "0", "x": "0", "y": "0", "z": "0", "club": "CUK", "con": "", "shotText": "Shot 4 in the hole"}]}, {"n": "18", "cNum": "18", "sc": "5", "pDay": "0", "pTot": "-1", "shots": [{"n": "1", "pid": "0", "time": "", "putt": "", "t": "S", "prv": "n", "tee": "y", "cup": "n", "from": "OTB", "to": "ELF", "asc": "1", "dist": "10292", "left": "9925", "x": "9709.723", "y": "10265.952", "z": "66.316", "club": "CDR", "con": "", "shotText": "Shot 1 286 yds to left fairway, 276 yds to hole"}, {"n": "2", "pid": "0", "time": "", "putt": "", "t": "S", "prv": "n", "tee": "n", "cup": "n", "from": "OFW", "to": "ERR", "asc": "1", "dist": "7761", "left": "2298", "x": "9730.318", "y": "10912.329", "z": "68.731", "club": "CUK", "con": "", "shotText": "Shot 2 216 yds to right rough, 64 yds to hole"}, {"n": "3", "pid": "0", "time": "", "putt": "", "t": "S", "prv": "n", "tee": "n", "cup": "n", "from": "ORO", "to": "OGR", "asc": "1", "dist": "2165", "left": "202", "x": "9678.759", "y": "11085.185", "z": "68.098", "club": "CUK", "con": "", "shotText": "Shot 3 60 yds to green, 16 ft 10 in. to hole"}, {"n": "4", "pid": "0", "time": "", "putt": "1", "t": "S", "prv": "n", "tee": "n", "cup": "n", "from": "OGR", "to": "OGR", "asc": "1", "dist": "213", "left": "10", "x": "9662.172", "y": "11091.442", "z": "68.074", "club": "CUK", "con": "", "shotText": "Shot 4 putt 17 ft 9 in., 10 in. to hole"}, {"n": "5", "pid": "0", "time": "", "putt": "2", "t": "S", "prv": "n", "tee": "n", "cup": "y", "from": "OGR", "to": "hole", "asc": "1", "dist": "10", "left": "0", "x": "0", "y": "0", "z": "0", "club": "CUK", "con": "", "shotText": "Shot 5 in the hole"}]}]}, {"n": "3", "holes": [{"n": "1", "cNum": "10", "sc": "4", "pDay": "0", "pTot": "-1", "shots": [{"n": "1", "pid": "0", "time": "", "putt": "", "t": "S", "prv": "n", "tee": "y", "cup": "n", "from": "OTB", "to": "ELR", "asc": "1", "dist": "9689", "left": "5551", "x": "10322.722", "y": "7355.632", "z": "84.237", "club": "CDR", "con": "", "shotText": "Shot 1 269 yds to left rough, 154 yds to hole"}, {"n": "2", "pid": "0", "time": "", "putt": "", "t": "S", "prv": "n", "tee": "n", "cup": "n", "from": "ORO", "to": "OGR", "asc": "1", "dist": "5212", "left": "355", "x": "10284.415", "y": "6922.994", "z": "81.873", "club": "CUK", "con": "", "shotText": "Shot 2 145 yds to green, 29 ft 7 in. to hole"}, {"n": "3", "pid": "0", "time": "", "putt": "1", "t": "S", "prv": "n", "tee": "n", "cup": "n", "from": "OGR", "to": "OGR", "asc": "1", "dist": "424", "left": "82", "x": "10266.543", "y": "6892.488", "z": "81.210", "club": "CUK", "con": "", "shotText": "Shot 3 putt 35 ft 4 in., 6 ft 10 in. to hole"}, {"n": "4", "pid": "0", "time": "", "putt": "2", "t": "S", "prv": "n", "tee": "n", "cup": "y", "from": "OGR", "to": "hole", "asc": "1", "dist": "82", "left": "0", "x": "0", "y": "0", "z": "0", "club": "CUK", "con": "", "shotText": "Shot 4 in the hole"}]}, {"n": "2", "cNum": "11", "sc": "3", "pDay": "0", "pTot": "-1", "shots": [{"n": "1", "pid": "0", "time": "", "putt": "", "t": "S", "prv": "n", "tee": "y", "cup": "n", "from": "OTB", "to": "ERR", "asc": "1", "dist": "7624", "left": "712", "x": "9728.903", "y": "6551.541", "z": "55.225", "club": "CUK", "con": "", "shotText": "Shot 1 212 yds to right rough, 59 ft 4 in. to hole"}, {"n": "2", "pid": "0", "time": "", "putt": "", "t": "S", "prv": "n", "tee": "n", "cup": "n", "from": "ORO", "to": "OGR", "asc": "1", "dist": "730", "left": "18", "x": "9739.349", "y": "6491.573", "z": "55.489", "club": "CUK", "con": "", "shotText": "Shot 2 60 ft 10 in. to green, 18 in. to hole"}, {"n": "3", "pid": "0", "time": "", "putt": "1", "t": "S", "prv": "n", "tee": "n", "cup": "y", "from": "OGR", "to": "hole", "asc": "1", "dist": "18", "left": "0", "x": "0", "y": "0", "z": "0", "club": "CUK", "con": "", "shotText": "Shot 3 in the hole"}]}, {"n": "3", "cNum": "12", "sc": "4", "pDay": "0", "pTot": "-1", "shots": [{"n": "1", "pid": "0", "time": "", "putt": "", "t": "S", "prv": "n", "tee": "y", "cup": "n", "from": "OTB", "to": "ELF", "asc": "1", "dist": "10159", "left": "7485", "x": "8950.648", "y": "6656.056", "z": "39.291", "club": "CDR", "con": "", "shotText": "Shot 1 282 yds to left fairway, 208 yds to hole"}, {"n": "2", "pid": "0", "time": "", "putt": "", "t": "S", "prv": "n", "tee": "n", "cup": "n", "from": "OFW", "to": "ELR", "asc": "1", "dist": "7463", "left": "312", "x": "8394.227", "y": "6933.723", "z": "30.301", "club": "CUK", "con": "", "shotText": "Shot 2 207 yds to left rough, 26 ft 0 in. to hole"}, {"n": "3", "pid": "0", "time": "", "putt": "", "t": "S", "prv": "n", "tee": "n", "cup": "n", "from": "ORO", "to": "OGR", "asc": "1", "dist": "370", "left": "62", "x": "8408.994", "y": "6960.744", "z": "29.892", "club": "CUK", "con": "", "shotText": "Shot 3 30 ft 10 in. to green, 5 ft 2 in. to hole"}, {"n": "4", "pid": "0", "time": "", "putt": "1", "t": "S", "prv": "n", "tee": "n", "cup": "y", "from": "OGR", "to": "hole", "asc": "1", "dist": "62", "left": "0", "x": "0", "y": "0", "z": "0", "club": "CUK", "con": "", "shotText": "Shot 4 in the hole"}]}, {"n": "4", "cNum": "13", "sc": "4", "pDay": "-1", "pTot": "-2", "shots": [{"n": "1", "pid": "0", "time": "", "putt": "", "t": "S", "prv": "n", "tee": "y", "cup": "n", "from": "OTB", "to": "ERF", "asc": "1", "dist": "10090", "left": "9529", "x": "9095.442", "y": "6979.808", "z": "32.098", "club": "CDR", "con": "", "shotText": "Shot 1 280 yds to right fairway, 265 yds to hole"}, {"n": "2", "pid": "0", "time": "", "putt": "", "t": "S", "prv": "n", "tee": "n", "cup": "n", "from": "OFW", "to": "EG3", "asc": "1", "dist": "8354", "left": "1211", "x": "9760.360", "y": "6773.810", "z": "40.222", "club": "CUK", "con": "", "shotText": "Shot 2 232 yds to right front green side bunker, 34 yds to hole"}, {"n": "3", "pid": "0", "time": "", "putt": "", "t": "S", "prv": "n", "tee": "n", "cup": "n", "from": "OGS", "to": "OGR", "asc": "1", "dist": "1307", "left": "93", "x": "9868.208", "y": "6767.166", "z": "53.912", "club": "CUK", "con": "", "shotText": "Shot 3 36 yds to green, 7 ft 9 in. to hole"}, {"n": "4", "pid": "0", "time": "", "putt": "1", "t": "S", "prv": "n", "tee": "n", "cup": "y", "from": "OGR", "to": "hole", "asc": "1", "dist": "93", "left": "0", "x": "0", "y": "0", "z": "0", "club": "CUK", "con": "", "shotText": "Shot 4 in the hole"}]}, {"n": "5", "cNum": "14", "sc": "3", "pDay": "-2", "pTot": "-3", "shots": [{"n": "1", "pid": "0", "time": "", "putt": "", "t": "S", "prv": "n", "tee": "y", "cup": "n", "from": "OTB", "to": "ERR", "asc": "1", "dist": "9897", "left": "6208", "x": "9926.176", "y": "7572.784", "z": "56.788", "club": "CDR", "con": "", "shotText": "Shot 1 275 yds to right rough, 172 yds to hole"}, {"n": "2", "pid": "0", "time": "", "putt": "", "t": "S", "prv": "n", "tee": "n", "cup": "n", "from": "ORO", "to": "OGR", "asc": "1", "dist": "5953", "left": "256", "x": "9575.701", "y": "7923.770", "z": "48.673", "club": "CUK", "con": "", "shotText": "Shot 2 165 yds to green, 21 ft 4 in. to hole"}, {"n": "3", "pid": "0", "time": "", "putt": "1", "t": "S", "prv": "n", "tee": "n", "cup": "y", "from": "OGR", "to": "hole", "asc": "1", "dist": "256", "left": "0", "x": "0", "y": "0", "z": "0", "club": "CUK", "con": "", "shotText": "Shot 3 in the hole"}]}, {"n": "6", "cNum": "15", "sc": "5", "pDay": "-1", "pTot": "-2", "shots": [{"n": "1", "pid": "0", "time": "", "putt": "", "t": "S", "prv": "n", "tee": "y", "cup": "n", "from": "OTB", "to": "ERF", "asc": "1", "dist": "10023", "left": "6950", "x": "9923.725", "y": "8316.737", "z": "55.962", "club": "CDR", "con": "", "shotText": "Shot 1 278 yds to right fairway, 193 yds to hole"}, {"n": "2", "pid": "0", "time": "", "putt": "", "t": "S", "prv": "n", "tee": "n", "cup": "n", "from": "OFW", "to": "ELR", "asc": "1", "dist": "6982", "left": "843", "x": "9703.277", "y": "8855.227", "z": "58.268", "club": "CUK", "con": "", "shotText": "Shot 2 194 yds to left rough, 70 ft 3 in. to hole"}, {"n": "3", "pid": "0", "time": "", "putt": "", "t": "S", "prv": "n", "tee": "n", "cup": "n", "from": "ORO", "to": "OGR", "asc": "1", "dist": "740", "left": "116", "x": "9763.303", "y": "8868.865", "z": "61.681", "club": "CUK", "con": "", "shotText": "Shot 3 61 ft 8 in. to green, 9 ft 8 in. to hole"}, {"n": "4", "pid": "0", "time": "", "putt": "1", "t": "S", "prv": "n", "tee": "n", "cup": "n", "from": "OGR", "to": "OGR", "asc": "1", "dist": "139", "left": "18", "x": "9771.983", "y": "8876.492", "z": "62.019", "club": "CUK", "con": "", "shotText": "Shot 4 putt 11 ft 7 in., 18 in. to hole"}, {"n": "5", "pid": "0", "time": "", "putt": "2", "t": "S", "prv": "n", "tee": "n", "cup": "y", "from": "OGR", "to": "hole", "asc": "1", "dist": "18", "left": "0", "x": "0", "y": "0", "z": "0", "club": "CUK", "con": "", "shotText": "Shot 5 in the hole"}]}, {"n": "7", "cNum": "16", "sc": "2", "pDay": "-2", "pTot": "-3", "shots": [{"n": "1", "pid": "0", "time": "", "putt": "", "t": "S", "prv": "n", "tee": "y", "cup": "n", "from": "OTB", "to": "OGR", "asc": "1", "dist": "6699", "left": "148", "x": "9088.507", "y": "8390.376", "z": "42.906", "club": "CUK", "con": "", "shotText": "Shot 1 186 yds to green, 12 ft 4 in. to hole"}, {"n": "2", "pid": "0", "time": "", "putt": "1", "t": "S", "prv": "n", "tee": "n", "cup": "y", "from": "OGR", "to": "hole", "asc": "1", "dist": "148", "left": "0", "x": "0", "y": "0", "z": "0", "club": "CUK", "con": "", "shotText": "Shot 2 in the hole"}]}, {"n": "8", "cNum": "17", "sc": "4", "pDay": "-2", "pTot": "-3", "shots": [{"n": "1", "pid": "0", "time": "", "putt": "", "t": "S", "prv": "n", "tee": "y", "cup": "n", "from": "OTB", "to": "ELF", "asc": "1", "dist": "10100", "left": "5635", "x": "9507.688", "y": "9145.296", "z": "51.939", "club": "CDR", "con": "", "shotText": "Shot 1 281 yds to left fairway, 157 yds to hole"}, {"n": "2", "pid": "0", "time": "", "putt": "", "t": "S", "prv": "n", "tee": "n", "cup": "n", "from": "OFW", "to": "OGR", "asc": "1", "dist": "5491", "left": "144", "x": "9731.757", "y": "9543.980", "z": "67.938", "club": "CUK", "con": "", "shotText": "Shot 2 153 yds to green, 12 ft 0 in. to hole"}, {"n": "3", "pid": "0", "time": "", "putt": "1", "t": "S", "prv": "n", "tee": "n", "cup": "n", "from": "OGR", "to": "OGR", "asc": "1", "dist": "152", "left": "6", "x": "9738.313", "y": "9554.834", "z": "68.007", "club": "CUK", "con": "", "shotText": "Shot 3 putt 12 ft 8 in., 6 in. to hole"}, {"n": "4", "pid": "0", "time": "", "putt": "2", "t": "S", "prv": "n", "tee": "n", "cup": "y", "from": "OGR", "to": "hole", "asc": "1", "dist": "6", "left": "0", "x": "0", "y": "0", "z": "0", "club": "CUK", "con": "", "shotText": "Shot 4 in the hole"}]}, {"n": "9", "cNum": "18", "sc": "5", "pDay": "-2", "pTot": "-3", "shots": [{"n": "1", "pid": "0", "time": "", "putt": "", "t": "S", "prv": "n", "tee": "y", "cup": "n", "from": "OTB", "to": "OST", "asc": "1", "dist": "10491", "left": "9299", "x": "9790.395", "y": "10367.439", "z": "69.566", "club": "CDR", "con": "", "shotText": "Shot 1 291 yds to fairway bunker, 258 yds to hole"}, {"n": "2", "pid": "0", "time": "", "putt": "", "t": "S", "prv": "n", "tee": "n", "cup": "n", "from": "OST", "to": "ELF", "asc": "1", "dist": "4888", "left": "4498", "x": "9676.954", "y": "10758.584", "z": "64.641", "club": "CUK", "con": "", "shotText": "Shot 2 136 yds to left fairway, 125 yds to hole"}, {"n": "3", "pid": "0", "time": "", "putt": "", "t": "S", "prv": "n", "tee": "n", "cup": "n", "from": "OFW", "to": "OGR", "asc": "1", "dist": "4479", "left": "221", "x": "9653.921", "y": "11131.122", "z": "69.208", "club": "CUK", "con": "", "shotText": "Shot 3 124 yds to green, 18 ft 5 in. to hole"}, {"n": "4", "pid": "0", "time": "", "putt": "1", "t": "S", "prv": "n", "tee": "n", "cup": "n", "from": "OGR", "to": "OGR", "asc": "1", "dist": "260", "left": "36", "x": "9675.485", "y": "11133.098", "z": "69.398", "club": "CUK", "con": "", "shotText": "Shot 4 putt 21 ft 8 in., 3 ft 0 in. to hole"}, {"n": "5", "pid": "0", "time": "", "putt": "2", "t": "S", "prv": "n", "tee": "n", "cup": "y", "from": "OGR", "to": "hole", "asc": "1", "dist": "36", "left": "0", "x": "0", "y": "0", "z": "0", "club": "CUK", "con": "", "shotText": "Shot 5 in the hole"}]}, {"n": "10", "cNum": "1", "sc": "4", "pDay": "-2", "pTot": "-3", "shots": [{"n": "1", "pid": "0", "time": "", "putt": "", "t": "S", "prv": "n", "tee": "y", "cup": "n", "from": "OTB", "to": "ELF", "asc": "1", "dist": "10098", "left": "5592", "x": "8967.755", "y": "10853.751", "z": "53.019", "club": "CDR", "con": "", "shotText": "Shot 1 281 yds to left fairway, 155 yds to hole"}, {"n": "2", "pid": "0", "time": "", "putt": "", "t": "S", "prv": "n", "tee": "n", "cup": "n", "from": "OFW", "to": "OGR", "asc": "1", "dist": "5660", "left": "123", "x": "8513.712", "y": "10725.957", "z": "51.976", "club": "CUK", "con": "", "shotText": "Shot 2 157 yds to green, 10 ft 3 in. to hole"}, {"n": "3", "pid": "0", "time": "", "putt": "1", "t": "S", "prv": "n", "tee": "n", "cup": "n", "from": "OGR", "to": "OGR", "asc": "1", "dist": "134", "left": "8", "x": "8517.175", "y": "10736.590", "z": "51.877", "club": "CUK", "con": "", "shotText": "Shot 3 putt 11 ft 2 in., 8 in. to hole"}, {"n": "4", "pid": "0", "time": "", "putt": "2", "t": "S", "prv": "n", "tee": "n", "cup": "y", "from": "OGR", "to": "hole", "asc": "1", "dist": "8", "left": "0", "x": "0", "y": "0", "z": "0", "club": "CUK", "con": "", "shotText": "Shot 4 in the hole"}]}, {"n": "11", "cNum": "2", "sc": "4", "pDay": "-2", "pTot": "-3", "shots": [{"n": "1", "pid": "0", "time": "", "putt": "", "t": "S", "prv": "n", "tee": "y", "cup": "n", "from": "OTB", "to": "ERI", "asc": "1", "dist": "9374", "left": "4712", "x": "8290.510", "y": "10111.600", "z": "46.247", "club": "CFW", "con": "", "shotText": "Shot 1 260 yds to right intermediate, 131 yds to hole"}, {"n": "2", "pid": "0", "time": "", "putt": "", "t": "S", "prv": "n", "tee": "n", "cup": "n", "from": "OIR", "to": "OGR", "asc": "1", "dist": "4598", "left": "192", "x": "8244.636", "y": "9731.198", "z": "43.015", "club": "CUK", "con": "", "shotText": "Shot 2 128 yds to green, 16 ft 0 in. to hole"}, {"n": "3", "pid": "0", "time": "", "putt": "1", "t": "S", "prv": "n", "tee": "n", "cup": "n", "from": "OGR", "to": "OGR", "asc": "1", "dist": "193", "left": "8", "x": "8255.840", "y": "9719.690", "z": "43.223", "club": "CUK", "con": "", "shotText": "Shot 3 putt 16 ft 1 in., 8 in. to hole"}, {"n": "4", "pid": "0", "time": "", "putt": "2", "t": "S", "prv": "n", "tee": "n", "cup": "y", "from": "OGR", "to": "hole", "asc": "1", "dist": "8", "left": "0", "x": "0", "y": "0", "z": "0", "club": "CUK", "con": "", "shotText": "Shot 4 in the hole"}]}, {"n": "12", "cNum": "3", "sc": "4", "pDay": "-1", "pTot": "-2", "shots": [{"n": "1", "pid": "0", "time": "", "putt": "", "t": "S", "prv": "n", "tee": "y", "cup": "n", "from": "OTB", "to": "OGR", "asc": "1", "dist": "6084", "left": "618", "x": "8058.598", "y": "9037.411", "z": "3.467", "club": "CUK", "con": "", "shotText": "Shot 1 169 yds to green, 51 ft 6 in. to hole"}, {"n": "2", "pid": "0", "time": "", "putt": "1", "t": "S", "prv": "n", "tee": "n", "cup": "n", "from": "OGR", "to": "OGR", "asc": "1", "dist": "783", "left": "161", "x": "8108.318", "y": "9079.674", "z": "4.124", "club": "CUK", "con": "", "shotText": "Shot 2 putt 65 ft 3 in., 13 ft 5 in. to hole"}, {"n": "3", "pid": "0", "time": "", "putt": "2", "t": "S", "prv": "n", "tee": "n", "cup": "n", "from": "OGR", "to": "OGR", "asc": "1", "dist": "184", "left": "18", "x": "8097.149", "y": "9069.187", "z": "3.839", "club": "CUK", "con": "", "shotText": "Shot 3 putt 15 ft 4 in., 18 in. to hole"}, {"n": "4", "pid": "0", "time": "", "putt": "3", "t": "S", "prv": "n", "tee": "n", "cup": "y", "from": "OGR", "to": "hole", "asc": "1", "dist": "18", "left": "0", "x": "0", "y": "0", "z": "0", "club": "CUK", "con": "", "shotText": "Shot 4 in the hole"}]}, {"n": "13", "cNum": "4", "sc": "4", "pDay": "-1", "pTot": "-2", "shots": [{"n": "1", "pid": "0", "time": "", "putt": "", "t": "S", "prv": "n", "tee": "y", "cup": "n", "from": "OTB", "to": "ERI", "asc": "1", "dist": "9907", "left": "7044", "x": "7805.087", "y": "10120.268", "z": "14.944", "club": "CDR", "con": "", "shotText": "Shot 1 275 yds to right intermediate, 196 yds to hole"}, {"n": "2", "pid": "0", "time": "", "putt": "", "t": "S", "prv": "n", "tee": "n", "cup": "n", "from": "OIR", "to": "OGR", "asc": "1", "dist": "7012", "left": "107", "x": "7698.635", "y": "10694.815", "z": "14.780", "club": "CUK", "con": "", "shotText": "Shot 2 195 yds to green, 8 ft 11 in. to hole"}, {"n": "3", "pid": "0", "time": "", "putt": "1", "t": "S", "prv": "n", "tee": "n", "cup": "n", "from": "OGR", "to": "OGR", "asc": "1", "dist": "138", "left": "29", "x": "7709.254", "y": "10699.153", "z": "14.860", "club": "CUK", "con": "", "shotText": "Shot 3 putt 11 ft 6 in., 2 ft 5 in. to hole"}, {"n": "4", "pid": "0", "time": "", "putt": "2", "t": "S", "prv": "n", "tee": "n", "cup": "y", "from": "OGR", "to": "hole", "asc": "1", "dist": "29", "left": "0", "x": "0", "y": "0", "z": "0", "club": "CUK", "con": "", "shotText": "Shot 4 in the hole"}]}, {"n": "14", "cNum": "5", "sc": "4", "pDay": "-1", "pTot": "-2", "shots": [{"n": "1", "pid": "0", "time": "", "putt": "", "t": "S", "prv": "n", "tee": "y", "cup": "n", "from": "OTB", "to": "ERF", "asc": "1", "dist": "10129", "left": "6525", "x": "8014.967", "y": "10026.340", "z": "20.270", "club": "CDR", "con": "", "shotText": "Shot 1 281 yds to right fairway, 181 yds to hole"}, {"n": "2", "pid": "0", "time": "", "putt": "", "t": "S", "prv": "n", "tee": "n", "cup": "n", "from": "OFW", "to": "OGR", "asc": "1", "dist": "6493", "left": "143", "x": "8023.503", "y": "9485.353", "z": "17.289", "club": "CUK", "con": "", "shotText": "Shot 2 180 yds to green, 11 ft 11 in. to hole"}, {"n": "3", "pid": "0", "time": "", "putt": "1", "t": "S", "prv": "n", "tee": "n", "cup": "n", "from": "OGR", "to": "OGR", "asc": "1", "dist": "163", "left": "20", "x": "8010.086", "y": "9483.148", "z": "17.275", "club": "CUK", "con": "", "shotText": "Shot 3 putt 13 ft 7 in., 20 in. to hole"}, {"n": "4", "pid": "0", "time": "", "putt": "2", "t": "S", "prv": "n", "tee": "n", "cup": "y", "from": "OGR", "to": "hole", "asc": "1", "dist": "20", "left": "0", "x": "0", "y": "0", "z": "0", "club": "CUK", "con": "", "shotText": "Shot 4 in the hole"}]}, {"n": "15", "cNum": "6", "sc": "4", "pDay": "-2", "pTot": "-3", "shots": [{"n": "1", "pid": "0", "time": "", "putt": "", "t": "S", "prv": "n", "tee": "y", "cup": "n", "from": "OTB", "to": "ERF", "asc": "1", "dist": "10488", "left": "9805", "x": "8728.692", "y": "10298.076", "z": "52.296", "club": "CDR", "con": "", "shotText": "Shot 1 291 yds to right fairway, 272 yds to hole"}, {"n": "2", "pid": "0", "time": "", "putt": "", "t": "S", "prv": "n", "tee": "n", "cup": "n", "from": "OFW", "to": "OGR", "asc": "1", "dist": "9506", "left": "401", "x": "9350.994", "y": "10788.212", "z": "59.380", "club": "CUK", "con": "", "shotText": "Shot 2 264 yds to green, 33 ft 5 in. to hole"}, {"n": "3", "pid": "0", "time": "", "putt": "1", "t": "S", "prv": "n", "tee": "n", "cup": "n", "from": "OGR", "to": "OGR", "asc": "1", "dist": "447", "left": "47", "x": "9355.049", "y": "10825.233", "z": "60.090", "club": "CUK", "con": "", "shotText": "Shot 3 putt 37 ft 3 in., 3 ft 11 in. to hole"}, {"n": "4", "pid": "0", "time": "", "putt": "2", "t": "S", "prv": "n", "tee": "n", "cup": "y", "from": "OGR", "to": "hole", "asc": "1", "dist": "47", "left": "0", "x": "0", "y": "0", "z": "0", "club": "CUK", "con": "", "shotText": "Shot 4 in the hole"}]}, {"n": "16", "cNum": "7", "sc": "4", "pDay": "-2", "pTot": "-3", "shots": [{"n": "1", "pid": "0", "time": "", "putt": "", "t": "S", "prv": "n", "tee": "y", "cup": "n", "from": "OTB", "to": "ERF", "asc": "1", "dist": "10271", "left": "6084", "x": "9357.385", "y": "10076.388", "z": "50.189", "club": "CDR", "con": "", "shotText": "Shot 1 285 yds to right fairway, 169 yds to hole"}, {"n": "2", "pid": "0", "time": "", "putt": "", "t": "S", "prv": "n", "tee": "n", "cup": "n", "from": "OFW", "to": "OGR", "asc": "1", "dist": "5584", "left": "648", "x": "9130.549", "y": "9670.154", "z": "42.181", "club": "CUK", "con": "", "shotText": "Shot 2 155 yds to green, 54 ft 0 in. to hole"}, {"n": "3", "pid": "0", "time": "", "putt": "1", "t": "S", "prv": "n", "tee": "n", "cup": "n", "from": "OGR", "to": "OGR", "asc": "1", "dist": "634", "left": "38", "x": "9081.817", "y": "9649.820", "z": "43.445", "club": "CUK", "con": "", "shotText": "Shot 3 putt 52 ft 10 in., 3 ft 2 in. to hole"}, {"n": "4", "pid": "0", "time": "", "putt": "2", "t": "S", "prv": "n", "tee": "n", "cup": "y", "from": "OGR", "to": "hole", "asc": "1", "dist": "38", "left": "0", "x": "0", "y": "0", "z": "0", "club": "CUK", "con": "", "shotText": "Shot 4 in the hole"}]}, {"n": "17", "cNum": "8", "sc": "3", "pDay": "-2", "pTot": "-3", "shots": [{"n": "1", "pid": "0", "time": "", "putt": "", "t": "S", "prv": "n", "tee": "y", "cup": "n", "from": "OTB", "to": "OGR", "asc": "1", "dist": "6148", "left": "212", "x": "9658.415", "y": "9745.608", "z": "66.148", "club": "CUK", "con": "", "shotText": "Shot 1 171 yds to green, 17 ft 8 in. to hole"}, {"n": "2", "pid": "0", "time": "", "putt": "1", "t": "S", "prv": "n", "tee": "n", "cup": "n", "from": "OGR", "to": "OGR", "asc": "1", "dist": "255", "left": "39", "x": "9645.513", "y": "9762.517", "z": "65.370", "club": "CUK", "con": "", "shotText": "Shot 2 putt 21 ft 3 in., 3 ft 3 in. to hole"}, {"n": "3", "pid": "0", "time": "", "putt": "2", "t": "S", "prv": "n", "tee": "n", "cup": "y", "from": "OGR", "to": "hole", "asc": "1", "dist": "39", "left": "0", "x": "0", "y": "0", "z": "0", "club": "CUK", "con": "", "shotText": "Shot 3 in the hole"}]}, {"n": "18", "cNum": "9", "sc": "5", "pDay": "-2", "pTot": "-3", "shots": [{"n": "1", "pid": "0", "time": "", "putt": "", "t": "S", "prv": "n", "tee": "y", "cup": "n", "from": "OTB", "to": "ERF", "asc": "1", "dist": "10714", "left": "11638", "x": "10075.753", "y": "8992.356", "z": "74.506", "club": "CDR", "con": "", "shotText": "Shot 1 298 yds to right fairway, 323 yds to hole"}, {"n": "2", "pid": "0", "time": "", "putt": "", "t": "S", "prv": "n", "tee": "n", "cup": "n", "from": "OFW", "to": "ERI", "asc": "1", "dist": "9060", "left": "2681", "x": "10087.800", "y": "8237.520", "z": "63.635", "club": "CUK", "con": "", "shotText": "Shot 2 252 yds to right intermediate, 74 yds to hole"}, {"n": "3", "pid": "0", "time": "", "putt": "", "t": "S", "prv": "n", "tee": "n", "cup": "n", "from": "OIR", "to": "OGR", "asc": "1", "dist": "2280", "left": "414", "x": "10141.538", "y": "8055.332", "z": "68.980", "club": "CUK", "con": "", "shotText": "Shot 3 63 yds to green, 34 ft 6 in. to hole"}, {"n": "4", "pid": "0", "time": "", "putt": "1", "t": "S", "prv": "n", "tee": "n", "cup": "n", "from": "OGR", "to": "OGR", "asc": "1", "dist": "409", "left": "6", "x": "10159.418", "y": "8026.387", "z": "70.742", "club": "CUK", "con": "", "shotText": "Shot 4 putt 34 ft 1 in., 6 in. to hole"}, {"n": "5", "pid": "0", "time": "", "putt": "2", "t": "S", "prv": "n", "tee": "n", "cup": "y", "from": "OGR", "to": "hole", "asc": "1", "dist": "6", "left": "0", "x": "0", "y": "0", "z": "0", "club": "CUK", "con": "", "shotText": "Shot 5 in the hole"}]}]}, {"n": "4", "holes": [{"n": "1", "cNum": "1", "sc": "5", "pDay": "1", "pTot": "-2", "shots": [{"n": "1", "pid": "0", "time": "", "putt": "", "t": "S", "prv": "n", "tee": "y", "cup": "n", "from": "OTB", "to": "ELF", "asc": "1", "dist": "10324", "left": "6062", "x": "8950.852", "y": "10859.496", "z": "53.099", "club": "CDR", "con": "", "shotText": "Shot 1 287 yds to left fairway, 168 yds to hole"}, {"n": "2", "pid": "0", "time": "", "putt": "", "t": "S", "prv": "n", "tee": "n", "cup": "n", "from": "OFW", "to": "OGR", "asc": "1", "dist": "5667", "left": "476", "x": "8494.290", "y": "10738.773", "z": "52.448", "club": "CUK", "con": "", "shotText": "Shot 2 157 yds to green, 39 ft 8 in. to hole"}, {"n": "3", "pid": "0", "time": "", "putt": "1", "t": "S", "prv": "n", "tee": "n", "cup": "n", "from": "OGR", "to": "OGR", "asc": "1", "dist": "541", "left": "61", "x": "8452.059", "y": "10754.431", "z": "53.404", "club": "CUK", "con": "", "shotText": "Shot 3 putt 45 ft 1 in., 5 ft 1 in. to hole"}, {"n": "4", "pid": "0", "time": "", "putt": "2", "t": "S", "prv": "n", "tee": "n", "cup": "n", "from": "OGR", "to": "OGR", "asc": "1", "dist": "84", "left": "19", "x": "8458.393", "y": "10751.544", "z": "53.394", "club": "CUK", "con": "", "shotText": "Shot 4 putt 7 ft 0 in., 19 in. to hole"}, {"n": "5", "pid": "0", "time": "", "putt": "3", "t": "S", "prv": "n", "tee": "n", "cup": "y", "from": "OGR", "to": "hole", "asc": "1", "dist": "19", "left": "0", "x": "0", "y": "0", "z": "0", "club": "CUK", "con": "", "shotText": "Shot 5 in the hole"}]}, {"n": "2", "cNum": "2", "sc": "4", "pDay": "1", "pTot": "-2", "shots": [{"n": "1", "pid": "0", "time": "", "putt": "", "t": "S", "prv": "n", "tee": "y", "cup": "n", "from": "OTB", "to": "ERF", "asc": "1", "dist": "8937", "left": "5206", "x": "8316.939", "y": "10153.528", "z": "48.736", "club": "CFW", "con": "", "shotText": "Shot 1 248 yds to right fairway, 145 yds to hole"}, {"n": "2", "pid": "0", "time": "", "putt": "", "t": "S", "prv": "n", "tee": "n", "cup": "n", "from": "OFW", "to": "OGR", "asc": "1", "dist": "5109", "left": "186", "x": "8315.741", "y": "9727.761", "z": "45.126", "club": "CUK", "con": "", "shotText": "Shot 2 142 yds to green, 15 ft 6 in. to hole"}, {"n": "3", "pid": "0", "time": "", "putt": "1", "t": "S", "prv": "n", "tee": "n", "cup": "n", "from": "OGR", "to": "OGR", "asc": "1", "dist": "242", "left": "52", "x": "8298.100", "y": "9718.019", "z": "44.868", "club": "CUK", "con": "", "shotText": "Shot 3 putt 20 ft 2 in., 4 ft 4 in. to hole"}, {"n": "4", "pid": "0", "time": "", "putt": "2", "t": "S", "prv": "n", "tee": "n", "cup": "y", "from": "OGR", "to": "hole", "asc": "1", "dist": "52", "left": "0", "x": "0", "y": "0", "z": "0", "club": "CUK", "con": "", "shotText": "Shot 4 in the hole"}]}, {"n": "3", "cNum": "3", "sc": "3", "pDay": "1", "pTot": "-2", "shots": [{"n": "1", "pid": "0", "time": "", "putt": "", "t": "S", "prv": "n", "tee": "y", "cup": "n", "from": "OTB", "to": "OGR", "asc": "1", "dist": "6849", "left": "162", "x": "8031.976", "y": "9106.740", "z": "1.807", "club": "CUK", "con": "", "shotText": "Shot 1 190 yds to green, 13 ft 6 in. to hole"}, {"n": "2", "pid": "0", "time": "", "putt": "1", "t": "S", "prv": "n", "tee": "n", "cup": "n", "from": "OGR", "to": "OGR", "asc": "1", "dist": "192", "left": "28", "x": "8045.134", "y": "9097.577", "z": "1.547", "club": "CUK", "con": "", "shotText": "Shot 2 putt 16 ft 0 in., 2 ft 4 in. to hole"}, {"n": "3", "pid": "0", "time": "", "putt": "2", "t": "S", "prv": "n", "tee": "n", "cup": "y", "from": "OGR", "to": "hole", "asc": "1", "dist": "28", "left": "0", "x": "0", "y": "0", "z": "0", "club": "CUK", "con": "", "shotText": "Shot 3 in the hole"}]}, {"n": "4", "cNum": "4", "sc": "4", "pDay": "1", "pTot": "-2", "shots": [{"n": "1", "pid": "0", "time": "", "putt": "", "t": "S", "prv": "n", "tee": "y", "cup": "n", "from": "OTB", "to": "ERF", "asc": "1", "dist": "10445", "left": "5992", "x": "7760.131", "y": "10210.185", "z": "11.375", "club": "CDR", "con": "", "shotText": "Shot 1 290 yds to right fairway, 166 yds to hole"}, {"n": "2", "pid": "0", "time": "", "putt": "", "t": "S", "prv": "n", "tee": "n", "cup": "n", "from": "OFW", "to": "OGR", "asc": "1", "dist": "6026", "left": "77", "x": "7666.221", "y": "10703.446", "z": "14.883", "club": "CUK", "con": "", "shotText": "Shot 2 167 yds to green, 6 ft 5 in. to hole"}, {"n": "3", "pid": "0", "time": "", "putt": "1", "t": "S", "prv": "n", "tee": "n", "cup": "n", "from": "OGR", "to": "OGR", "asc": "1", "dist": "124", "left": "42", "x": "7657.543", "y": "10697.908", "z": "14.623", "club": "CUK", "con": "", "shotText": "Shot 3 putt 10 ft 4 in., 3 ft 6 in. to hole"}, {"n": "4", "pid": "0", "time": "", "putt": "2", "t": "S", "prv": "n", "tee": "n", "cup": "y", "from": "OGR", "to": "hole", "asc": "1", "dist": "42", "left": "0", "x": "0", "y": "0", "z": "0", "club": "CUK", "con": "", "shotText": "Shot 4 in the hole"}]}, {"n": "5", "cNum": "5", "sc": "4", "pDay": "1", "pTot": "-2", "shots": [{"n": "1", "pid": "0", "time": "", "putt": "", "t": "S", "prv": "n", "tee": "y", "cup": "n", "from": "OTB", "to": "ELF", "asc": "1", "dist": "10018", "left": "5717", "x": "8042.256", "y": "10034.155", "z": "22.120", "club": "CDR", "con": "", "shotText": "Shot 1 278 yds to left fairway, 159 yds to hole"}, {"n": "2", "pid": "0", "time": "", "putt": "", "t": "S", "prv": "n", "tee": "n", "cup": "n", "from": "OFW", "to": "ELF", "asc": "1", "dist": "5390", "left": "329", "x": "8048.123", "y": "9585.083", "z": "14.495", "club": "CUK", "con": "", "shotText": "Shot 2 150 yds to left fairway, 27 ft 5 in. to hole"}, {"n": "3", "pid": "0", "time": "", "putt": "", "t": "S", "prv": "n", "tee": "n", "cup": "n", "from": "OFW", "to": "OGR", "asc": "1", "dist": "316", "left": "15", "x": "8045.322", "y": "9558.955", "z": "15.535", "club": "CUK", "con": "", "shotText": "Shot 3 26 ft 4 in. to green, 15 in. to hole"}, {"n": "4", "pid": "0", "time": "", "putt": "1", "t": "S", "prv": "n", "tee": "n", "cup": "y", "from": "OGR", "to": "hole", "asc": "1", "dist": "15", "left": "0", "x": "0", "y": "0", "z": "0", "club": "CUK", "con": "", "shotText": "Shot 4 in the hole"}]}, {"n": "6", "cNum": "6", "sc": "5", "pDay": "1", "pTot": "-2", "shots": [{"n": "1", "pid": "0", "time": "", "putt": "", "t": "S", "prv": "n", "tee": "y", "cup": "n", "from": "OTB", "to": "ERR", "asc": "1", "dist": "10981", "left": "9004", "x": "8794.135", "y": "10316.420", "z": "51.462", "club": "CDR", "con": "", "shotText": "Shot 1 305 yds to right rough, 250 yds to hole"}, {"n": "2", "pid": "0", "time": "", "putt": "", "t": "S", "prv": "n", "tee": "n", "cup": "n", "from": "ORO", "to": "ERR", "asc": "1", "dist": "7726", "left": "1300", "x": "9292.005", "y": "10724.613", "z": "54.018", "club": "CUK", "con": "", "shotText": "Shot 2 215 yds to right rough, 36 yds to hole"}, {"n": "3", "pid": "0", "time": "", "putt": "", "t": "S", "prv": "n", "tee": "n", "cup": "n", "from": "ORO", "to": "OGR", "asc": "1", "dist": "1223", "left": "76", "x": "9357.352", "y": "10802.648", "z": "59.952", "club": "CUK", "con": "", "shotText": "Shot 3 34 yds to green, 6 ft 4 in. to hole"}, {"n": "4", "pid": "0", "time": "", "putt": "1", "t": "S", "prv": "n", "tee": "n", "cup": "n", "from": "OGR", "to": "OGR", "asc": "1", "dist": "98", "left": "17", "x": "9362.564", "y": "10808.909", "z": "60.124", "club": "CUK", "con": "", "shotText": "Shot 4 putt 8 ft 2 in., 17 in. to hole"}, {"n": "5", "pid": "0", "time": "", "putt": "2", "t": "S", "prv": "n", "tee": "n", "cup": "y", "from": "OGR", "to": "hole", "asc": "1", "dist": "17", "left": "0", "x": "0", "y": "0", "z": "0", "club": "CUK", "con": "", "shotText": "Shot 5 in the hole"}]}, {"n": "7", "cNum": "7", "sc": "5", "pDay": "2", "pTot": "-1", "shots": [{"n": "1", "pid": "0", "time": "", "putt": "", "t": "S", "prv": "n", "tee": "y", "cup": "n", "from": "OTB", "to": "ELF", "asc": "1", "dist": "9807", "left": "7209", "x": "9403.054", "y": "10116.305", "z": "54.566", "club": "CDR", "con": "", "shotText": "Shot 1 272 yds to left fairway, 200 yds to hole"}, {"n": "2", "pid": "0", "time": "", "putt": "", "t": "S", "prv": "n", "tee": "n", "cup": "n", "from": "OFW", "to": "OGR", "asc": "1", "dist": "7198", "left": "383", "x": "9068.987", "y": "9618.236", "z": "44.365", "club": "CUK", "con": "", "shotText": "Shot 2 200 yds to green, 31 ft 11 in. to hole"}, {"n": "3", "pid": "0", "time": "", "putt": "1", "t": "S", "prv": "n", "tee": "n", "cup": "n", "from": "OGR", "to": "OGR", "asc": "1", "dist": "454", "left": "69", "x": "9038.350", "y": "9640.453", "z": "44.388", "club": "CUK", "con": "", "shotText": "Shot 3 putt 37 ft 10 in., 5 ft 9 in. to hole"}, {"n": "4", "pid": "0", "time": "", "putt": "2", "t": "S", "prv": "n", "tee": "n", "cup": "n", "from": "OGR", "to": "OGR", "asc": "1", "dist": "80", "left": "6", "x": "9042.451", "y": "9635.234", "z": "44.441", "club": "CUK", "con": "", "shotText": "Shot 4 putt 6 ft 8 in., 6 in. to hole"}, {"n": "5", "pid": "0", "time": "", "putt": "3", "t": "S", "prv": "n", "tee": "n", "cup": "y", "from": "OGR", "to": "hole", "asc": "1", "dist": "6", "left": "0", "x": "0", "y": "0", "z": "0", "club": "CUK", "con": "", "shotText": "Shot 5 in the hole"}]}, {"n": "8", "cNum": "8", "sc": "3", "pDay": "2", "pTot": "-1", "shots": [{"n": "1", "pid": "0", "time": "", "putt": "", "t": "S", "prv": "n", "tee": "y", "cup": "n", "from": "OTB", "to": "OGR", "asc": "1", "dist": "6424", "left": "324", "x": "9682.029", "y": "9729.827", "z": "66.865", "club": "CUK", "con": "", "shotText": "Shot 1 178 yds to green, 27 ft 0 in. to hole"}, {"n": "2", "pid": "0", "time": "", "putt": "1", "t": "S", "prv": "n", "tee": "n", "cup": "n", "from": "OGR", "to": "OGR", "asc": "1", "dist": "309", "left": "32", "x": "9674.934", "y": "9754.553", "z": "66.888", "club": "CUK", "con": "", "shotText": "Shot 2 putt 25 ft 9 in., 2 ft 8 in. to hole"}, {"n": "3", "pid": "0", "time": "", "putt": "2", "t": "S", "prv": "n", "tee": "n", "cup": "y", "from": "OGR", "to": "hole", "asc": "1", "dist": "32", "left": "0", "x": "0", "y": "0", "z": "0", "club": "CUK", "con": "", "shotText": "Shot 3 in the hole"}]}, {"n": "9", "cNum": "9", "sc": "4", "pDay": "1", "pTot": "-2", "shots": [{"n": "1", "pid": "0", "time": "", "putt": "", "t": "S", "prv": "n", "tee": "y", "cup": "n", "from": "OTB", "to": "ELR", "asc": "1", "dist": "9554", "left": "12731", "x": "10203.393", "y": "9114.873", "z": "85.802", "club": "CDR", "con": "", "shotText": "Shot 1 265 yds to left rough, 354 yds to hole"}, {"n": "1", "pid": "0", "time": "", "putt": "", "t": "D", "prv": "n", "tee": "n", "cup": "n", "from": "OUK", "to": "ELR", "asc": "0", "dist": "64", "left": "12729", "x": "10198.10", "y": "9115.13", "z": "85.36", "club": "CUK", "con": "", "shotText": "Drop in left rough, 354 yds to hole"}, {"n": "2", "pid": "0", "time": "", "putt": "", "t": "S", "prv": "n", "tee": "n", "cup": "n", "from": "ORO", "to": "ERF", "asc": "1", "dist": "5355", "left": "7535", "x": "10085.456", "y": "8683.573", "z": "70.599", "club": "CUK", "con": "", "shotText": "Shot 2 149 yds to right fairway, 209 yds to hole"}, {"n": "3", "pid": "0", "time": "", "putt": "", "t": "S", "prv": "n", "tee": "n", "cup": "n", "from": "OFW", "to": "ERI", "asc": "1", "dist": "7782", "left": "252", "x": "10121.205", "y": "8036.073", "z": "69.613", "club": "CUK", "con": "", "shotText": "Shot 3 216 yds to right intermediate, 21 ft 0 in. to hole"}, {"n": "4", "pid": "0", "time": "", "putt": "", "t": "S", "prv": "n", "tee": "n", "cup": "y", "from": "OIR", "to": "hole", "asc": "1", "dist": "252", "left": "0", "x": "0", "y": "0", "z": "0", "club": "CUK", "con": "", "shotText": "Shot 4 in the hole"}]}, {"n": "10", "cNum": "10", "sc": "4", "pDay": "1", "pTot": "-2", "shots": [{"n": "1", "pid": "0", "time": "", "putt": "", "t": "S", "prv": "n", "tee": "y", "cup": "n", "from": "OTB", "to": "ELF", "asc": "1", "dist": "9817", "left": "4756", "x": "10275.040", "y": "7340.481", "z": "79.891", "club": "CDR", "con": "", "shotText": "Shot 1 273 yds to left fairway, 132 yds to hole"}, {"n": "2", "pid": "0", "time": "", "putt": "", "t": "S", "prv": "n", "tee": "n", "cup": "n", "from": "OFW", "to": "OGR", "asc": "1", "dist": "4601", "left": "155", "x": "10279.563", "y": "6957.061", "z": "81.332", "club": "CUK", "con": "", "shotText": "Shot 2 128 yds to green, 12 ft 11 in. to hole"}, {"n": "3", "pid": "0", "time": "", "putt": "1", "t": "S", "prv": "n", "tee": "n", "cup": "n", "from": "OGR", "to": "OGR", "asc": "1", "dist": "146", "left": "10", "x": "10280.741", "y": "6944.978", "z": "81.343", "club": "CUK", "con": "", "shotText": "Shot 3 putt 12 ft 2 in., 10 in. to hole"}, {"n": "4", "pid": "0", "time": "", "putt": "2", "t": "S", "prv": "n", "tee": "n", "cup": "y", "from": "OGR", "to": "hole", "asc": "1", "dist": "10", "left": "0", "x": "0", "y": "0", "z": "0", "club": "CUK", "con": "", "shotText": "Shot 4 in the hole"}]}, {"n": "11", "cNum": "11", "sc": "3", "pDay": "1", "pTot": "-2", "shots": [{"n": "1", "pid": "0", "time": "", "putt": "", "t": "S", "prv": "n", "tee": "y", "cup": "n", "from": "OTB", "to": "ERR", "asc": "1", "dist": "7506", "left": "367", "x": "9728.481", "y": "6556.969", "z": "54.736", "club": "CUK", "con": "", "shotText": "Shot 1 209 yds to right rough, 30 ft 7 in. to hole"}, {"n": "2", "pid": "0", "time": "", "putt": "", "t": "S", "prv": "n", "tee": "n", "cup": "n", "from": "ORO", "to": "OGR", "asc": "1", "dist": "438", "left": "67", "x": "9736.538", "y": "6521.332", "z": "54.624", "club": "CUK", "con": "", "shotText": "Shot 2 36 ft 6 in. to green, 5 ft 7 in. to hole"}, {"n": "3", "pid": "0", "time": "", "putt": "1", "t": "S", "prv": "n", "tee": "n", "cup": "y", "from": "OGR", "to": "hole", "asc": "1", "dist": "67", "left": "0", "x": "0", "y": "0", "z": "0", "club": "CUK", "con": "", "shotText": "Shot 3 in the hole"}]}, {"n": "12", "cNum": "12", "sc": "4", "pDay": "1", "pTot": "-2", "shots": [{"n": "1", "pid": "0", "time": "", "putt": "", "t": "S", "prv": "n", "tee": "y", "cup": "n", "from": "OTB", "to": "ERF", "asc": "1", "dist": "10131", "left": "7995", "x": "8956.743", "y": "6678.811", "z": "38.614", "club": "CDR", "con": "", "shotText": "Shot 1 281 yds to right fairway, 222 yds to hole"}, {"n": "2", "pid": "0", "time": "", "putt": "", "t": "S", "prv": "n", "tee": "n", "cup": "n", "from": "OFW", "to": "OGR", "asc": "1", "dist": "7830", "left": "190", "x": "8365.194", "y": "6954.049", "z": "31.245", "club": "CUK", "con": "", "shotText": "Shot 2 218 yds to green, 15 ft 10 in. to hole"}, {"n": "3", "pid": "0", "time": "", "putt": "1", "t": "S", "prv": "n", "tee": "n", "cup": "n", "from": "OGR", "to": "OGR", "asc": "1", "dist": "207", "left": "18", "x": "8347.924", "y": "6953.765", "z": "31.177", "club": "CUK", "con": "", "shotText": "Shot 3 putt 17 ft 3 in., 18 in. to hole"}, {"n": "4", "pid": "0", "time": "", "putt": "2", "t": "S", "prv": "n", "tee": "n", "cup": "y", "from": "OGR", "to": "hole", "asc": "1", "dist": "18", "left": "0", "x": "0", "y": "0", "z": "0", "club": "CUK", "con": "", "shotText": "Shot 4 in the hole"}]}, {"n": "13", "cNum": "13", "sc": "4", "pDay": "0", "pTot": "-3", "shots": [{"n": "1", "pid": "0", "time": "", "putt": "", "t": "S", "prv": "n", "tee": "y", "cup": "n", "from": "OTB", "to": "ERF", "asc": "1", "dist": "9928", "left": "9113", "x": "9094.091", "y": "6993.206", "z": "31.781", "club": "CDR", "con": "", "shotText": "Shot 1 276 yds to right fairway, 253 yds to hole"}, {"n": "2", "pid": "0", "time": "", "putt": "", "t": "S", "prv": "n", "tee": "n", "cup": "n", "from": "OFW", "to": "ERR", "asc": "1", "dist": "8435", "left": "687", "x": "9774.998", "y": "6819.282", "z": "44.369", "club": "CUK", "con": "", "shotText": "Shot 2 234 yds to right rough, 57 ft 3 in. to hole"}, {"n": "3", "pid": "0", "time": "", "putt": "", "t": "S", "prv": "n", "tee": "n", "cup": "n", "from": "ORO", "to": "OGR", "asc": "1", "dist": "559", "left": "129", "x": "9820.731", "y": "6813.730", "z": "51.481", "club": "CUK", "con": "", "shotText": "Shot 3 46 ft 7 in. to green, 10 ft 9 in. to hole"}, {"n": "4", "pid": "0", "time": "", "putt": "1", "t": "S", "prv": "n", "tee": "n", "cup": "y", "from": "OGR", "to": "hole", "asc": "1", "dist": "129", "left": "0", "x": "0", "y": "0", "z": "0", "club": "CUK", "con": "", "shotText": "Shot 4 in the hole"}]}, {"n": "14", "cNum": "14", "sc": "4", "pDay": "0", "pTot": "-3", "shots": [{"n": "1", "pid": "0", "time": "", "putt": "", "t": "S", "prv": "n", "tee": "y", "cup": "n", "from": "OTB", "to": "ERR", "asc": "1", "dist": "10389", "left": "5726", "x": "9934.727", "y": "7623.681", "z": "56.659", "club": "CDR", "con": "", "shotText": "Shot 1 289 yds to right rough, 159 yds to hole"}, {"n": "2", "pid": "0", "time": "", "putt": "", "t": "S", "prv": "n", "tee": "n", "cup": "n", "from": "ORO", "to": "OGR", "asc": "1", "dist": "5361", "left": "427", "x": "9587.408", "y": "7904.587", "z": "48.170", "club": "CUK", "con": "", "shotText": "Shot 2 149 yds to green, 35 ft 7 in. to hole"}, {"n": "3", "pid": "0", "time": "", "putt": "1", "t": "S", "prv": "n", "tee": "n", "cup": "n", "from": "OGR", "to": "OGR", "asc": "1", "dist": "412", "left": "27", "x": "9553.185", "y": "7906.683", "z": "49.147", "club": "CUK", "con": "", "shotText": "Shot 3 putt 34 ft 4 in., 2 ft 3 in. to hole"}, {"n": "4", "pid": "0", "time": "", "putt": "2", "t": "S", "prv": "n", "tee": "n", "cup": "y", "from": "OGR", "to": "hole", "asc": "1", "dist": "27", "left": "0", "x": "0", "y": "0", "z": "0", "club": "CUK", "con": "", "shotText": "Shot 4 in the hole"}]}, {"n": "15", "cNum": "15", "sc": "5", "pDay": "1", "pTot": "-2", "shots": [{"n": "1", "pid": "0", "time": "", "putt": "", "t": "S", "prv": "n", "tee": "y", "cup": "n", "from": "OTB", "to": "ELR", "asc": "1", "dist": "10443", "left": "7105", "x": "9818.398", "y": "8339.668", "z": "54.604", "club": "CDR", "con": "", "shotText": "Shot 1 290 yds to left rough, 197 yds to hole"}, {"n": "2", "pid": "0", "time": "", "putt": "", "t": "S", "prv": "n", "tee": "n", "cup": "n", "from": "ORO", "to": "ELF", "asc": "1", "dist": "1068", "left": "6294", "x": "9868.614", "y": "8413.191", "z": "55.156", "club": "CUK", "con": "", "shotText": "Shot 2 89 ft 0 in. to left fairway, 175 yds to hole"}, {"n": "3", "pid": "0", "time": "", "putt": "", "t": "S", "prv": "n", "tee": "n", "cup": "n", "from": "OFW", "to": "EG2", "asc": "1", "dist": "5833", "left": "540", "x": "9811.607", "y": "8895.882", "z": "60.329", "club": "CUK", "con": "", "shotText": "Shot 3 162 yds to right green side bunker, 45 ft 0 in. to hole"}, {"n": "4", "pid": "0", "time": "", "putt": "", "t": "S", "prv": "n", "tee": "n", "cup": "n", "from": "OGS", "to": "OGR", "asc": "1", "dist": "548", "left": "14", "x": "9783.835", "y": "8931.905", "z": "64.281", "club": "CUK", "con": "", "shotText": "Shot 4 45 ft 8 in. to green, 14 in. to hole"}, {"n": "5", "pid": "0", "time": "", "putt": "1", "t": "S", "prv": "n", "tee": "n", "cup": "y", "from": "OGR", "to": "hole", "asc": "1", "dist": "14", "left": "0", "x": "0", "y": "0", "z": "0", "club": "CUK", "con": "", "shotText": "Shot 5 in the hole"}]}, {"n": "16", "cNum": "16", "sc": "3", "pDay": "1", "pTot": "-2", "shots": [{"n": "1", "pid": "0", "time": "", "putt": "", "t": "S", "prv": "n", "tee": "y", "cup": "n", "from": "OTB", "to": "OGR", "asc": "1", "dist": "7084", "left": "381", "x": "9069.416", "y": "8362.937", "z": "43.707", "club": "CUK", "con": "", "shotText": "Shot 1 197 yds to green, 31 ft 9 in. to hole"}, {"n": "2", "pid": "0", "time": "", "putt": "1", "t": "S", "prv": "n", "tee": "n", "cup": "n", "from": "OGR", "to": "OGR", "asc": "1", "dist": "394", "left": "11", "x": "9071.418", "y": "8330.207", "z": "44.559", "club": "CUK", "con": "", "shotText": "Shot 2 putt 32 ft 10 in., 11 in. to hole"}, {"n": "3", "pid": "0", "time": "", "putt": "2", "t": "S", "prv": "n", "tee": "n", "cup": "y", "from": "OGR", "to": "hole", "asc": "1", "dist": "11", "left": "0", "x": "0", "y": "0", "z": "0", "club": "CUK", "con": "", "shotText": "Shot 3 in the hole"}]}, {"n": "17", "cNum": "17", "sc": "4", "pDay": "1", "pTot": "-2", "shots": [{"n": "1", "pid": "0", "time": "", "putt": "", "t": "S", "prv": "n", "tee": "y", "cup": "n", "from": "OTB", "to": "ERF", "asc": "1", "dist": "10295", "left": "5689", "x": "9540.935", "y": "9134.751", "z": "52.997", "club": "CDR", "con": "", "shotText": "Shot 1 286 yds to right fairway, 158 yds to hole"}, {"n": "2", "pid": "0", "time": "", "putt": "", "t": "S", "prv": "n", "tee": "n", "cup": "n", "from": "OFW", "to": "OGR", "asc": "1", "dist": "5757", "left": "172", "x": "9805.857", "y": "9534.365", "z": "70.352", "club": "CUK", "con": "", "shotText": "Shot 2 160 yds to green, 14 ft 4 in. to hole"}, {"n": "3", "pid": "0", "time": "", "putt": "1", "t": "S", "prv": "n", "tee": "n", "cup": "n", "from": "OGR", "to": "OGR", "asc": "1", "dist": "196", "left": "24", "x": "9789.587", "y": "9536.132", "z": "69.889", "club": "CUK", "con": "", "shotText": "Shot 3 putt 16 ft 4 in., 2 ft 0 in. to hole"}, {"n": "4", "pid": "0", "time": "", "putt": "2", "t": "S", "prv": "n", "tee": "n", "cup": "y", "from": "OGR", "to": "hole", "asc": "1", "dist": "24", "left": "0", "x": "0", "y": "0", "z": "0", "club": "CUK", "con": "", "shotText": "Shot 4 in the hole"}]}, {"n": "18", "cNum": "18", "sc": "5", "pDay": "1", "pTot": "-2", "shots": [{"n": "1", "pid": "0", "time": "", "putt": "", "t": "S", "prv": "n", "tee": "y", "cup": "n", "from": "OTB", "to": "ELR", "asc": "1", "dist": "9785", "left": "9851", "x": "9610.051", "y": "10267.058", "z": "64.502", "club": "CDR", "con": "", "shotText": "Shot 1 272 yds to left rough, 274 yds to hole"}, {"n": "2", "pid": "0", "time": "", "putt": "", "t": "S", "prv": "n", "tee": "n", "cup": "n", "from": "ORO", "to": "ELF", "asc": "1", "dist": "3402", "left": "6696", "x": "9700.912", "y": "10535.579", "z": "65.375", "club": "CUK", "con": "", "shotText": "Shot 2 95 yds to left fairway, 186 yds to hole"}, {"n": "3", "pid": "0", "time": "", "putt": "", "t": "S", "prv": "n", "tee": "n", "cup": "n", "from": "OFW", "to": "OGR", "asc": "1", "dist": "6696", "left": "301", "x": "9646.970", "y": "11090.972", "z": "68.066", "club": "CUK", "con": "", "shotText": "Shot 3 186 yds to green, 25 ft 1 in. to hole"}, {"n": "4", "pid": "0", "time": "", "putt": "1", "t": "S", "prv": "n", "tee": "n", "cup": "n", "from": "OGR", "to": "OGR", "asc": "1", "dist": "317", "left": "23", "x": "9621.032", "y": "11086.244", "z": "67.193", "club": "CUK", "con": "", "shotText": "Shot 4 putt 26 ft 5 in., 23 in. to hole"}, {"n": "5", "pid": "0", "time": "", "putt": "2", "t": "S", "prv": "n", "tee": "n", "cup": "y", "from": "OGR", "to": "hole", "asc": "1", "dist": "23", "left": "0", "x": "0", "y": "0", "z": "0", "club": "CUK", "con": "", "shotText": "Shot 5 in the hole"}]}]}]}}