{"p": {"msgId": "460722", "id": "33399", "rnds": [{"n": "1", "holes": [{"n": "1", "cNum": "1", "sc": "6", "pDay": "2", "pTot": "2", "shots": [{"n": "1", "pid": "00000", "time": "", "putt": "", "t": "S", "prv": "n", "tee": "y", "cup": "n", "from": "OTB", "to": "OUK", "asc": "1", "dist": "10830", "left": "4352", "x": "11926.755", "y": "8874.943", "z": "11.410", "club": "CFW", "con": "", "shotText": "Shot 1 301 yds to unknown, 121 yds to hole"}, {"n": "2", "pid": "00000", "time": "", "putt": "", "t": "P", "prv": "n", "tee": "n", "cup": "n", "from": "OUK", "to": "OTB", "asc": "1", "dist": "0", "left": "0", "x": "0", "y": "0", "z": "0", "club": "CUK", "con": "", "shotText": "Shot 2 Penalty"}, {"n": "3", "pid": "00000", "time": "", "putt": "", "t": "S", "prv": "y", "tee": "y", "cup": "n", "from": "OTB", "to": "ERR", "asc": "1", "dist": "8443", "left": "6206", "x": "11839.855", "y": "9081.415", "z": "12.386", "club": "CFW", "con": "", "shotText": "Shot 3 235 yds to right rough, 172 yds to hole"}, {"n": "4", "pid": "00000", "time": "", "putt": "", "t": "S", "prv": "n", "tee": "n", "cup": "n", "from": "ORO", "to": "OCO", "asc": "1", "dist": "6472", "left": "442", "x": "12318.815", "y": "8833.398", "z": "13.845", "club": "CUK", "con": "", "shotText": "Shot 4 180 yds to fringe, 36 ft 10 in. to hole"}, {"n": "5", "pid": "00000", "time": "", "putt": "", "t": "S", "prv": "n", "tee": "n", "cup": "n", "from": "OCO", "to": "OGR", "asc": "1", "dist": "400", "left": "51", "x": "12289.557", "y": "8817.425", "z": "14.277", "club": "CUK", "con": "", "shotText": "Shot 5 33 ft 4 in. to green, 4 ft 3 in. to hole"}, {"n": "6", "pid": "00000", "time": "", "putt": "1", "t": "S", "prv": "n", "tee": "n", "cup": "y", "from": "OGR", "to": "hole", "asc": "1", "dist": "51", "left": "0", "x": "0", "y": "0", "z": "0", "club": "CUK", "con": "", "shotText": "Shot 6 in the hole"}]}, {"n": "2", "cNum": "2", "sc": "4", "pDay": "1", "pTot": "1", "shots": [{"n": "1", "pid": "00000", "time": "", "putt": "", "t": "S", "prv": "n", "tee": "y", "cup": "n", "from": "OTB", "to": "ELF", "asc": "1", "dist": "9531", "left": "8705", "x": "12847.376", "y": "8051.588", "z": "12.512", "club": "CDR", "con": "", "shotText": "Shot 1 265 yds to left fairway, 242 yds to hole"}, {"n": "2", "pid": "00000", "time": "", "putt": "", "t": "S", "prv": "n", "tee": "n", "cup": "n", "from": "OFW", "to": "OGR", "asc": "1", "dist": "8414", "left": "306", "x": "13014.762", "y": "7370.727", "z": "14.088", "club": "CUK", "con": "", "shotText": "Shot 2 234 yds to green, 25 ft 6 in. to hole"}, {"n": "3", "pid": "00000", "time": "", "putt": "1", "t": "S", "prv": "n", "tee": "n", "cup": "n", "from": "OGR", "to": "OGR", "asc": "1", "dist": "274", "left": "34", "x": "13013.703", "y": "7347.949", "z": "14.396", "club": "CUK", "con": "", "shotText": "Shot 3 putt 22 ft 10 in., 2 ft 10 in. to hole"}, {"n": "4", "pid": "00000", "time": "", "putt": "2", "t": "S", "prv": "n", "tee": "n", "cup": "y", "from": "OGR", "to": "hole", "asc": "1", "dist": "34", "left": "0", "x": "0", "y": "0", "z": "0", "club": "CUK", "con": "", "shotText": "Shot 4 in the hole"}]}, {"n": "3", "cNum": "3", "sc": "4", "pDay": "1", "pTot": "1", "shots": [{"n": "1", "pid": "00000", "time": "", "putt": "", "t": "S", "prv": "n", "tee": "y", "cup": "n", "from": "OTB", "to": "ERF", "asc": "1", "dist": "10705", "left": "5774", "x": "12441.200", "y": "6663.302", "z": "12.481", "club": "CDR", "con": "", "shotText": "Shot 1 297 yds to right fairway, 160 yds to hole"}, {"n": "2", "pid": "00000", "time": "", "putt": "", "t": "S", "prv": "n", "tee": "n", "cup": "n", "from": "OFW", "to": "EG2", "asc": "1", "dist": "5737", "left": "653", "x": "12179.446", "y": "6263.208", "z": "11.008", "club": "CUK", "con": "", "shotText": "Shot 2 159 yds to right green side bunker, 54 ft 5 in. to hole"}, {"n": "3", "pid": "00000", "time": "", "putt": "", "t": "S", "prv": "n", "tee": "n", "cup": "n", "from": "OGS", "to": "OGR", "asc": "1", "dist": "673", "left": "21", "x": "12225.498", "y": "6231.374", "z": "14.075", "club": "CUK", "con": "", "shotText": "Shot 3 56 ft 1 in. to green, 21 in. to hole"}, {"n": "4", "pid": "00000", "time": "", "putt": "1", "t": "S", "prv": "n", "tee": "n", "cup": "y", "from": "OGR", "to": "hole", "asc": "1", "dist": "21", "left": "0", "x": "0", "y": "0", "z": "0", "club": "CUK", "con": "", "shotText": "Shot 4 in the hole"}]}, {"n": "4", "cNum": "4", "sc": "3", "pDay": "1", "pTot": "1", "shots": [{"n": "1", "pid": "00000", "time": "", "putt": "", "t": "S", "prv": "n", "tee": "y", "cup": "n", "from": "OTB", "to": "OGR", "asc": "1", "dist": "6417", "left": "561", "x": "12131.838", "y": "5549.030", "z": "12.573", "club": "CUK", "con": "", "shotText": "Shot 1 178 yds to green, 46 ft 9 in. to hole"}, {"n": "2", "pid": "00000", "time": "", "putt": "1", "t": "S", "prv": "n", "tee": "n", "cup": "n", "from": "OGR", "to": "OGR", "asc": "1", "dist": "556", "left": "5", "x": "12177.287", "y": "5558.074", "z": "12.673", "club": "CUK", "con": "", "shotText": "Shot 2 putt 46 ft 4 in., 5 in. to hole"}, {"n": "3", "pid": "00000", "time": "", "putt": "2", "t": "S", "prv": "n", "tee": "n", "cup": "y", "from": "OGR", "to": "hole", "asc": "1", "dist": "5", "left": "0", "x": "0", "y": "0", "z": "0", "club": "CUK", "con": "", "shotText": "Shot 3 in the hole"}]}, {"n": "5", "cNum": "5", "sc": "5", "pDay": "1", "pTot": "1", "shots": [{"n": "1", "pid": "00000", "time": "", "putt": "", "t": "S", "prv": "n", "tee": "y", "cup": "n", "from": "OTB", "to": "ELF", "asc": "1", "dist": "9999", "left": "9484", "x": "12777.208", "y": "5370.574", "z": "15.853", "club": "CDR", "con": "", "shotText": "Shot 1 278 yds to left fairway, 263 yds to hole"}, {"n": "2", "pid": "00000", "time": "", "putt": "", "t": "S", "prv": "n", "tee": "n", "cup": "n", "from": "OFW", "to": "ELR", "asc": "1", "dist": "10232", "left": "756", "x": "13395.169", "y": "5958.135", "z": "15.407", "club": "CUK", "con": "", "shotText": "Shot 2 284 yds to left rough, 63 ft 0 in. to hole"}, {"n": "3", "pid": "00000", "time": "", "putt": "", "t": "S", "prv": "n", "tee": "n", "cup": "n", "from": "ORO", "to": "OGR", "asc": "1", "dist": "778", "left": "91", "x": "13350.311", "y": "5911.417", "z": "18.696", "club": "CUK", "con": "", "shotText": "Shot 3 64 ft 10 in. to green, 7 ft 7 in. to hole"}, {"n": "4", "pid": "00000", "time": "", "putt": "1", "t": "S", "prv": "n", "tee": "n", "cup": "n", "from": "OGR", "to": "OGR", "asc": "1", "dist": "123", "left": "27", "x": "13359.504", "y": "5906.955", "z": "18.807", "club": "CUK", "con": "", "shotText": "Shot 4 putt 10 ft 3 in., 2 ft 3 in. to hole"}, {"n": "5", "pid": "00000", "time": "", "putt": "2", "t": "S", "prv": "n", "tee": "n", "cup": "y", "from": "OGR", "to": "hole", "asc": "1", "dist": "27", "left": "0", "x": "0", "y": "0", "z": "0", "club": "CUK", "con": "", "shotText": "Shot 5 in the hole"}]}, {"n": "6", "cNum": "6", "sc": "4", "pDay": "1", "pTot": "1", "shots": [{"n": "1", "pid": "00000", "time": "", "putt": "", "t": "S", "prv": "n", "tee": "y", "cup": "n", "from": "OTB", "to": "ERF", "asc": "1", "dist": "9572", "left": "5641", "x": "13043.657", "y": "6591.906", "z": "12.258", "club": "CFW", "con": "", "shotText": "Shot 1 266 yds to right fairway, 157 yds to hole"}, {"n": "2", "pid": "00000", "time": "", "putt": "", "t": "S", "prv": "n", "tee": "n", "cup": "n", "from": "OFW", "to": "OGR", "asc": "1", "dist": "5766", "left": "125", "x": "12983.898", "y": "7068.668", "z": "14.544", "club": "CUK", "con": "", "shotText": "Shot 2 160 yds to green, 10 ft 5 in. to hole"}, {"n": "3", "pid": "00000", "time": "", "putt": "1", "t": "S", "prv": "n", "tee": "n", "cup": "n", "from": "OGR", "to": "OGR", "asc": "1", "dist": "166", "left": "41", "x": "12987.332", "y": "7055.285", "z": "14.391", "club": "CUK", "con": "", "shotText": "Shot 3 putt 13 ft 10 in., 3 ft 5 in. to hole"}, {"n": "4", "pid": "00000", "time": "", "putt": "2", "t": "S", "prv": "n", "tee": "n", "cup": "y", "from": "OGR", "to": "hole", "asc": "1", "dist": "41", "left": "0", "x": "0", "y": "0", "z": "0", "club": "CUK", "con": "", "shotText": "Shot 4 in the hole"}]}, {"n": "7", "cNum": "7", "sc": "3", "pDay": "1", "pTot": "1", "shots": [{"n": "1", "pid": "00000", "time": "", "putt": "", "t": "S", "prv": "n", "tee": "y", "cup": "n", "from": "OTB", "to": "OGR", "asc": "1", "dist": "7024", "left": "205", "x": "12244.518", "y": "6932.583", "z": "13.897", "club": "CUK", "con": "", "shotText": "Shot 1 195 yds to green, 17 ft 1 in. to hole"}, {"n": "2", "pid": "00000", "time": "", "putt": "1", "t": "S", "prv": "n", "tee": "n", "cup": "n", "from": "OGR", "to": "OGR", "asc": "1", "dist": "219", "left": "12", "x": "12252.021", "y": "6949.233", "z": "13.774", "club": "CUK", "con": "", "shotText": "Shot 2 putt 18 ft 3 in., 12 in. to hole"}, {"n": "3", "pid": "00000", "time": "", "putt": "2", "t": "S", "prv": "n", "tee": "n", "cup": "y", "from": "OGR", "to": "hole", "asc": "1", "dist": "12", "left": "0", "x": "0", "y": "0", "z": "0", "club": "CUK", "con": "", "shotText": "Shot 3 in the hole"}]}, {"n": "8", "cNum": "8", "sc": "4", "pDay": "1", "pTot": "1", "shots": [{"n": "1", "pid": "00000", "time": "", "putt": "", "t": "S", "prv": "n", "tee": "y", "cup": "n", "from": "OTB", "to": "ELF", "asc": "1", "dist": "10282", "left": "6417", "x": "12039.041", "y": "7698.737", "z": "10.218", "club": "CFW", "con": "", "shotText": "Shot 1 286 yds to left fairway, 178 yds to hole"}, {"n": "2", "pid": "00000", "time": "", "putt": "", "t": "S", "prv": "n", "tee": "n", "cup": "n", "from": "OFW", "to": "OGR", "asc": "1", "dist": "6643", "left": "257", "x": "11781.853", "y": "8188.960", "z": "14.369", "club": "CUK", "con": "", "shotText": "Shot 2 185 yds to green, 21 ft 5 in. to hole"}, {"n": "3", "pid": "00000", "time": "", "putt": "1", "t": "S", "prv": "n", "tee": "n", "cup": "n", "from": "OGR", "to": "OGR", "asc": "1", "dist": "272", "left": "11", "x": "11780.875", "y": "8166.351", "z": "13.932", "club": "CUK", "con": "", "shotText": "Shot 3 putt 22 ft 8 in., 11 in. to hole"}, {"n": "4", "pid": "00000", "time": "", "putt": "2", "t": "S", "prv": "n", "tee": "n", "cup": "y", "from": "OGR", "to": "hole", "asc": "1", "dist": "11", "left": "0", "x": "0", "y": "0", "z": "0", "club": "CUK", "con": "", "shotText": "Shot 4 in the hole"}]}, {"n": "9", "cNum": "9", "sc": "4", "pDay": "1", "pTot": "1", "shots": [{"n": "1", "pid": "00000", "time": "", "putt": "", "t": "S", "prv": "n", "tee": "y", "cup": "n", "from": "OTB", "to": "ELR", "asc": "1", "dist": "8414", "left": "3617", "x": "11422.009", "y": "8993.366", "z": "11.923", "club": "CIR", "con": "", "shotText": "Shot 1 234 yds to left rough, 100 yds to hole"}, {"n": "2", "pid": "00000", "time": "", "putt": "", "t": "S", "prv": "n", "tee": "n", "cup": "n", "from": "ORO", "to": "ERR", "asc": "1", "dist": "4072", "left": "455", "x": "11284.708", "y": "9303.714", "z": "12.573", "club": "CUK", "con": "", "shotText": "Shot 2 113 yds to right rough, 37 ft 11 in. to hole"}, {"n": "3", "pid": "00000", "time": "", "putt": "", "t": "S", "prv": "n", "tee": "n", "cup": "n", "from": "ORO", "to": "OGR", "asc": "1", "dist": "472", "left": "16", "x": "11295.415", "y": "9265.827", "z": "12.944", "club": "CUK", "con": "", "shotText": "Shot 3 39 ft 4 in. to green, 16 in. to hole"}, {"n": "4", "pid": "00000", "time": "", "putt": "1", "t": "S", "prv": "n", "tee": "n", "cup": "y", "from": "OGR", "to": "hole", "asc": "1", "dist": "16", "left": "0", "x": "0", "y": "0", "z": "0", "club": "CUK", "con": "", "shotText": "Shot 4 in the hole"}]}, {"n": "10", "cNum": "10", "sc": "4", "pDay": "1", "pTot": "1", "shots": [{"n": "1", "pid": "00000", "time": "", "putt": "", "t": "S", "prv": "n", "tee": "y", "cup": "n", "from": "OTB", "to": "ERR", "asc": "1", "dist": "9323", "left": "6778", "x": "10801.118", "y": "8413.751", "z": "13.086", "club": "CFW", "con": "", "shotText": "Shot 1 259 yds to right rough, 188 yds to hole"}, {"n": "2", "pid": "00000", "time": "", "putt": "", "t": "S", "prv": "n", "tee": "n", "cup": "n", "from": "ORO", "to": "OGR", "asc": "1", "dist": "6631", "left": "155", "x": "10937.007", "y": "7878.130", "z": "13.133", "club": "CUK", "con": "", "shotText": "Shot 2 184 yds to green, 12 ft 11 in. to hole"}, {"n": "3", "pid": "00000", "time": "", "putt": "1", "t": "S", "prv": "n", "tee": "n", "cup": "n", "from": "OGR", "to": "OGR", "asc": "1", "dist": "181", "left": "24", "x": "10946.021", "y": "7866.057", "z": "13.304", "club": "CUK", "con": "", "shotText": "Shot 3 putt 15 ft 1 in., 2 ft 0 in. to hole"}, {"n": "4", "pid": "00000", "time": "", "putt": "2", "t": "S", "prv": "n", "tee": "n", "cup": "y", "from": "OGR", "to": "hole", "asc": "1", "dist": "24", "left": "0", "x": "0", "y": "0", "z": "0", "club": "CUK", "con": "", "shotText": "Shot 4 in the hole"}]}, {"n": "11", "cNum": "11", "sc": "3", "pDay": "0", "pTot": "0", "shots": [{"n": "1", "pid": "00000", "time": "", "putt": "", "t": "S", "prv": "n", "tee": "y", "cup": "n", "from": "OTB", "to": "ERF", "asc": "1", "dist": "8895", "left": "6975", "x": "11286.267", "y": "7019.686", "z": "10.579", "club": "CFW", "con": "", "shotText": "Shot 1 247 yds to right fairway, 194 yds to hole"}, {"n": "2", "pid": "00000", "time": "", "putt": "", "t": "S", "prv": "n", "tee": "n", "cup": "n", "from": "OFW", "to": "OGR", "asc": "1", "dist": "7015", "left": "51", "x": "11534.078", "y": "6490.265", "z": "15.024", "club": "CUK", "con": "", "shotText": "Shot 2 195 yds to green, 4 ft 3 in. to hole"}, {"n": "3", "pid": "00000", "time": "", "putt": "1", "t": "S", "prv": "n", "tee": "n", "cup": "y", "from": "OGR", "to": "hole", "asc": "1", "dist": "51", "left": "0", "x": "0", "y": "0", "z": "0", "club": "CUK", "con": "", "shotText": "Shot 3 in the hole"}]}, {"n": "12", "cNum": "12", "sc": "4", "pDay": "0", "pTot": "0", "shots": [{"n": "1", "pid": "00000", "time": "", "putt": "", "t": "S", "prv": "n", "tee": "y", "cup": "n", "from": "OTB", "to": "ELF", "asc": "1", "dist": "10772", "left": "4224", "x": "11092.707", "y": "5695.610", "z": "10.387", "club": "CDR", "con": "", "shotText": "Shot 1 299 yds to left fairway, 117 yds to hole"}, {"n": "2", "pid": "00000", "time": "", "putt": "", "t": "S", "prv": "n", "tee": "n", "cup": "n", "from": "OFW", "to": "OGR", "asc": "1", "dist": "4172", "left": "55", "x": "10758.550", "y": "5599.702", "z": "13.604", "club": "CUK", "con": "", "shotText": "Shot 2 116 yds to green, 4 ft 7 in. to hole"}, {"n": "3", "pid": "00000", "time": "", "putt": "1", "t": "S", "prv": "n", "tee": "n", "cup": "n", "from": "OGR", "to": "OGR", "asc": "1", "dist": "76", "left": "17", "x": "10752.276", "y": "5600.281", "z": "13.780", "club": "CUK", "con": "", "shotText": "Shot 3 putt 6 ft 4 in., 17 in. to hole"}, {"n": "4", "pid": "00000", "time": "", "putt": "2", "t": "S", "prv": "n", "tee": "n", "cup": "y", "from": "OGR", "to": "hole", "asc": "1", "dist": "17", "left": "0", "x": "0", "y": "0", "z": "0", "club": "CUK", "con": "", "shotText": "Shot 4 in the hole"}]}, {"n": "13", "cNum": "13", "sc": "4", "pDay": "0", "pTot": "0", "shots": [{"n": "1", "pid": "00000", "time": "", "putt": "", "t": "S", "prv": "n", "tee": "y", "cup": "n", "from": "OTB", "to": "OTO", "asc": "1", "dist": "8055", "left": "5457", "x": "9877.895", "y": "5539.766", "z": "14.426", "club": "CIR", "con": "", "shotText": "Shot 1 224 yds to tree outline, 152 yds to hole"}, {"n": "2", "pid": "00000", "time": "", "putt": "", "t": "S", "prv": "n", "tee": "n", "cup": "n", "from": "ONA", "to": "EG2", "asc": "1", "dist": "5416", "left": "520", "x": "9527.246", "y": "5255.627", "z": "14.405", "club": "CUK", "con": "", "shotText": "Shot 2 150 yds to right green side bunker, 43 ft 4 in. to hole"}, {"n": "3", "pid": "00000", "time": "", "putt": "", "t": "S", "prv": "n", "tee": "n", "cup": "n", "from": "OGS", "to": "OGR", "asc": "1", "dist": "583", "left": "60", "x": "9555.729", "y": "5216.239", "z": "14.662", "club": "CUK", "con": "", "shotText": "Shot 3 48 ft 7 in. to green, 5 ft 0 in. to hole"}, {"n": "4", "pid": "00000", "time": "", "putt": "1", "t": "S", "prv": "n", "tee": "n", "cup": "y", "from": "OGR", "to": "hole", "asc": "1", "dist": "60", "left": "0", "x": "0", "y": "0", "z": "0", "club": "CUK", "con": "", "shotText": "Shot 4 in the hole"}]}, {"n": "14", "cNum": "14", "sc": "3", "pDay": "0", "pTot": "0", "shots": [{"n": "1", "pid": "00000", "time": "", "putt": "", "t": "S", "prv": "n", "tee": "y", "cup": "n", "from": "OTB", "to": "OGR", "asc": "1", "dist": "7012", "left": "246", "x": "9695.595", "y": "5708.100", "z": "11.096", "club": "CUK", "con": "", "shotText": "Shot 1 195 yds to green, 20 ft 6 in. to hole"}, {"n": "2", "pid": "00000", "time": "", "putt": "1", "t": "S", "prv": "n", "tee": "n", "cup": "n", "from": "OGR", "to": "OGR", "asc": "1", "dist": "274", "left": "29", "x": "9717.936", "y": "5712.874", "z": "10.892", "club": "CUK", "con": "", "shotText": "Shot 2 putt 22 ft 10 in., 2 ft 5 in. to hole"}, {"n": "3", "pid": "00000", "time": "", "putt": "2", "t": "S", "prv": "n", "tee": "n", "cup": "y", "from": "OGR", "to": "hole", "asc": "1", "dist": "29", "left": "0", "x": "0", "y": "0", "z": "0", "club": "CUK", "con": "", "shotText": "Shot 3 in the hole"}]}, {"n": "15", "cNum": "15", "sc": "4", "pDay": "-1", "pTot": "-1", "shots": [{"n": "1", "pid": "00000", "time": "", "putt": "", "t": "S", "prv": "n", "tee": "y", "cup": "n", "from": "OTB", "to": "ELF", "asc": "1", "dist": "10304", "left": "9757", "x": "10191.450", "y": "6509.989", "z": "14.135", "club": "CDR", "con": "", "shotText": "Shot 1 286 yds to left fairway, 271 yds to hole"}, {"n": "2", "pid": "00000", "time": "", "putt": "", "t": "S", "prv": "n", "tee": "n", "cup": "n", "from": "OFW", "to": "ERF", "asc": "1", "dist": "7077", "left": "3629", "x": "10664.985", "y": "6861.533", "z": "11.275", "club": "CUK", "con": "", "shotText": "Shot 2 197 yds to right fairway, 101 yds to hole"}, {"n": "3", "pid": "00000", "time": "", "putt": "", "t": "S", "prv": "n", "tee": "n", "cup": "n", "from": "OFW", "to": "OGR", "asc": "1", "dist": "3758", "left": "136", "x": "10679.744", "y": "7174.386", "z": "12.244", "club": "CUK", "con": "", "shotText": "Shot 3 104 yds to green, 11 ft 4 in. to hole"}, {"n": "4", "pid": "00000", "time": "", "putt": "1", "t": "S", "prv": "n", "tee": "n", "cup": "y", "from": "OGR", "to": "hole", "asc": "1", "dist": "136", "left": "0", "x": "0", "y": "0", "z": "0", "club": "CUK", "con": "", "shotText": "Shot 4 in the hole"}]}, {"n": "16", "cNum": "16", "sc": "4", "pDay": "-1", "pTot": "-1", "shots": [{"n": "1", "pid": "00000", "time": "", "putt": "", "t": "S", "prv": "n", "tee": "y", "cup": "n", "from": "OTB", "to": "ERF", "asc": "1", "dist": "10722", "left": "4868", "x": "10704.466", "y": "8343.818", "z": "12.986", "club": "CDR", "con": "", "shotText": "Shot 1 298 yds to right fairway, 135 yds to hole"}, {"n": "2", "pid": "00000", "time": "", "putt": "", "t": "S", "prv": "n", "tee": "n", "cup": "n", "from": "OFW", "to": "OGR", "asc": "1", "dist": "4778", "left": "139", "x": "10321.321", "y": "8452.179", "z": "13.662", "club": "CUK", "con": "", "shotText": "Shot 2 133 yds to green, 11 ft 7 in. to hole"}, {"n": "3", "pid": "00000", "time": "", "putt": "1", "t": "S", "prv": "n", "tee": "n", "cup": "n", "from": "OGR", "to": "OGR", "asc": "1", "dist": "164", "left": "22", "x": "10310.342", "y": "8444.041", "z": "13.495", "club": "CUK", "con": "", "shotText": "Shot 3 putt 13 ft 8 in., 22 in. to hole"}, {"n": "4", "pid": "00000", "time": "", "putt": "2", "t": "S", "prv": "n", "tee": "n", "cup": "y", "from": "OGR", "to": "hole", "asc": "1", "dist": "22", "left": "0", "x": "0", "y": "0", "z": "0", "club": "CUK", "con": "", "shotText": "Shot 4 in the hole"}]}, {"n": "17", "cNum": "17", "sc": "3", "pDay": "-1", "pTot": "-1", "shots": [{"n": "1", "pid": "00000", "time": "", "putt": "", "t": "S", "prv": "n", "tee": "y", "cup": "n", "from": "OTB", "to": "OGR", "asc": "1", "dist": "6118", "left": "131", "x": "9767.846", "y": "8339.407", "z": "13.220", "club": "CUK", "con": "", "shotText": "Shot 1 170 yds to green, 10 ft 11 in. to hole"}, {"n": "2", "pid": "00000", "time": "", "putt": "1", "t": "S", "prv": "n", "tee": "n", "cup": "n", "from": "OGR", "to": "OGR", "asc": "1", "dist": "143", "left": "8", "x": "9778.779", "y": "8344.146", "z": "12.830", "club": "CUK", "con": "", "shotText": "Shot 2 putt 11 ft 11 in., 8 in. to hole"}, {"n": "3", "pid": "00000", "time": "", "putt": "2", "t": "S", "prv": "n", "tee": "n", "cup": "y", "from": "OGR", "to": "hole", "asc": "1", "dist": "8", "left": "0", "x": "0", "y": "0", "z": "0", "club": "CUK", "con": "", "shotText": "Shot 3 in the hole"}]}, {"n": "18", "cNum": "18", "sc": "5", "pDay": "0", "pTot": "0", "shots": [{"n": "1", "pid": "00000", "time": "", "putt": "", "t": "S", "prv": "n", "tee": "y", "cup": "n", "from": "OTB", "to": "ELF", "asc": "1", "dist": "10606", "left": "5661", "x": "9911.761", "y": "9367.405", "z": "11.982", "club": "CDR", "con": "", "shotText": "Shot 1 295 yds to left fairway, 157 yds to hole"}, {"n": "2", "pid": "00000", "time": "", "putt": "", "t": "S", "prv": "n", "tee": "n", "cup": "n", "from": "OFW", "to": "ELF", "asc": "1", "dist": "5373", "left": "476", "x": "9987.712", "y": "9808.664", "z": "14.120", "club": "CUK", "con": "", "shotText": "Shot 2 149 yds to left fairway, 39 ft 8 in. to hole"}, {"n": "3", "pid": "00000", "time": "", "putt": "", "t": "S", "prv": "n", "tee": "n", "cup": "n", "from": "OFW", "to": "OGR", "asc": "1", "dist": "546", "left": "75", "x": "9953.376", "y": "9838.547", "z": "13.367", "club": "CUK", "con": "", "shotText": "Shot 3 45 ft 6 in. to green, 6 ft 3 in. to hole"}, {"n": "4", "pid": "00000", "time": "", "putt": "1", "t": "S", "prv": "n", "tee": "n", "cup": "n", "from": "OGR", "to": "OGR", "asc": "1", "dist": "95", "left": "16", "x": "9961.116", "y": "9836.821", "z": "13.399", "club": "CUK", "con": "", "shotText": "Shot 4 putt 7 ft 11 in., 16 in. to hole"}, {"n": "5", "pid": "00000", "time": "", "putt": "2", "t": "S", "prv": "n", "tee": "n", "cup": "y", "from": "OGR", "to": "hole", "asc": "1", "dist": "16", "left": "0", "x": "0", "y": "0", "z": "0", "club": "CUK", "con": "", "shotText": "Shot 5 in the hole"}]}]}, {"n": "2", "holes": [{"n": "1", "cNum": "10", "sc": "4", "pDay": "0", "pTot": "0", "shots": [{"n": "1", "pid": "00000", "time": "", "putt": "", "t": "S", "prv": "n", "tee": "y", "cup": "n", "from": "OTB", "to": "ERF", "asc": "1", "dist": "11065", "left": "5097", "x": "10882.287", "y": "8223.166", "z": "10.136", "club": "CDR", "con": "", "shotText": "Shot 1 307 yds to right fairway, 142 yds to hole"}, {"n": "2", "pid": "00000", "time": "", "putt": "", "t": "S", "prv": "n", "tee": "n", "cup": "n", "from": "OFW", "to": "OCO", "asc": "1", "dist": "5250", "left": "165", "x": "10972.429", "y": "7795.100", "z": "14.514", "club": "CUK", "con": "", "shotText": "Shot 2 146 yds to fringe, 13 ft 9 in. to hole"}, {"n": "3", "pid": "00000", "time": "", "putt": "", "t": "S", "prv": "n", "tee": "n", "cup": "n", "from": "OCO", "to": "OGR", "asc": "1", "dist": "177", "left": "8", "x": "10963.799", "y": "7807.024", "z": "14.353", "club": "CUK", "con": "", "shotText": "Shot 3 14 ft 9 in. to green, 8 in. to hole"}, {"n": "4", "pid": "00000", "time": "", "putt": "1", "t": "S", "prv": "n", "tee": "n", "cup": "y", "from": "OGR", "to": "hole", "asc": "1", "dist": "8", "left": "0", "x": "0", "y": "0", "z": "0", "club": "CUK", "con": "", "shotText": "Shot 4 in the hole"}]}, {"n": "2", "cNum": "11", "sc": "4", "pDay": "0", "pTot": "0", "shots": [{"n": "1", "pid": "00000", "time": "", "putt": "", "t": "S", "prv": "n", "tee": "y", "cup": "n", "from": "OTB", "to": "ERF", "asc": "1", "dist": "9489", "left": "5842", "x": "11291.198", "y": "6970.348", "z": "11.330", "club": "CFW", "con": "", "shotText": "Shot 1 264 yds to right fairway, 162 yds to hole"}, {"n": "2", "pid": "00000", "time": "", "putt": "", "t": "S", "prv": "n", "tee": "n", "cup": "n", "from": "OFW", "to": "OGR", "asc": "1", "dist": "5819", "left": "206", "x": "11508.893", "y": "6537.029", "z": "13.996", "club": "CUK", "con": "", "shotText": "Shot 2 162 yds to green, 17 ft 2 in. to hole"}, {"n": "3", "pid": "00000", "time": "", "putt": "1", "t": "S", "prv": "n", "tee": "n", "cup": "n", "from": "OGR", "to": "OGR", "asc": "1", "dist": "240", "left": "34", "x": "11491.250", "y": "6527.582", "z": "13.645", "club": "CUK", "con": "", "shotText": "Shot 3 putt 20 ft 0 in., 2 ft 10 in. to hole"}, {"n": "4", "pid": "00000", "time": "", "putt": "2", "t": "S", "prv": "n", "tee": "n", "cup": "y", "from": "OGR", "to": "hole", "asc": "1", "dist": "34", "left": "0", "x": "0", "y": "0", "z": "0", "club": "CUK", "con": "", "shotText": "Shot 4 in the hole"}]}, {"n": "3", "cNum": "12", "sc": "4", "pDay": "0", "pTot": "0", "shots": [{"n": "1", "pid": "00000", "time": "", "putt": "", "t": "S", "prv": "n", "tee": "y", "cup": "n", "from": "OTB", "to": "ELR", "asc": "1", "dist": "9988", "left": "5824", "x": "11173.828", "y": "5705.903", "z": "11.023", "club": "CFW", "con": "", "shotText": "Shot 1 277 yds to left rough, 162 yds to hole"}, {"n": "2", "pid": "00000", "time": "", "putt": "", "t": "S", "prv": "n", "tee": "n", "cup": "n", "from": "ORO", "to": "OCO", "asc": "1", "dist": "5680", "left": "174", "x": "10727.983", "y": "5546.966", "z": "14.121", "club": "CUK", "con": "", "shotText": "Shot 2 158 yds to fringe, 14 ft 6 in. to hole"}, {"n": "3", "pid": "00000", "time": "", "putt": "", "t": "S", "prv": "n", "tee": "n", "cup": "n", "from": "OCO", "to": "OGR", "asc": "1", "dist": "193", "left": "26", "x": "10712.030", "y": "5549.306", "z": "14.025", "club": "CUK", "con": "", "shotText": "Shot 3 16 ft 1 in. to green, 2 ft 2 in. to hole"}, {"n": "4", "pid": "00000", "time": "", "putt": "1", "t": "S", "prv": "n", "tee": "n", "cup": "y", "from": "OGR", "to": "hole", "asc": "1", "dist": "26", "left": "0", "x": "0", "y": "0", "z": "0", "club": "CUK", "con": "", "shotText": "Shot 4 in the hole"}]}, {"n": "4", "cNum": "13", "sc": "4", "pDay": "0", "pTot": "0", "shots": [{"n": "1", "pid": "00000", "time": "", "putt": "", "t": "S", "prv": "n", "tee": "y", "cup": "n", "from": "OTB", "to": "ERR", "asc": "1", "dist": "8104", "left": "5462", "x": "9886.570", "y": "5508.315", "z": "12.813", "club": "CIR", "con": "", "shotText": "Shot 1 225 yds to right rough, 152 yds to hole"}, {"n": "2", "pid": "00000", "time": "", "putt": "", "t": "S", "prv": "n", "tee": "n", "cup": "n", "from": "ORO", "to": "OCO", "asc": "1", "dist": "5703", "left": "385", "x": "9525.970", "y": "5198.756", "z": "14.752", "club": "CUK", "con": "", "shotText": "Shot 2 158 yds to fringe, 32 ft 1 in. to hole"}, {"n": "3", "pid": "00000", "time": "", "putt": "", "t": "S", "prv": "n", "tee": "n", "cup": "n", "from": "OCO", "to": "OGR", "asc": "1", "dist": "342", "left": "43", "x": "9525.204", "y": "5227.269", "z": "14.983", "club": "CUK", "con": "", "shotText": "Shot 3 28 ft 6 in. to green, 3 ft 7 in. to hole"}, {"n": "4", "pid": "00000", "time": "", "putt": "1", "t": "S", "prv": "n", "tee": "n", "cup": "y", "from": "OGR", "to": "hole", "asc": "1", "dist": "43", "left": "0", "x": "0", "y": "0", "z": "0", "club": "CUK", "con": "", "shotText": "Shot 4 in the hole"}]}, {"n": "5", "cNum": "14", "sc": "3", "pDay": "0", "pTot": "0", "shots": [{"n": "1", "pid": "00000", "time": "", "putt": "", "t": "S", "prv": "n", "tee": "y", "cup": "n", "from": "OTB", "to": "ELF", "asc": "1", "dist": "6540", "left": "285", "x": "9648.265", "y": "5701.347", "z": "10.695", "club": "CUK", "con": "", "shotText": "Shot 1 182 yds to left fairway, 23 ft 9 in. to hole"}, {"n": "2", "pid": "00000", "time": "", "putt": "", "t": "S", "prv": "n", "tee": "n", "cup": "n", "from": "OFW", "to": "OGR", "asc": "1", "dist": "320", "left": "31", "x": "9664.469", "y": "5680.126", "z": "10.822", "club": "CUK", "con": "", "shotText": "Shot 2 26 ft 8 in. to green, 2 ft 7 in. to hole"}, {"n": "3", "pid": "00000", "time": "", "putt": "1", "t": "S", "prv": "n", "tee": "n", "cup": "y", "from": "OGR", "to": "hole", "asc": "1", "dist": "31", "left": "0", "x": "0", "y": "0", "z": "0", "club": "CUK", "con": "", "shotText": "Shot 3 in the hole"}]}, {"n": "6", "cNum": "15", "sc": "4", "pDay": "-1", "pTot": "-1", "shots": [{"n": "1", "pid": "00000", "time": "", "putt": "", "t": "S", "prv": "n", "tee": "y", "cup": "n", "from": "OTB", "to": "ELR", "asc": "1", "dist": "10227", "left": "10195", "x": "10160.874", "y": "6511.171", "z": "13.758", "club": "CDR", "con": "", "shotText": "Shot 1 284 yds to left rough, 283 yds to hole"}, {"n": "2", "pid": "00000", "time": "", "putt": "", "t": "S", "prv": "n", "tee": "n", "cup": "n", "from": "ORO", "to": "OTO", "asc": "1", "dist": "6560", "left": "4786", "x": "10649.480", "y": "6756.361", "z": "11.258", "club": "CUK", "con": "", "shotText": "Shot 2 182 yds to tree outline, 133 yds to hole"}, {"n": "3", "pid": "00000", "time": "", "putt": "", "t": "S", "prv": "n", "tee": "n", "cup": "n", "from": "ONA", "to": "OGR", "asc": "1", "dist": "4887", "left": "672", "x": "10668.586", "y": "7163.185", "z": "11.845", "club": "CUK", "con": "", "shotText": "Shot 3 136 yds to green, 56 ft 0 in. to hole"}, {"n": "4", "pid": "00000", "time": "", "putt": "1", "t": "S", "prv": "n", "tee": "n", "cup": "y", "from": "OGR", "to": "hole", "asc": "1", "dist": "672", "left": "0", "x": "0", "y": "0", "z": "0", "club": "CUK", "con": "", "shotText": "Shot 4 in the hole"}]}, {"n": "7", "cNum": "16", "sc": "4", "pDay": "-1", "pTot": "-1", "shots": [{"n": "1", "pid": "00000", "time": "", "putt": "", "t": "S", "prv": "n", "tee": "y", "cup": "n", "from": "OTB", "to": "ERF", "asc": "1", "dist": "9566", "left": "4149", "x": "10681.818", "y": "8359.476", "z": "13.063", "club": "CFW", "con": "", "shotText": "Shot 1 266 yds to right fairway, 115 yds to hole"}, {"n": "2", "pid": "00000", "time": "", "putt": "", "t": "S", "prv": "n", "tee": "n", "cup": "n", "from": "OFW", "to": "OGR", "asc": "1", "dist": "4107", "left": "183", "x": "10351.335", "y": "8448.523", "z": "13.249", "club": "CUK", "con": "", "shotText": "Shot 2 114 yds to green, 15 ft 3 in. to hole"}, {"n": "3", "pid": "00000", "time": "", "putt": "1", "t": "S", "prv": "n", "tee": "n", "cup": "n", "from": "OGR", "to": "OGR", "asc": "1", "dist": "213", "left": "34", "x": "10341.415", "y": "8433.794", "z": "13.539", "club": "CUK", "con": "", "shotText": "Shot 3 putt 17 ft 9 in., 2 ft 10 in. to hole"}, {"n": "4", "pid": "00000", "time": "", "putt": "2", "t": "S", "prv": "n", "tee": "n", "cup": "y", "from": "OGR", "to": "hole", "asc": "1", "dist": "34", "left": "0", "x": "0", "y": "0", "z": "0", "club": "CUK", "con": "", "shotText": "Shot 4 in the hole"}]}, {"n": "8", "cNum": "17", "sc": "4", "pDay": "0", "pTot": "0", "shots": [{"n": "1", "pid": "00000", "time": "", "putt": "", "t": "S", "prv": "n", "tee": "y", "cup": "n", "from": "OTB", "to": "OGR", "asc": "1", "dist": "5831", "left": "646", "x": "9768.487", "y": "8338.269", "z": "13.212", "club": "CUK", "con": "", "shotText": "Shot 1 162 yds to green, 53 ft 10 in. to hole"}, {"n": "2", "pid": "00000", "time": "", "putt": "1", "t": "S", "prv": "n", "tee": "n", "cup": "n", "from": "OGR", "to": "OGR", "asc": "1", "dist": "710", "left": "69", "x": "9735.623", "y": "8289.049", "z": "13.934", "club": "CUK", "con": "", "shotText": "Shot 2 putt 59 ft 2 in., 5 ft 9 in. to hole"}, {"n": "3", "pid": "00000", "time": "", "putt": "2", "t": "S", "prv": "n", "tee": "n", "cup": "n", "from": "OGR", "to": "OGR", "asc": "1", "dist": "103", "left": "30", "x": "9736.741", "y": "8297.588", "z": "13.865", "club": "CUK", "con": "", "shotText": "Shot 3 putt 8 ft 7 in., 2 ft 6 in. to hole"}, {"n": "4", "pid": "00000", "time": "", "putt": "3", "t": "S", "prv": "n", "tee": "n", "cup": "y", "from": "OGR", "to": "hole", "asc": "1", "dist": "30", "left": "0", "x": "0", "y": "0", "z": "0", "club": "CUK", "con": "", "shotText": "Shot 4 in the hole"}]}, {"n": "9", "cNum": "18", "sc": "4", "pDay": "0", "pTot": "0", "shots": [{"n": "1", "pid": "00000", "time": "", "putt": "", "t": "S", "prv": "n", "tee": "y", "cup": "n", "from": "OTB", "to": "ELF", "asc": "1", "dist": "9919", "left": "7085", "x": "9855.346", "y": "9300.532", "z": "11.696", "club": "CDR", "con": "", "shotText": "Shot 1 276 yds to left fairway, 197 yds to hole"}, {"n": "2", "pid": "00000", "time": "", "putt": "", "t": "S", "prv": "n", "tee": "n", "cup": "n", "from": "OFW", "to": "ELR", "asc": "1", "dist": "6913", "left": "526", "x": "9936.511", "y": "9870.857", "z": "12.338", "club": "CUK", "con": "", "shotText": "Shot 2 192 yds to left rough, 43 ft 10 in. to hole"}, {"n": "3", "pid": "00000", "time": "", "putt": "", "t": "S", "prv": "n", "tee": "n", "cup": "n", "from": "ORO", "to": "OGR", "asc": "1", "dist": "426", "left": "114", "x": "9971.914", "y": "9872.520", "z": "13.714", "club": "CUK", "con": "", "shotText": "Shot 3 35 ft 6 in. to green, 9 ft 6 in. to hole"}, {"n": "4", "pid": "00000", "time": "", "putt": "1", "t": "S", "prv": "n", "tee": "n", "cup": "y", "from": "OGR", "to": "hole", "asc": "1", "dist": "114", "left": "0", "x": "0", "y": "0", "z": "0", "club": "CUK", "con": "", "shotText": "Shot 4 in the hole"}]}, {"n": "10", "cNum": "1", "sc": "4", "pDay": "0", "pTot": "0", "shots": [{"n": "1", "pid": "00000", "time": "", "putt": "", "t": "S", "prv": "n", "tee": "y", "cup": "n", "from": "OTB", "to": "ELF", "asc": "1", "dist": "9242", "left": "5503", "x": "11903.672", "y": "9065.737", "z": "12.714", "club": "CDR", "con": "", "shotText": "Shot 1 257 yds to left fairway, 153 yds to hole"}, {"n": "2", "pid": "00000", "time": "", "putt": "", "t": "S", "prv": "n", "tee": "n", "cup": "n", "from": "OFW", "to": "OCO", "asc": "1", "dist": "4963", "left": "694", "x": "12246.131", "y": "8833.915", "z": "14.119", "club": "CUK", "con": "", "shotText": "Shot 2 138 yds to fringe, 57 ft 10 in. to hole"}, {"n": "3", "pid": "00000", "time": "", "putt": "", "t": "S", "prv": "n", "tee": "n", "cup": "n", "from": "OCO", "to": "OGR", "asc": "1", "dist": "666", "left": "33", "x": "12301.327", "y": "8839.405", "z": "13.824", "club": "CUK", "con": "", "shotText": "Shot 3 55 ft 6 in. to green, 2 ft 9 in. to hole"}, {"n": "4", "pid": "00000", "time": "", "putt": "1", "t": "S", "prv": "n", "tee": "n", "cup": "y", "from": "OGR", "to": "hole", "asc": "1", "dist": "33", "left": "0", "x": "0", "y": "0", "z": "0", "club": "CUK", "con": "", "shotText": "Shot 4 in the hole"}]}, {"n": "11", "cNum": "2", "sc": "4", "pDay": "-1", "pTot": "-1", "shots": [{"n": "1", "pid": "00000", "time": "", "putt": "", "t": "S", "prv": "n", "tee": "y", "cup": "n", "from": "OTB", "to": "ELF", "asc": "1", "dist": "10755", "left": "7100", "x": "12893.560", "y": "7952.979", "z": "11.749", "club": "CDR", "con": "", "shotText": "Shot 1 299 yds to left fairway, 197 yds to hole"}, {"n": "2", "pid": "00000", "time": "", "putt": "", "t": "S", "prv": "n", "tee": "n", "cup": "n", "from": "OFW", "to": "OGR", "asc": "1", "dist": "7429", "left": "341", "x": "13022.780", "y": "7347.567", "z": "14.489", "club": "CUK", "con": "", "shotText": "Shot 2 206 yds to green, 28 ft 5 in. to hole"}, {"n": "3", "pid": "00000", "time": "", "putt": "1", "t": "S", "prv": "n", "tee": "n", "cup": "n", "from": "OGR", "to": "OGR", "asc": "1", "dist": "351", "left": "18", "x": "13009.697", "y": "7373.769", "z": "14.094", "club": "CUK", "con": "", "shotText": "Shot 3 putt 29 ft 3 in., 18 in. to hole"}, {"n": "4", "pid": "00000", "time": "", "putt": "2", "t": "S", "prv": "n", "tee": "n", "cup": "y", "from": "OGR", "to": "hole", "asc": "1", "dist": "18", "left": "0", "x": "0", "y": "0", "z": "0", "club": "CUK", "con": "", "shotText": "Shot 4 in the hole"}]}, {"n": "12", "cNum": "3", "sc": "3", "pDay": "-2", "pTot": "-2", "shots": [{"n": "1", "pid": "00000", "time": "", "putt": "", "t": "S", "prv": "n", "tee": "y", "cup": "n", "from": "OTB", "to": "ERF", "asc": "1", "dist": "11452", "left": "5448", "x": "12412.029", "y": "6609.270", "z": "12.822", "club": "CDR", "con": "", "shotText": "Shot 1 318 yds to right fairway, 151 yds to hole"}, {"n": "2", "pid": "00000", "time": "", "putt": "", "t": "S", "prv": "n", "tee": "n", "cup": "n", "from": "OFW", "to": "OGR", "asc": "1", "dist": "5416", "left": "34", "x": "12191.535", "y": "6215.499", "z": "14.436", "club": "CUK", "con": "", "shotText": "Shot 2 150 yds to green, 2 ft 10 in. to hole"}, {"n": "3", "pid": "00000", "time": "", "putt": "1", "t": "S", "prv": "n", "tee": "n", "cup": "y", "from": "OGR", "to": "hole", "asc": "1", "dist": "34", "left": "0", "x": "0", "y": "0", "z": "0", "club": "CUK", "con": "", "shotText": "Shot 3 in the hole"}]}, {"n": "13", "cNum": "4", "sc": "2", "pDay": "-3", "pTot": "-3", "shots": [{"n": "1", "pid": "00000", "time": "", "putt": "", "t": "S", "prv": "n", "tee": "y", "cup": "n", "from": "OTB", "to": "OGR", "asc": "1", "dist": "7078", "left": "176", "x": "12143.935", "y": "5535.267", "z": "13.130", "club": "CUK", "con": "", "shotText": "Shot 1 197 yds to green, 14 ft 8 in. to hole"}, {"n": "2", "pid": "00000", "time": "", "putt": "1", "t": "S", "prv": "n", "tee": "n", "cup": "y", "from": "OGR", "to": "hole", "asc": "1", "dist": "176", "left": "0", "x": "0", "y": "0", "z": "0", "club": "CUK", "con": "", "shotText": "Shot 2 in the hole"}]}, {"n": "14", "cNum": "5", "sc": "5", "pDay": "-3", "pTot": "-3", "shots": [{"n": "1", "pid": "00000", "time": "", "putt": "", "t": "S", "prv": "n", "tee": "y", "cup": "n", "from": "OTB", "to": "OTO", "asc": "1", "dist": "9926", "left": "10058", "x": "12791.501", "y": "5243.610", "z": "13.932", "club": "CDR", "con": "", "shotText": "Shot 1 276 yds to tree outline, 279 yds to hole"}, {"n": "2", "pid": "00000", "time": "", "putt": "", "t": "S", "prv": "n", "tee": "n", "cup": "n", "from": "ONA", "to": "ELF", "asc": "1", "dist": "1355", "left": "9143", "x": "12781.395", "y": "5356.027", "z": "15.596", "club": "CUK", "con": "", "shotText": "Shot 2 38 yds to left fairway, 254 yds to hole"}, {"n": "3", "pid": "00000", "time": "", "putt": "", "t": "S", "prv": "n", "tee": "n", "cup": "n", "from": "OFW", "to": "ERF", "asc": "1", "dist": "9499", "left": "881", "x": "13390.881", "y": "5861.088", "z": "15.315", "club": "CUK", "con": "", "shotText": "Shot 3 264 yds to right fairway, 73 ft 5 in. to hole"}, {"n": "4", "pid": "00000", "time": "", "putt": "", "t": "S", "prv": "n", "tee": "n", "cup": "n", "from": "OFW", "to": "OCO", "asc": "1", "dist": "1013", "left": "129", "x": "13314.701", "y": "5897.327", "z": "17.866", "club": "CUK", "con": "", "shotText": "Shot 4 84 ft 5 in. to fringe, 10 ft 9 in. to hole"}, {"n": "5", "pid": "00000", "time": "", "putt": "", "t": "S", "prv": "n", "tee": "n", "cup": "y", "from": "OCO", "to": "hole", "asc": "1", "dist": "129", "left": "0", "x": "0", "y": "0", "z": "0", "club": "CUK", "con": "", "shotText": "Shot 5 in the hole"}]}, {"n": "15", "cNum": "6", "sc": "4", "pDay": "-3", "pTot": "-3", "shots": [{"n": "1", "pid": "00000", "time": "", "putt": "", "t": "S", "prv": "n", "tee": "y", "cup": "n", "from": "OTB", "to": "ERF", "asc": "1", "dist": "9963", "left": "4523", "x": "13030.986", "y": "6624.473", "z": "12.489", "club": "CFW", "con": "", "shotText": "Shot 1 277 yds to right fairway, 126 yds to hole"}, {"n": "2", "pid": "00000", "time": "", "putt": "", "t": "S", "prv": "n", "tee": "n", "cup": "n", "from": "OFW", "to": "OGR", "asc": "1", "dist": "4651", "left": "163", "x": "13004.243", "y": "7011.097", "z": "13.326", "club": "CUK", "con": "", "shotText": "Shot 2 129 yds to green, 13 ft 7 in. to hole"}, {"n": "3", "pid": "00000", "time": "", "putt": "1", "t": "S", "prv": "n", "tee": "n", "cup": "n", "from": "OGR", "to": "OGR", "asc": "1", "dist": "207", "left": "40", "x": "13016.365", "y": "6998.820", "z": "12.889", "club": "CUK", "con": "", "shotText": "Shot 3 putt 17 ft 3 in., 3 ft 4 in. to hole"}, {"n": "4", "pid": "00000", "time": "", "putt": "2", "t": "S", "prv": "n", "tee": "n", "cup": "y", "from": "OGR", "to": "hole", "asc": "1", "dist": "40", "left": "0", "x": "0", "y": "0", "z": "0", "club": "CUK", "con": "", "shotText": "Shot 4 in the hole"}]}, {"n": "16", "cNum": "7", "sc": "3", "pDay": "-3", "pTot": "-3", "shots": [{"n": "1", "pid": "00000", "time": "", "putt": "", "t": "S", "prv": "n", "tee": "y", "cup": "n", "from": "OTB", "to": "OGR", "asc": "1", "dist": "6832", "left": "507", "x": "12267.932", "y": "6927.441", "z": "13.899", "club": "CUK", "con": "", "shotText": "Shot 1 190 yds to green, 42 ft 3 in. to hole"}, {"n": "2", "pid": "00000", "time": "", "putt": "1", "t": "S", "prv": "n", "tee": "n", "cup": "n", "from": "OGR", "to": "OGR", "asc": "1", "dist": "493", "left": "25", "x": "12231.229", "y": "6908.931", "z": "14.211", "club": "CUK", "con": "", "shotText": "Shot 2 putt 41 ft 1 in., 2 ft 1 in. to hole"}, {"n": "3", "pid": "00000", "time": "", "putt": "2", "t": "S", "prv": "n", "tee": "n", "cup": "y", "from": "OGR", "to": "hole", "asc": "1", "dist": "25", "left": "0", "x": "0", "y": "0", "z": "0", "club": "CUK", "con": "", "shotText": "Shot 3 in the hole"}]}, {"n": "17", "cNum": "8", "sc": "4", "pDay": "-3", "pTot": "-3", "shots": [{"n": "1", "pid": "00000", "time": "", "putt": "", "t": "S", "prv": "n", "tee": "y", "cup": "n", "from": "OTB", "to": "ERF", "asc": "1", "dist": "10471", "left": "6411", "x": "12112.855", "y": "7714.636", "z": "12.030", "club": "CDR", "con": "", "shotText": "Shot 1 291 yds to right fairway, 178 yds to hole"}, {"n": "2", "pid": "00000", "time": "", "putt": "", "t": "S", "prv": "n", "tee": "n", "cup": "n", "from": "OFW", "to": "OGR", "asc": "1", "dist": "6134", "left": "279", "x": "11823.414", "y": "8135.951", "z": "12.737", "club": "CUK", "con": "", "shotText": "Shot 2 170 yds to green, 23 ft 3 in. to hole"}, {"n": "3", "pid": "00000", "time": "", "putt": "1", "t": "S", "prv": "n", "tee": "n", "cup": "n", "from": "OGR", "to": "OGR", "asc": "1", "dist": "304", "left": "21", "x": "11811.344", "y": "8158.186", "z": "13.152", "club": "CUK", "con": "", "shotText": "Shot 3 putt 25 ft 4 in., 21 in. to hole"}, {"n": "4", "pid": "00000", "time": "", "putt": "2", "t": "S", "prv": "n", "tee": "n", "cup": "y", "from": "OGR", "to": "hole", "asc": "1", "dist": "21", "left": "0", "x": "0", "y": "0", "z": "0", "club": "CUK", "con": "", "shotText": "Shot 4 in the hole"}]}, {"n": "18", "cNum": "9", "sc": "2", "pDay": "-5", "pTot": "-5", "shots": [{"n": "1", "pid": "00000", "time": "", "putt": "", "t": "S", "prv": "n", "tee": "y", "cup": "n", "from": "OTB", "to": "ERR", "asc": "1", "dist": "10837", "left": "1169", "x": "11341.298", "y": "9196.068", "z": "11.003", "club": "CDR", "con": "", "shotText": "Shot 1 301 yds to right rough, 97 ft 5 in. to hole"}, {"n": "2", "pid": "00000", "time": "", "putt": "", "t": "S", "prv": "n", "tee": "n", "cup": "y", "from": "ORO", "to": "hole", "asc": "1", "dist": "1169", "left": "0", "x": "0", "y": "0", "z": "0", "club": "CUK", "con": "", "shotText": "Shot 2 in the hole"}]}]}, {"n": "3", "holes": [{"n": "1", "cNum": "1", "sc": "3", "pDay": "-1", "pTot": "-6", "shots": [{"n": "1", "pid": "00000", "time": "", "putt": "", "t": "S", "prv": "n", "tee": "y", "cup": "n", "from": "OTB", "to": "ERF", "asc": "1", "dist": "10192", "left": "4262", "x": "11952.227", "y": "8998.660", "z": "13.545", "club": "CDR", "con": "", "shotText": "Shot 1 283 yds to right fairway, 118 yds to hole"}, {"n": "2", "pid": "00000", "time": "", "putt": "", "t": "S", "prv": "n", "tee": "n", "cup": "n", "from": "OFW", "to": "OGR", "asc": "1", "dist": "4136", "left": "158", "x": "12262.054", "y": "8847.584", "z": "14.296", "club": "CUK", "con": "", "shotText": "Shot 2 115 yds to green, 13 ft 2 in. to hole"}, {"n": "3", "pid": "00000", "time": "", "putt": "1", "t": "S", "prv": "n", "tee": "n", "cup": "y", "from": "OGR", "to": "hole", "asc": "1", "dist": "158", "left": "0", "x": "0", "y": "0", "z": "0", "club": "CUK", "con": "", "shotText": "Shot 3 in the hole"}]}, {"n": "2", "cNum": "2", "sc": "4", "pDay": "-2", "pTot": "-7", "shots": [{"n": "1", "pid": "00000", "time": "", "putt": "", "t": "S", "prv": "n", "tee": "y", "cup": "n", "from": "OTB", "to": "ELR", "asc": "1", "dist": "10493", "left": "7623", "x": "12904.465", "y": "7983.624", "z": "12.010", "club": "CDR", "con": "", "shotText": "Shot 1 291 yds to left rough, 212 yds to hole"}, {"n": "2", "pid": "00000", "time": "", "putt": "", "t": "S", "prv": "n", "tee": "n", "cup": "n", "from": "ORO", "to": "ERF", "asc": "1", "dist": "6740", "left": "914", "x": "13026.924", "y": "7435.451", "z": "11.807", "club": "CUK", "con": "", "shotText": "Shot 2 187 yds to right fairway, 76 ft 2 in. to hole"}, {"n": "3", "pid": "00000", "time": "", "putt": "", "t": "S", "prv": "n", "tee": "n", "cup": "n", "from": "OFW", "to": "OGR", "asc": "1", "dist": "879", "left": "34", "x": "13022.532", "y": "7362.344", "z": "14.175", "club": "CUK", "con": "", "shotText": "Shot 3 73 ft 3 in. to green, 2 ft 10 in. to hole"}, {"n": "4", "pid": "00000", "time": "", "putt": "1", "t": "S", "prv": "n", "tee": "n", "cup": "y", "from": "OGR", "to": "hole", "asc": "1", "dist": "34", "left": "0", "x": "0", "y": "0", "z": "0", "club": "CUK", "con": "", "shotText": "Shot 4 in the hole"}]}, {"n": "3", "cNum": "3", "sc": "4", "pDay": "-2", "pTot": "-7", "shots": [{"n": "1", "pid": "00000", "time": "", "putt": "", "t": "S", "prv": "n", "tee": "y", "cup": "n", "from": "OTB", "to": "ONA", "asc": "1", "dist": "9844", "left": "7293", "x": "12461.156", "y": "6744.210", "z": "12.534", "club": "CDR", "con": "", "shotText": "Shot 1 273 yds to native area, 203 yds to hole"}, {"n": "2", "pid": "00000", "time": "", "putt": "", "t": "S", "prv": "n", "tee": "n", "cup": "n", "from": "ONA", "to": "OGR", "asc": "1", "dist": "7367", "left": "131", "x": "12170.660", "y": "6203.398", "z": "14.729", "club": "CUK", "con": "", "shotText": "Shot 2 205 yds to green, 10 ft 11 in. to hole"}, {"n": "3", "pid": "00000", "time": "", "putt": "1", "t": "S", "prv": "n", "tee": "n", "cup": "n", "from": "OGR", "to": "OGR", "asc": "1", "dist": "148", "left": "14", "x": "12164.325", "y": "6213.966", "z": "14.495", "club": "CUK", "con": "", "shotText": "Shot 3 putt 12 ft 4 in., 14 in. to hole"}, {"n": "4", "pid": "00000", "time": "", "putt": "2", "t": "S", "prv": "n", "tee": "n", "cup": "y", "from": "OGR", "to": "hole", "asc": "1", "dist": "14", "left": "0", "x": "0", "y": "0", "z": "0", "club": "CUK", "con": "", "shotText": "Shot 4 in the hole"}]}, {"n": "4", "cNum": "4", "sc": "3", "pDay": "-2", "pTot": "-7", "shots": [{"n": "1", "pid": "00000", "time": "", "putt": "", "t": "S", "prv": "n", "tee": "y", "cup": "n", "from": "OTB", "to": "OGR", "asc": "1", "dist": "6424", "left": "119", "x": "12168.571", "y": "5553.057", "z": "12.667", "club": "CUK", "con": "", "shotText": "Shot 1 178 yds to green, 9 ft 11 in. to hole"}, {"n": "2", "pid": "00000", "time": "", "putt": "1", "t": "S", "prv": "n", "tee": "n", "cup": "n", "from": "OGR", "to": "OGR", "asc": "1", "dist": "138", "left": "16", "x": "12165.965", "y": "5564.236", "z": "12.384", "club": "CUK", "con": "", "shotText": "Shot 2 putt 11 ft 6 in., 16 in. to hole"}, {"n": "3", "pid": "00000", "time": "", "putt": "2", "t": "S", "prv": "n", "tee": "n", "cup": "y", "from": "OGR", "to": "hole", "asc": "1", "dist": "16", "left": "0", "x": "0", "y": "0", "z": "0", "club": "CUK", "con": "", "shotText": "Shot 3 in the hole"}]}, {"n": "5", "cNum": "5", "sc": "4", "pDay": "-3", "pTot": "-8", "shots": [{"n": "1", "pid": "00000", "time": "", "putt": "", "t": "S", "prv": "n", "tee": "y", "cup": "n", "from": "OTB", "to": "ERF", "asc": "1", "dist": "10569", "left": "9066", "x": "12826.204", "y": "5378.385", "z": "15.384", "club": "CDR", "con": "", "shotText": "Shot 1 294 yds to right fairway, 252 yds to hole"}, {"n": "2", "pid": "00000", "time": "", "putt": "", "t": "S", "prv": "n", "tee": "n", "cup": "n", "from": "OFW", "to": "OGR", "asc": "1", "dist": "8831", "left": "343", "x": "13347.741", "y": "5897.579", "z": "18.473", "club": "CUK", "con": "", "shotText": "Shot 2 245 yds to green, 28 ft 7 in. to hole"}, {"n": "3", "pid": "00000", "time": "", "putt": "1", "t": "S", "prv": "n", "tee": "n", "cup": "n", "from": "OGR", "to": "OGR", "asc": "1", "dist": "333", "left": "26", "x": "13348.793", "y": "5925.327", "z": "18.692", "club": "CUK", "con": "", "shotText": "Shot 3 putt 27 ft 9 in., 2 ft 2 in. to hole"}, {"n": "4", "pid": "00000", "time": "", "putt": "2", "t": "S", "prv": "n", "tee": "n", "cup": "y", "from": "OGR", "to": "hole", "asc": "1", "dist": "26", "left": "0", "x": "0", "y": "0", "z": "0", "club": "CUK", "con": "", "shotText": "Shot 4 in the hole"}]}, {"n": "6", "cNum": "6", "sc": "4", "pDay": "-3", "pTot": "-8", "shots": [{"n": "1", "pid": "00000", "time": "", "putt": "", "t": "S", "prv": "n", "tee": "y", "cup": "n", "from": "OTB", "to": "OST", "asc": "1", "dist": "8453", "left": "6161", "x": "13143.700", "y": "6539.330", "z": "9.366", "club": "CFW", "con": "", "shotText": "Shot 1 235 yds to fairway bunker, 171 yds to hole"}, {"n": "2", "pid": "00000", "time": "", "putt": "", "t": "S", "prv": "n", "tee": "n", "cup": "n", "from": "OST", "to": "ELR", "asc": "1", "dist": "5617", "left": "888", "x": "12970.301", "y": "6974.141", "z": "11.743", "club": "CUK", "con": "", "shotText": "Shot 2 156 yds to left rough, 74 ft 0 in. to hole"}, {"n": "3", "pid": "00000", "time": "", "putt": "", "t": "S", "prv": "n", "tee": "n", "cup": "n", "from": "ORO", "to": "OGR", "asc": "1", "dist": "903", "left": "40", "x": "13015.080", "y": "7034.598", "z": "13.482", "club": "CUK", "con": "", "shotText": "Shot 3 75 ft 3 in. to green, 3 ft 4 in. to hole"}, {"n": "4", "pid": "00000", "time": "", "putt": "1", "t": "S", "prv": "n", "tee": "n", "cup": "y", "from": "OGR", "to": "hole", "asc": "1", "dist": "40", "left": "0", "x": "0", "y": "0", "z": "0", "club": "CUK", "con": "", "shotText": "Shot 4 in the hole"}]}, {"n": "7", "cNum": "7", "sc": "3", "pDay": "-3", "pTot": "-8", "shots": [{"n": "1", "pid": "00000", "time": "", "putt": "", "t": "S", "prv": "n", "tee": "y", "cup": "n", "from": "OTB", "to": "OCO", "asc": "1", "dist": "7510", "left": "220", "x": "12209.443", "y": "6920.916", "z": "14.158", "club": "CUK", "con": "", "shotText": "Shot 1 209 yds to fringe, 18 ft 4 in. to hole"}, {"n": "2", "pid": "00000", "time": "", "putt": "", "t": "S", "prv": "n", "tee": "n", "cup": "n", "from": "OCO", "to": "OGR", "asc": "1", "dist": "218", "left": "9", "x": "12225.942", "y": "6928.433", "z": "13.824", "club": "CUK", "con": "", "shotText": "Shot 2 18 ft 2 in. to green, 9 in. to hole"}, {"n": "3", "pid": "00000", "time": "", "putt": "1", "t": "S", "prv": "n", "tee": "n", "cup": "y", "from": "OGR", "to": "hole", "asc": "1", "dist": "9", "left": "0", "x": "0", "y": "0", "z": "0", "club": "CUK", "con": "", "shotText": "Shot 3 in the hole"}]}, {"n": "8", "cNum": "8", "sc": "4", "pDay": "-3", "pTot": "-8", "shots": [{"n": "1", "pid": "00000", "time": "", "putt": "", "t": "S", "prv": "n", "tee": "y", "cup": "n", "from": "OTB", "to": "ERF", "asc": "1", "dist": "9847", "left": "6772", "x": "12116.082", "y": "7665.077", "z": "11.607", "club": "CFW", "con": "", "shotText": "Shot 1 274 yds to right fairway, 188 yds to hole"}, {"n": "2", "pid": "00000", "time": "", "putt": "", "t": "S", "prv": "n", "tee": "n", "cup": "n", "from": "OFW", "to": "OGR", "asc": "1", "dist": "7190", "left": "416", "x": "11792.338", "y": "8169.287", "z": "13.729", "club": "CUK", "con": "", "shotText": "Shot 2 200 yds to green, 34 ft 8 in. to hole"}, {"n": "3", "pid": "00000", "time": "", "putt": "1", "t": "S", "prv": "n", "tee": "n", "cup": "n", "from": "OGR", "to": "OGR", "asc": "1", "dist": "357", "left": "64", "x": "11807.683", "y": "8143.832", "z": "12.967", "club": "CUK", "con": "", "shotText": "Shot 3 putt 29 ft 9 in., 5 ft 4 in. to hole"}, {"n": "4", "pid": "00000", "time": "", "putt": "2", "t": "S", "prv": "n", "tee": "n", "cup": "y", "from": "OGR", "to": "hole", "asc": "1", "dist": "64", "left": "0", "x": "0", "y": "0", "z": "0", "club": "CUK", "con": "", "shotText": "Shot 4 in the hole"}]}, {"n": "9", "cNum": "9", "sc": "4", "pDay": "-3", "pTot": "-8", "shots": [{"n": "1", "pid": "00000", "time": "", "putt": "", "t": "S", "prv": "n", "tee": "y", "cup": "n", "from": "OTB", "to": "ERR", "asc": "1", "dist": "10848", "left": "1217", "x": "11348.621", "y": "9197.225", "z": "10.909", "club": "CDR", "con": "", "shotText": "Shot 1 301 yds to right rough, 34 yds to hole"}, {"n": "2", "pid": "00000", "time": "", "putt": "", "t": "S", "prv": "n", "tee": "n", "cup": "n", "from": "ORO", "to": "OGR", "asc": "1", "dist": "1272", "left": "133", "x": "11287.648", "y": "9283.887", "z": "13.000", "club": "CUK", "con": "", "shotText": "Shot 2 35 yds to green, 11 ft 1 in. to hole"}, {"n": "3", "pid": "00000", "time": "", "putt": "1", "t": "S", "prv": "n", "tee": "n", "cup": "n", "from": "OGR", "to": "OGR", "asc": "1", "dist": "147", "left": "10", "x": "11281.800", "y": "9273.080", "z": "13.132", "club": "CUK", "con": "", "shotText": "Shot 3 putt 12 ft 3 in., 10 in. to hole"}, {"n": "4", "pid": "00000", "time": "", "putt": "2", "t": "S", "prv": "n", "tee": "n", "cup": "y", "from": "OGR", "to": "hole", "asc": "1", "dist": "10", "left": "0", "x": "0", "y": "0", "z": "0", "club": "CUK", "con": "", "shotText": "Shot 4 in the hole"}]}, {"n": "10", "cNum": "10", "sc": "4", "pDay": "-3", "pTot": "-8", "shots": [{"n": "1", "pid": "00000", "time": "", "putt": "", "t": "S", "prv": "n", "tee": "y", "cup": "n", "from": "OTB", "to": "ERF", "asc": "1", "dist": "9700", "left": "5518", "x": "10881.089", "y": "8337.581", "z": "12.133", "club": "CFW", "con": "", "shotText": "Shot 1 269 yds to right fairway, 153 yds to hole"}, {"n": "2", "pid": "00000", "time": "", "putt": "", "t": "S", "prv": "n", "tee": "n", "cup": "n", "from": "OFW", "to": "OCO", "asc": "1", "dist": "5239", "left": "315", "x": "10946.637", "y": "7905.962", "z": "12.301", "club": "CUK", "con": "", "shotText": "Shot 2 146 yds to fringe, 26 ft 3 in. to hole"}, {"n": "3", "pid": "00000", "time": "", "putt": "", "t": "S", "prv": "n", "tee": "n", "cup": "n", "from": "OCO", "to": "OGR", "asc": "1", "dist": "316", "left": "2", "x": "10962.716", "y": "7885.092", "z": "12.954", "club": "CUK", "con": "", "shotText": "Shot 3 26 ft 4 in. to green, 2 in. to hole"}, {"n": "4", "pid": "00000", "time": "", "putt": "1", "t": "S", "prv": "n", "tee": "n", "cup": "y", "from": "OGR", "to": "hole", "asc": "1", "dist": "2", "left": "0", "x": "0", "y": "0", "z": "0", "club": "CUK", "con": "", "shotText": "Shot 4 in the hole"}]}, {"n": "11", "cNum": "11", "sc": "5", "pDay": "-2", "pTot": "-7", "shots": [{"n": "1", "pid": "00000", "time": "", "putt": "", "t": "S", "prv": "n", "tee": "y", "cup": "n", "from": "OTB", "to": "ERR", "asc": "1", "dist": "8586", "left": "7429", "x": "11226.860", "y": "7045.105", "z": "9.970", "club": "CFW", "con": "", "shotText": "Shot 1 239 yds to right rough, 206 yds to hole"}, {"n": "2", "pid": "00000", "time": "", "putt": "", "t": "S", "prv": "n", "tee": "n", "cup": "n", "from": "ORO", "to": "ERR", "asc": "1", "dist": "7176", "left": "470", "x": "11484.664", "y": "6505.511", "z": "13.809", "club": "CUK", "con": "", "shotText": "Shot 2 199 yds to right rough, 39 ft 2 in. to hole"}, {"n": "3", "pid": "00000", "time": "", "putt": "", "t": "S", "prv": "n", "tee": "n", "cup": "n", "from": "ORO", "to": "OGR", "asc": "1", "dist": "364", "left": "119", "x": "11514.961", "y": "6506.644", "z": "14.585", "club": "CUK", "con": "", "shotText": "Shot 3 30 ft 4 in. to green, 9 ft 11 in. to hole"}, {"n": "4", "pid": "00000", "time": "", "putt": "1", "t": "S", "prv": "n", "tee": "n", "cup": "n", "from": "OGR", "to": "OGR", "asc": "1", "dist": "126", "left": "4", "x": "11524.296", "y": "6501.886", "z": "14.731", "club": "CUK", "con": "", "shotText": "Shot 4 putt 10 ft 6 in., 4 in. to hole"}, {"n": "5", "pid": "00000", "time": "", "putt": "2", "t": "S", "prv": "n", "tee": "n", "cup": "y", "from": "OGR", "to": "hole", "asc": "1", "dist": "4", "left": "0", "x": "0", "y": "0", "z": "0", "club": "CUK", "con": "", "shotText": "Shot 5 in the hole"}]}, {"n": "12", "cNum": "12", "sc": "4", "pDay": "-2", "pTot": "-7", "shots": [{"n": "1", "pid": "00000", "time": "", "putt": "", "t": "S", "prv": "n", "tee": "y", "cup": "n", "from": "OTB", "to": "ERF", "asc": "1", "dist": "10440", "left": "4719", "x": "11087.352", "y": "5741.502", "z": "11.115", "club": "CDR", "con": "", "shotText": "Shot 1 290 yds to right fairway, 131 yds to hole"}, {"n": "2", "pid": "00000", "time": "", "putt": "", "t": "S", "prv": "n", "tee": "n", "cup": "n", "from": "OFW", "to": "OGR", "asc": "1", "dist": "4563", "left": "171", "x": "10739.768", "y": "5587.258", "z": "14.111", "club": "CUK", "con": "", "shotText": "Shot 2 127 yds to green, 14 ft 3 in. to hole"}, {"n": "3", "pid": "00000", "time": "", "putt": "1", "t": "S", "prv": "n", "tee": "n", "cup": "n", "from": "OGR", "to": "OGR", "asc": "1", "dist": "195", "left": "28", "x": "10723.564", "y": "5585.819", "z": "14.301", "club": "CUK", "con": "", "shotText": "Shot 3 putt 16 ft 3 in., 2 ft 4 in. to hole"}, {"n": "4", "pid": "00000", "time": "", "putt": "2", "t": "S", "prv": "n", "tee": "n", "cup": "y", "from": "OGR", "to": "hole", "asc": "1", "dist": "28", "left": "0", "x": "0", "y": "0", "z": "0", "club": "CUK", "con": "", "shotText": "Shot 4 in the hole"}]}, {"n": "13", "cNum": "13", "sc": "5", "pDay": "-1", "pTot": "-6", "shots": [{"n": "1", "pid": "00000", "time": "", "putt": "", "t": "S", "prv": "n", "tee": "y", "cup": "n", "from": "OTB", "to": "ERF", "asc": "1", "dist": "8641", "left": "4988", "x": "9854.302", "y": "5474.006", "z": "12.994", "club": "CIR", "con": "", "shotText": "Shot 1 240 yds to right fairway, 139 yds to hole"}, {"n": "2", "pid": "00000", "time": "", "putt": "", "t": "S", "prv": "n", "tee": "n", "cup": "n", "from": "OFW", "to": "OGR", "asc": "1", "dist": "4626", "left": "612", "x": "9540.515", "y": "5250.040", "z": "15.150", "club": "CUK", "con": "", "shotText": "Shot 2 129 yds to green, 51 ft 0 in. to hole"}, {"n": "3", "pid": "00000", "time": "", "putt": "1", "t": "S", "prv": "n", "tee": "n", "cup": "n", "from": "OGR", "to": "OGR", "asc": "1", "dist": "580", "left": "57", "x": "9538.493", "y": "5201.756", "z": "14.620", "club": "CUK", "con": "", "shotText": "Shot 3 putt 48 ft 4 in., 4 ft 9 in. to hole"}, {"n": "4", "pid": "00000", "time": "", "putt": "2", "t": "S", "prv": "n", "tee": "n", "cup": "n", "from": "OGR", "to": "OGR", "asc": "1", "dist": "75", "left": "22", "x": "9542.315", "y": "5196.833", "z": "14.582", "club": "CUK", "con": "", "shotText": "Shot 4 putt 6 ft 3 in., 22 in. to hole"}, {"n": "5", "pid": "00000", "time": "", "putt": "3", "t": "S", "prv": "n", "tee": "n", "cup": "y", "from": "OGR", "to": "hole", "asc": "1", "dist": "22", "left": "0", "x": "0", "y": "0", "z": "0", "club": "CUK", "con": "", "shotText": "Shot 5 in the hole"}]}, {"n": "14", "cNum": "14", "sc": "3", "pDay": "-1", "pTot": "-6", "shots": [{"n": "1", "pid": "00000", "time": "", "putt": "", "t": "S", "prv": "n", "tee": "y", "cup": "n", "from": "OTB", "to": "ELF", "asc": "1", "dist": "6735", "left": "697", "x": "9648.112", "y": "5714.314", "z": "11.645", "club": "CUK", "con": "", "shotText": "Shot 1 187 yds to left fairway, 58 ft 1 in. to hole"}, {"n": "2", "pid": "00000", "time": "", "putt": "", "t": "S", "prv": "n", "tee": "n", "cup": "n", "from": "OFW", "to": "OGR", "asc": "1", "dist": "713", "left": "16", "x": "9684.559", "y": "5667.387", "z": "10.975", "club": "CUK", "con": "", "shotText": "Shot 2 59 ft 5 in. to green, 16 in. to hole"}, {"n": "3", "pid": "00000", "time": "", "putt": "1", "t": "S", "prv": "n", "tee": "n", "cup": "y", "from": "OGR", "to": "hole", "asc": "1", "dist": "16", "left": "0", "x": "0", "y": "0", "z": "0", "club": "CUK", "con": "", "shotText": "Shot 3 in the hole"}]}, {"n": "15", "cNum": "15", "sc": "5", "pDay": "-1", "pTot": "-6", "shots": [{"n": "1", "pid": "00000", "time": "", "putt": "", "t": "S", "prv": "n", "tee": "y", "cup": "n", "from": "OTB", "to": "ELF", "asc": "1", "dist": "11279", "left": "8645", "x": "10245.135", "y": "6569.211", "z": "13.844", "club": "CDR", "con": "", "shotText": "Shot 1 313 yds to left fairway, 240 yds to hole"}, {"n": "2", "pid": "00000", "time": "", "putt": "", "t": "S", "prv": "n", "tee": "n", "cup": "n", "from": "OFW", "to": "ELF", "asc": "1", "dist": "9238", "left": "595", "x": "10694.627", "y": "7194.201", "z": "13.596", "club": "CUK", "con": "", "shotText": "Shot 2 257 yds to left fairway, 49 ft 7 in. to hole"}, {"n": "3", "pid": "00000", "time": "", "putt": "", "t": "S", "prv": "n", "tee": "n", "cup": "n", "from": "OFW", "to": "OGR", "asc": "1", "dist": "692", "left": "95", "x": "10666.315", "y": "7143.995", "z": "11.807", "club": "CUK", "con": "", "shotText": "Shot 3 57 ft 8 in. to green, 7 ft 11 in. to hole"}, {"n": "4", "pid": "00000", "time": "", "putt": "1", "t": "S", "prv": "n", "tee": "n", "cup": "n", "from": "OGR", "to": "OGR", "asc": "1", "dist": "103", "left": "5", "x": "10671.821", "y": "7150.622", "z": "11.893", "club": "CUK", "con": "", "shotText": "Shot 4 putt 8 ft 7 in., 5 in. to hole"}, {"n": "5", "pid": "00000", "time": "", "putt": "2", "t": "S", "prv": "n", "tee": "n", "cup": "y", "from": "OGR", "to": "hole", "asc": "1", "dist": "5", "left": "0", "x": "0", "y": "0", "z": "0", "club": "CUK", "con": "", "shotText": "Shot 5 in the hole"}]}, {"n": "16", "cNum": "16", "sc": "4", "pDay": "-1", "pTot": "-6", "shots": [{"n": "1", "pid": "00000", "time": "", "putt": "", "t": "S", "prv": "n", "tee": "y", "cup": "n", "from": "OTB", "to": "ELF", "asc": "1", "dist": "9255", "left": "4245", "x": "10649.334", "y": "8331.405", "z": "13.005", "club": "CFW", "con": "", "shotText": "Shot 1 257 yds to left fairway, 118 yds to hole"}, {"n": "2", "pid": "00000", "time": "", "putt": "", "t": "S", "prv": "n", "tee": "n", "cup": "n", "from": "OFW", "to": "OGR", "asc": "1", "dist": "4622", "left": "454", "x": "10286.184", "y": "8459.828", "z": "13.902", "club": "CUK", "con": "", "shotText": "Shot 2 128 yds to green, 37 ft 10 in. to hole"}, {"n": "3", "pid": "00000", "time": "", "putt": "1", "t": "S", "prv": "n", "tee": "n", "cup": "n", "from": "OGR", "to": "OGR", "asc": "1", "dist": "529", "left": "93", "x": "10329.963", "y": "8464.665", "z": "13.571", "club": "CUK", "con": "", "shotText": "Shot 3 putt 44 ft 1 in., 7 ft 9 in. to hole"}, {"n": "4", "pid": "00000", "time": "", "putt": "2", "t": "S", "prv": "n", "tee": "n", "cup": "y", "from": "OGR", "to": "hole", "asc": "1", "dist": "93", "left": "0", "x": "0", "y": "0", "z": "0", "club": "CUK", "con": "", "shotText": "Shot 4 in the hole"}]}, {"n": "17", "cNum": "17", "sc": "3", "pDay": "-1", "pTot": "-6", "shots": [{"n": "1", "pid": "00000", "time": "", "putt": "", "t": "S", "prv": "n", "tee": "y", "cup": "n", "from": "OTB", "to": "OGR", "asc": "1", "dist": "5446", "left": "530", "x": "9787.360", "y": "8350.677", "z": "12.613", "club": "CUK", "con": "", "shotText": "Shot 1 151 yds to green, 44 ft 2 in. to hole"}, {"n": "2", "pid": "00000", "time": "", "putt": "1", "t": "S", "prv": "n", "tee": "n", "cup": "n", "from": "OGR", "to": "OGR", "asc": "1", "dist": "498", "left": "32", "x": "9767.096", "y": "8314.506", "z": "13.598", "club": "CUK", "con": "", "shotText": "Shot 2 putt 41 ft 6 in., 2 ft 8 in. to hole"}, {"n": "3", "pid": "00000", "time": "", "putt": "2", "t": "S", "prv": "n", "tee": "n", "cup": "y", "from": "OGR", "to": "hole", "asc": "1", "dist": "32", "left": "0", "x": "0", "y": "0", "z": "0", "club": "CUK", "con": "", "shotText": "Shot 3 in the hole"}]}, {"n": "18", "cNum": "18", "sc": "5", "pDay": "0", "pTot": "-5", "shots": [{"n": "1", "pid": "00000", "time": "", "putt": "", "t": "S", "prv": "n", "tee": "y", "cup": "n", "from": "OTB", "to": "ERF", "asc": "1", "dist": "9262", "left": "7173", "x": "9892.804", "y": "9249.031", "z": "12.638", "club": "CFW", "con": "", "shotText": "Shot 1 257 yds to right fairway, 199 yds to hole"}, {"n": "2", "pid": "00000", "time": "", "putt": "", "t": "S", "prv": "n", "tee": "n", "cup": "n", "from": "OFW", "to": "ERF", "asc": "1", "dist": "7873", "left": "696", "x": "9989.616", "y": "9897.915", "z": "13.503", "club": "CUK", "con": "", "shotText": "Shot 2 219 yds to right fairway, 58 ft 0 in. to hole"}, {"n": "3", "pid": "00000", "time": "", "putt": "", "t": "S", "prv": "n", "tee": "n", "cup": "n", "from": "OFW", "to": "OGR", "asc": "1", "dist": "600", "left": "96", "x": "9983.930", "y": "9848.244", "z": "13.557", "club": "CUK", "con": "", "shotText": "Shot 3 50 ft 0 in. to green, 8 ft 0 in. to hole"}, {"n": "4", "pid": "00000", "time": "", "putt": "1", "t": "S", "prv": "n", "tee": "n", "cup": "n", "from": "OGR", "to": "OGR", "asc": "1", "dist": "134", "left": "34", "x": "9983.272", "y": "9837.106", "z": "13.574", "club": "CUK", "con": "", "shotText": "Shot 4 putt 11 ft 2 in., 2 ft 10 in. to hole"}, {"n": "5", "pid": "00000", "time": "", "putt": "2", "t": "S", "prv": "n", "tee": "n", "cup": "y", "from": "OGR", "to": "hole", "asc": "1", "dist": "34", "left": "0", "x": "0", "y": "0", "z": "0", "club": "CUK", "con": "", "shotText": "Shot 5 in the hole"}]}]}, {"n": "4", "holes": [{"n": "1", "cNum": "1", "sc": "4", "pDay": "0", "pTot": "-5", "shots": [{"n": "1", "pid": "00000", "time": "", "putt": "", "t": "S", "prv": "n", "tee": "y", "cup": "n", "from": "OTB", "to": "ERF", "asc": "1", "dist": "10234", "left": "4405", "x": "11971.903", "y": "9017.317", "z": "12.635", "club": "CDR", "con": "", "shotText": "Shot 1 284 yds to right fairway, 122 yds to hole"}, {"n": "2", "pid": "00000", "time": "", "putt": "", "t": "S", "prv": "n", "tee": "n", "cup": "n", "from": "OFW", "to": "OGR", "asc": "1", "dist": "4549", "left": "482", "x": "12291.060", "y": "8812.699", "z": "14.389", "club": "CUK", "con": "", "shotText": "Shot 2 126 yds to green, 40 ft 2 in. to hole"}, {"n": "3", "pid": "00000", "time": "", "putt": "1", "t": "S", "prv": "n", "tee": "n", "cup": "n", "from": "OGR", "to": "OGR", "asc": "1", "dist": "438", "left": "45", "x": "12299.845", "y": "8848.126", "z": "13.767", "club": "CUK", "con": "", "shotText": "Shot 3 putt 36 ft 6 in., 3 ft 9 in. to hole"}, {"n": "4", "pid": "00000", "time": "", "putt": "2", "t": "S", "prv": "n", "tee": "n", "cup": "y", "from": "OGR", "to": "hole", "asc": "1", "dist": "45", "left": "0", "x": "0", "y": "0", "z": "0", "club": "CUK", "con": "", "shotText": "Shot 4 in the hole"}]}, {"n": "2", "cNum": "2", "sc": "6", "pDay": "1", "pTot": "-4", "shots": [{"n": "1", "pid": "00000", "time": "", "putt": "", "t": "S", "prv": "n", "tee": "y", "cup": "n", "from": "OTB", "to": "OST", "asc": "1", "dist": "9763", "left": "8514", "x": "12897.560", "y": "8052.500", "z": "11.586", "club": "CDR", "con": "", "shotText": "Shot 1 271 yds to fairway bunker, 237 yds to hole"}, {"n": "2", "pid": "00000", "time": "", "putt": "", "t": "S", "prv": "n", "tee": "n", "cup": "n", "from": "OST", "to": "ELR", "asc": "1", "dist": "2418", "left": "6120", "x": "12948.476", "y": "7857.576", "z": "10.756", "club": "CUK", "con": "", "shotText": "Shot 2 67 yds to left rough, 170 yds to hole"}, {"n": "3", "pid": "00000", "time": "", "putt": "", "t": "S", "prv": "n", "tee": "n", "cup": "n", "from": "ORO", "to": "OGR", "asc": "1", "dist": "5798", "left": "533", "x": "13026.398", "y": "7380.766", "z": "13.821", "club": "CUK", "con": "", "shotText": "Shot 3 161 yds to green, 44 ft 5 in. to hole"}, {"n": "4", "pid": "00000", "time": "", "putt": "1", "t": "S", "prv": "n", "tee": "n", "cup": "n", "from": "OGR", "to": "OGR", "asc": "1", "dist": "482", "left": "51", "x": "12998.175", "y": "7352.211", "z": "14.115", "club": "CUK", "con": "", "shotText": "Shot 4 putt 40 ft 2 in., 4 ft 3 in. to hole"}, {"n": "5", "pid": "00000", "time": "", "putt": "2", "t": "S", "prv": "n", "tee": "n", "cup": "n", "from": "OGR", "to": "OGR", "asc": "1", "dist": "87", "left": "39", "x": "12991.266", "y": "7349.945", "z": "14.071", "club": "CUK", "con": "", "shotText": "Shot 5 putt 7 ft 3 in., 3 ft 3 in. to hole"}, {"n": "6", "pid": "00000", "time": "", "putt": "3", "t": "S", "prv": "n", "tee": "n", "cup": "y", "from": "OGR", "to": "hole", "asc": "1", "dist": "39", "left": "0", "x": "0", "y": "0", "z": "0", "club": "CUK", "con": "", "shotText": "Shot 6 in the hole"}]}, {"n": "3", "cNum": "3", "sc": "4", "pDay": "1", "pTot": "-4", "shots": [{"n": "1", "pid": "00000", "time": "", "putt": "", "t": "S", "prv": "n", "tee": "y", "cup": "n", "from": "OTB", "to": "ELR", "asc": "1", "dist": "10306", "left": "6245", "x": "12530.233", "y": "6630.911", "z": "11.220", "club": "CDR", "con": "", "shotText": "Shot 1 286 yds to left rough, 173 yds to hole"}, {"n": "2", "pid": "00000", "time": "", "putt": "", "t": "S", "prv": "n", "tee": "n", "cup": "n", "from": "ORO", "to": "OGR", "asc": "1", "dist": "6522", "left": "282", "x": "12182.507", "y": "6213.227", "z": "14.513", "club": "CUK", "con": "", "shotText": "Shot 2 181 yds to green, 23 ft 6 in. to hole"}, {"n": "3", "pid": "00000", "time": "", "putt": "1", "t": "S", "prv": "n", "tee": "n", "cup": "n", "from": "OGR", "to": "OGR", "asc": "1", "dist": "293", "left": "17", "x": "12194.270", "y": "6234.594", "z": "14.247", "club": "CUK", "con": "", "shotText": "Shot 3 putt 24 ft 5 in., 17 in. to hole"}, {"n": "4", "pid": "00000", "time": "", "putt": "2", "t": "S", "prv": "n", "tee": "n", "cup": "y", "from": "OGR", "to": "hole", "asc": "1", "dist": "17", "left": "0", "x": "0", "y": "0", "z": "0", "club": "CUK", "con": "", "shotText": "Shot 4 in the hole"}]}, {"n": "4", "cNum": "4", "sc": "2", "pDay": "0", "pTot": "-5", "shots": [{"n": "1", "pid": "00000", "time": "", "putt": "", "t": "S", "prv": "n", "tee": "y", "cup": "n", "from": "OTB", "to": "OGR", "asc": "1", "dist": "6585", "left": "52", "x": "12187.608", "y": "5545.896", "z": "12.858", "club": "CUK", "con": "", "shotText": "Shot 1 183 yds to green, 4 ft 4 in. to hole"}, {"n": "2", "pid": "00000", "time": "", "putt": "1", "t": "S", "prv": "n", "tee": "n", "cup": "y", "from": "OGR", "to": "hole", "asc": "1", "dist": "52", "left": "0", "x": "0", "y": "0", "z": "0", "club": "CUK", "con": "", "shotText": "Shot 2 in the hole"}]}, {"n": "5", "cNum": "5", "sc": "4", "pDay": "-1", "pTot": "-6", "shots": [{"n": "1", "pid": "00000", "time": "", "putt": "", "t": "S", "prv": "n", "tee": "y", "cup": "n", "from": "OTB", "to": "ERR", "asc": "1", "dist": "10366", "left": "9110", "x": "12818.379", "y": "5316.977", "z": "15.486", "club": "CDR", "con": "", "shotText": "Shot 1 288 yds to right rough, 253 yds to hole"}, {"n": "2", "pid": "00000", "time": "", "putt": "", "t": "S", "prv": "n", "tee": "n", "cup": "n", "from": "ORO", "to": "ELF", "asc": "1", "dist": "8618", "left": "509", "x": "13295.465", "y": "5853.747", "z": "16.049", "club": "CUK", "con": "", "shotText": "Shot 2 239 yds to left fairway, 42 ft 5 in. to hole"}, {"n": "3", "pid": "00000", "time": "", "putt": "", "t": "S", "prv": "n", "tee": "n", "cup": "n", "from": "OFW", "to": "OGR", "asc": "1", "dist": "542", "left": "39", "x": "13331.875", "y": "5880.442", "z": "18.055", "club": "CUK", "con": "", "shotText": "Shot 3 45 ft 2 in. to green, 3 ft 3 in. to hole"}, {"n": "4", "pid": "00000", "time": "", "putt": "1", "t": "S", "prv": "n", "tee": "n", "cup": "y", "from": "OGR", "to": "hole", "asc": "1", "dist": "39", "left": "0", "x": "0", "y": "0", "z": "0", "club": "CUK", "con": "", "shotText": "Shot 4 in the hole"}]}, {"n": "6", "cNum": "6", "sc": "4", "pDay": "-1", "pTot": "-6", "shots": [{"n": "1", "pid": "00000", "time": "", "putt": "", "t": "S", "prv": "n", "tee": "y", "cup": "n", "from": "OTB", "to": "ERF", "asc": "1", "dist": "10255", "left": "4890", "x": "13044.764", "y": "6664.191", "z": "12.386", "club": "CFW", "con": "", "shotText": "Shot 1 285 yds to right fairway, 136 yds to hole"}, {"n": "2", "pid": "00000", "time": "", "putt": "", "t": "S", "prv": "n", "tee": "n", "cup": "n", "from": "OFW", "to": "OGR", "asc": "1", "dist": "4475", "left": "450", "x": "13010.057", "y": "7035.520", "z": "13.580", "club": "CUK", "con": "", "shotText": "Shot 2 124 yds to green, 37 ft 6 in. to hole"}, {"n": "3", "pid": "00000", "time": "", "putt": "1", "t": "S", "prv": "n", "tee": "n", "cup": "n", "from": "OGR", "to": "OGR", "asc": "1", "dist": "473", "left": "30", "x": "12992.699", "y": "7070.922", "z": "14.756", "club": "CUK", "con": "", "shotText": "Shot 3 putt 39 ft 5 in., 2 ft 6 in. to hole"}, {"n": "4", "pid": "00000", "time": "", "putt": "2", "t": "S", "prv": "n", "tee": "n", "cup": "y", "from": "OGR", "to": "hole", "asc": "1", "dist": "30", "left": "0", "x": "0", "y": "0", "z": "0", "club": "CUK", "con": "", "shotText": "Shot 4 in the hole"}]}, {"n": "7", "cNum": "7", "sc": "4", "pDay": "0", "pTot": "-5", "shots": [{"n": "1", "pid": "00000", "time": "", "putt": "", "t": "S", "prv": "n", "tee": "y", "cup": "n", "from": "OTB", "to": "ELR", "asc": "1", "dist": "6278", "left": "307", "x": "12306.500", "y": "6936.581", "z": "12.855", "club": "CUK", "con": "", "shotText": "Shot 1 174 yds to left rough, 25 ft 7 in. to hole"}, {"n": "2", "pid": "00000", "time": "", "putt": "", "t": "S", "prv": "n", "tee": "n", "cup": "n", "from": "ORO", "to": "OGR", "asc": "1", "dist": "266", "left": "41", "x": "12284.604", "y": "6939.795", "z": "13.485", "club": "CUK", "con": "", "shotText": "Shot 2 22 ft 2 in. to green, 3 ft 5 in. to hole"}, {"n": "3", "pid": "00000", "time": "", "putt": "1", "t": "S", "prv": "n", "tee": "n", "cup": "n", "from": "OGR", "to": "OGR", "asc": "1", "dist": "55", "left": "15", "x": "12280.619", "y": "6942.048", "z": "13.531", "club": "CUK", "con": "", "shotText": "Shot 3 putt 4 ft 7 in., 15 in. to hole"}, {"n": "4", "pid": "00000", "time": "", "putt": "2", "t": "S", "prv": "n", "tee": "n", "cup": "y", "from": "OGR", "to": "hole", "asc": "1", "dist": "15", "left": "0", "x": "0", "y": "0", "z": "0", "club": "CUK", "con": "", "shotText": "Shot 4 in the hole"}]}, {"n": "8", "cNum": "8", "sc": "5", "pDay": "1", "pTot": "-4", "shots": [{"n": "1", "pid": "00000", "time": "", "putt": "", "t": "S", "prv": "n", "tee": "y", "cup": "n", "from": "OTB", "to": "ERF", "asc": "1", "dist": "9896", "left": "7086", "x": "12084.417", "y": "7674.630", "z": "10.695", "club": "CFW", "con": "", "shotText": "Shot 1 275 yds to right fairway, 197 yds to hole"}, {"n": "2", "pid": "00000", "time": "", "putt": "", "t": "S", "prv": "n", "tee": "n", "cup": "n", "from": "OFW", "to": "EG6", "asc": "1", "dist": "6568", "left": "627", "x": "11773.053", "y": "8124.783", "z": "8.660", "club": "CUK", "con": "", "shotText": "Shot 2 182 yds to left green side bunker, 52 ft 3 in. to hole"}, {"n": "3", "pid": "00000", "time": "", "putt": "", "t": "S", "prv": "n", "tee": "n", "cup": "n", "from": "OGS", "to": "OGR", "asc": "1", "dist": "787", "left": "158", "x": "11776.124", "y": "8190.040", "z": "14.433", "club": "CUK", "con": "", "shotText": "Shot 3 65 ft 7 in. to green, 13 ft 2 in. to hole"}, {"n": "4", "pid": "00000", "time": "", "putt": "1", "t": "S", "prv": "n", "tee": "n", "cup": "n", "from": "OGR", "to": "OGR", "asc": "1", "dist": "185", "left": "29", "x": "11774.925", "y": "8174.712", "z": "14.083", "club": "CUK", "con": "", "shotText": "Shot 4 putt 15 ft 5 in., 2 ft 5 in. to hole"}, {"n": "5", "pid": "00000", "time": "", "putt": "2", "t": "S", "prv": "n", "tee": "n", "cup": "y", "from": "OGR", "to": "hole", "asc": "1", "dist": "29", "left": "0", "x": "0", "y": "0", "z": "0", "club": "CUK", "con": "", "shotText": "Shot 5 in the hole"}]}, {"n": "9", "cNum": "9", "sc": "3", "pDay": "0", "pTot": "-5", "shots": [{"n": "1", "pid": "00000", "time": "", "putt": "", "t": "S", "prv": "n", "tee": "y", "cup": "n", "from": "OTB", "to": "ELR", "asc": "1", "dist": "11079", "left": "240", "x": "11279.60", "y": "9195.84", "z": "12.55", "club": "CDR", "con": "", "shotText": "Shot 1 308 yds to left rough, 20 ft 0 in. to hole"}, {"n": "2", "pid": "00000", "time": "", "putt": "", "t": "S", "prv": "n", "tee": "n", "cup": "n", "from": "ORO", "to": "OGR", "asc": "1", "dist": "260", "left": "23", "x": "11290.499", "y": "9214.512", "z": "13.293", "club": "CUK", "con": "", "shotText": "Shot 2 21 ft 8 in. to green, 23 in. to hole"}, {"n": "3", "pid": "00000", "time": "", "putt": "1", "t": "S", "prv": "n", "tee": "n", "cup": "y", "from": "OGR", "to": "hole", "asc": "1", "dist": "23", "left": "0", "x": "0", "y": "0", "z": "0", "club": "CUK", "con": "", "shotText": "Shot 3 in the hole"}]}, {"n": "10", "cNum": "10", "sc": "4", "pDay": "0", "pTot": "-5", "shots": [{"n": "1", "pid": "00000", "time": "", "putt": "", "t": "S", "prv": "n", "tee": "y", "cup": "n", "from": "OTB", "to": "ERF", "asc": "1", "dist": "10595", "left": "5668", "x": "10844.897", "y": "8283.132", "z": "12.066", "club": "CDR", "con": "", "shotText": "Shot 1 294 yds to right fairway, 157 yds to hole"}, {"n": "2", "pid": "00000", "time": "", "putt": "", "t": "S", "prv": "n", "tee": "n", "cup": "n", "from": "OFW", "to": "OGR", "asc": "1", "dist": "5425", "left": "289", "x": "10965.815", "y": "7847.495", "z": "13.643", "club": "CUK", "con": "", "shotText": "Shot 2 151 yds to green, 24 ft 1 in. to hole"}, {"n": "3", "pid": "00000", "time": "", "putt": "1", "t": "S", "prv": "n", "tee": "n", "cup": "n", "from": "OGR", "to": "OGR", "asc": "1", "dist": "277", "left": "17", "x": "10957.729", "y": "7825.909", "z": "14.032", "club": "CUK", "con": "", "shotText": "Shot 3 putt 23 ft 1 in., 17 in. to hole"}, {"n": "4", "pid": "00000", "time": "", "putt": "2", "t": "S", "prv": "n", "tee": "n", "cup": "y", "from": "OGR", "to": "hole", "asc": "1", "dist": "17", "left": "0", "x": "0", "y": "0", "z": "0", "club": "CUK", "con": "", "shotText": "Shot 4 in the hole"}]}, {"n": "11", "cNum": "11", "sc": "4", "pDay": "0", "pTot": "-5", "shots": [{"n": "1", "pid": "00000", "time": "", "putt": "", "t": "S", "prv": "n", "tee": "y", "cup": "n", "from": "OTB", "to": "ERR", "asc": "1", "dist": "10493", "left": "5048", "x": "11281.951", "y": "6895.082", "z": "11.311", "club": "CDR", "con": "", "shotText": "Shot 1 291 yds to right rough, 140 yds to hole"}, {"n": "2", "pid": "00000", "time": "", "putt": "", "t": "S", "prv": "n", "tee": "n", "cup": "n", "from": "ORO", "to": "OGR", "asc": "1", "dist": "5558", "left": "513", "x": "11524.380", "y": "6500.428", "z": "14.741", "club": "CUK", "con": "", "shotText": "Shot 2 154 yds to green, 42 ft 9 in. to hole"}, {"n": "3", "pid": "00000", "time": "", "putt": "1", "t": "S", "prv": "n", "tee": "n", "cup": "n", "from": "OGR", "to": "OGR", "asc": "1", "dist": "538", "left": "21", "x": "11506.474", "y": "6541.485", "z": "13.932", "club": "CUK", "con": "", "shotText": "Shot 3 putt 44 ft 10 in., 21 in. to hole"}, {"n": "4", "pid": "00000", "time": "", "putt": "2", "t": "S", "prv": "n", "tee": "n", "cup": "y", "from": "OGR", "to": "hole", "asc": "1", "dist": "21", "left": "0", "x": "0", "y": "0", "z": "0", "club": "CUK", "con": "", "shotText": "Shot 4 in the hole"}]}, {"n": "12", "cNum": "12", "sc": "4", "pDay": "0", "pTot": "-5", "shots": [{"n": "1", "pid": "00000", "time": "", "putt": "", "t": "S", "prv": "n", "tee": "y", "cup": "n", "from": "OTB", "to": "ERR", "asc": "1", "dist": "9726", "left": "5779", "x": "11109.900", "y": "5784.056", "z": "11.785", "club": "CDR", "con": "", "shotText": "Shot 1 270 yds to right rough, 161 yds to hole"}, {"n": "2", "pid": "00000", "time": "", "putt": "", "t": "S", "prv": "n", "tee": "n", "cup": "n", "from": "ORO", "to": "ELF", "asc": "1", "dist": "6149", "left": "369", "x": "10668.850", "y": "5523.181", "z": "14.301", "club": "CUK", "con": "", "shotText": "Shot 2 171 yds to left fairway, 30 ft 9 in. to hole"}, {"n": "3", "pid": "00000", "time": "", "putt": "", "t": "S", "prv": "n", "tee": "n", "cup": "n", "from": "OFW", "to": "OGR", "asc": "1", "dist": "378", "left": "6", "x": "10697.422", "y": "5536.351", "z": "13.985", "club": "CUK", "con": "", "shotText": "Shot 3 31 ft 6 in. to green, 6 in. to hole"}, {"n": "4", "pid": "00000", "time": "", "putt": "1", "t": "S", "prv": "n", "tee": "n", "cup": "y", "from": "OGR", "to": "hole", "asc": "1", "dist": "6", "left": "0", "x": "0", "y": "0", "z": "0", "club": "CUK", "con": "", "shotText": "Shot 4 in the hole"}]}, {"n": "13", "cNum": "13", "sc": "3", "pDay": "-1", "pTot": "-6", "shots": [{"n": "1", "pid": "00000", "time": "", "putt": "", "t": "S", "prv": "n", "tee": "y", "cup": "n", "from": "OTB", "to": "ERF", "asc": "1", "dist": "8536", "left": "4444", "x": "9866.101", "y": "5477.196", "z": "12.953", "club": "CFW", "con": "", "shotText": "Shot 1 237 yds to right fairway, 123 yds to hole"}, {"n": "2", "pid": "00000", "time": "", "putt": "", "t": "S", "prv": "n", "tee": "n", "cup": "n", "from": "OFW", "to": "OGR", "asc": "1", "dist": "4416", "left": "32", "x": "9568.670", "y": "5260.465", "z": "14.249", "club": "CUK", "con": "", "shotText": "Shot 2 123 yds to green, 2 ft 8 in. to hole"}, {"n": "3", "pid": "00000", "time": "", "putt": "1", "t": "S", "prv": "n", "tee": "n", "cup": "y", "from": "OGR", "to": "hole", "asc": "1", "dist": "32", "left": "0", "x": "0", "y": "0", "z": "0", "club": "CUK", "con": "", "shotText": "Shot 3 in the hole"}]}, {"n": "14", "cNum": "14", "sc": "4", "pDay": "0", "pTot": "-5", "shots": [{"n": "1", "pid": "00000", "time": "", "putt": "", "t": "S", "prv": "n", "tee": "y", "cup": "n", "from": "OTB", "to": "ELR", "asc": "1", "dist": "6914", "left": "519", "x": "9656.247", "y": "5722.856", "z": "12.427", "club": "CUK", "con": "", "shotText": "Shot 1 192 yds to left rough, 43 ft 3 in. to hole"}, {"n": "2", "pid": "00000", "time": "", "putt": "", "t": "S", "prv": "n", "tee": "n", "cup": "n", "from": "ORO", "to": "OGR", "asc": "1", "dist": "598", "left": "74", "x": "9703.190", "y": "5706.229", "z": "10.985", "club": "CUK", "con": "", "shotText": "Shot 2 49 ft 10 in. to green, 6 ft 2 in. to hole"}, {"n": "3", "pid": "00000", "time": "", "putt": "1", "t": "S", "prv": "n", "tee": "n", "cup": "n", "from": "OGR", "to": "OGR", "asc": "1", "dist": "101", "left": "24", "x": "9695.567", "y": "5709.875", "z": "11.105", "club": "CUK", "con": "", "shotText": "Shot 3 putt 8 ft 5 in., 2 ft 0 in. to hole"}, {"n": "4", "pid": "00000", "time": "", "putt": "2", "t": "S", "prv": "n", "tee": "n", "cup": "y", "from": "OGR", "to": "hole", "asc": "1", "dist": "24", "left": "0", "x": "0", "y": "0", "z": "0", "club": "CUK", "con": "", "shotText": "Shot 4 in the hole"}]}, {"n": "15", "cNum": "15", "sc": "4", "pDay": "-1", "pTot": "-6", "shots": [{"n": "1", "pid": "00000", "time": "", "putt": "", "t": "S", "prv": "n", "tee": "y", "cup": "n", "from": "OTB", "to": "ERF", "asc": "1", "dist": "11037", "left": "9138", "x": "10253.334", "y": "6505.680", "z": "14.159", "club": "CDR", "con": "", "shotText": "Shot 1 307 yds to right fairway, 254 yds to hole"}, {"n": "2", "pid": "00000", "time": "", "putt": "", "t": "S", "prv": "n", "tee": "n", "cup": "n", "from": "OFW", "to": "OGR", "asc": "1", "dist": "9662", "left": "610", "x": "10707.694", "y": "7170.405", "z": "13.008", "club": "CUK", "con": "", "shotText": "Shot 2 268 yds to green, 50 ft 10 in. to hole"}, {"n": "3", "pid": "00000", "time": "", "putt": "1", "t": "S", "prv": "n", "tee": "n", "cup": "n", "from": "OGR", "to": "OGR", "asc": "1", "dist": "590", "left": "50", "x": "10700.624", "y": "7121.781", "z": "13.325", "club": "CUK", "con": "", "shotText": "Shot 3 putt 49 ft 2 in., 4 ft 2 in. to hole"}, {"n": "4", "pid": "00000", "time": "", "putt": "2", "t": "S", "prv": "n", "tee": "n", "cup": "y", "from": "OGR", "to": "hole", "asc": "1", "dist": "50", "left": "0", "x": "0", "y": "0", "z": "0", "club": "CUK", "con": "", "shotText": "Shot 4 in the hole"}]}, {"n": "16", "cNum": "16", "sc": "4", "pDay": "-1", "pTot": "-6", "shots": [{"n": "1", "pid": "00000", "time": "", "putt": "", "t": "S", "prv": "n", "tee": "y", "cup": "n", "from": "OTB", "to": "OST", "asc": "1", "dist": "9547", "left": "3889", "x": "10600.700", "y": "8338.260", "z": "10.566", "club": "CFW", "con": "", "shotText": "Shot 1 265 yds to fairway bunker, 108 yds to hole"}, {"n": "2", "pid": "00000", "time": "", "putt": "", "t": "S", "prv": "n", "tee": "n", "cup": "n", "from": "OST", "to": "OGR", "asc": "1", "dist": "4047", "left": "180", "x": "10291.789", "y": "8473.466", "z": "14.321", "club": "CUK", "con": "", "shotText": "Shot 2 112 yds to green, 15 ft 0 in. to hole"}, {"n": "3", "pid": "00000", "time": "", "putt": "1", "t": "S", "prv": "n", "tee": "n", "cup": "n", "from": "OGR", "to": "OGR", "asc": "1", "dist": "231", "left": "49", "x": "10302.205", "y": "8457.242", "z": "13.721", "club": "CUK", "con": "", "shotText": "Shot 3 putt 19 ft 3 in., 4 ft 1 in. to hole"}, {"n": "4", "pid": "00000", "time": "", "putt": "2", "t": "S", "prv": "n", "tee": "n", "cup": "y", "from": "OGR", "to": "hole", "asc": "1", "dist": "49", "left": "0", "x": "0", "y": "0", "z": "0", "club": "CUK", "con": "", "shotText": "Shot 4 in the hole"}]}, {"n": "17", "cNum": "17", "sc": "3", "pDay": "-1", "pTot": "-6", "shots": [{"n": "1", "pid": "00000", "time": "", "putt": "", "t": "S", "prv": "n", "tee": "y", "cup": "n", "from": "OTB", "to": "EG6", "asc": "1", "dist": "6375", "left": "518", "x": "9732.025", "y": "8263.484", "z": "9.747", "club": "CUK", "con": "", "shotText": "Shot 1 177 yds to left green side bunker, 43 ft 2 in. to hole"}, {"n": "2", "pid": "00000", "time": "", "putt": "", "t": "S", "prv": "n", "tee": "n", "cup": "n", "from": "OGS", "to": "OGR", "asc": "1", "dist": "573", "left": "55", "x": "9709.524", "y": "8305.386", "z": "13.813", "club": "CUK", "con": "", "shotText": "Shot 2 47 ft 9 in. to green, 4 ft 7 in. to hole"}, {"n": "3", "pid": "00000", "time": "", "putt": "1", "t": "S", "prv": "n", "tee": "n", "cup": "y", "from": "OGR", "to": "hole", "asc": "1", "dist": "55", "left": "0", "x": "0", "y": "0", "z": "0", "club": "CUK", "con": "", "shotText": "Shot 3 in the hole"}]}, {"n": "18", "cNum": "18", "sc": "3", "pDay": "-2", "pTot": "-7", "shots": [{"n": "1", "pid": "00000", "time": "", "putt": "", "t": "S", "prv": "n", "tee": "y", "cup": "n", "from": "OTB", "to": "ELF", "asc": "1", "dist": "10450", "left": "6448", "x": "9833.389", "y": "9350.226", "z": "12.319", "club": "CFW", "con": "", "shotText": "Shot 1 290 yds to left fairway, 179 yds to hole"}, {"n": "2", "pid": "00000", "time": "", "putt": "", "t": "S", "prv": "n", "tee": "n", "cup": "n", "from": "OFW", "to": "OGR", "asc": "1", "dist": "6278", "left": "186", "x": "9946.061", "y": "9861.111", "z": "13.624", "club": "CUK", "con": "", "shotText": "Shot 2 174 yds to green, 15 ft 6 in. to hole"}, {"n": "3", "pid": "00000", "time": "", "putt": "1", "t": "S", "prv": "n", "tee": "n", "cup": "y", "from": "OGR", "to": "hole", "asc": "1", "dist": "186", "left": "0", "x": "0", "y": "0", "z": "0", "club": "CUK", "con": "", "shotText": "Shot 3 in the hole"}]}]}]}}